Workbook

Sheet out_language_fr
A1: 0
A2: 语言总表
A3: 索引ID | B3: 内容 | C3: 中文，用于导出（不要在原表简转繁）
A4: 1*1 | B4: stack_error,n_list
A5: id | B5: text
A6: int | B6: string
A7: id | B7: text
A8: int | B8: ori_string
A9: 100001 | B9: Modèle du texte pour le e-mail du backend T | C9: T后台纯文本邮件模板 | D9: =VLOOKUP(A9,Sheet1!A:B,2,0) | E9: D列为简中语言表的文本，若CD列中文本冲突，以D列为准
A10: 100002 | B10: Modèle du texte + récompense pour le e-mail du backend T | C10: T后台文本+奖励邮件模板 | D10: =VLOOKUP(A10,Sheet1!A:B,2,0)
A11: 100003 | B11: Guerrier Solitaire | C11: 菇勇者 | D11: =VLOOKUP(A11,Sheet1!A:B,2,0)
A12: 100004 | B12: Combattant | C12: 战士 | D12: =VLOOKUP(A12,Sheet1!A:B,2,0)
A13: 100005 | B13: Archer | C13: 弓箭手 | D13: =VLOOKUP(A13,Sheet1!A:B,2,0)
A14: 100006 | B14: Mage | C14: 法师 | D14: =VLOOKUP(A14,Sheet1!A:B,2,0)
A15: 100007 | B15: Épéiste | C15: 剑客 | D15: =VLOOKUP(A15,Sheet1!A:B,2,0)
A16: 100008 | B16: Samouraï à la Hache | C16: 斧武士 | D16: =VLOOKUP(A16,Sheet1!A:B,2,0)
A17: 100009 | B17: Tireur d'Ombre | C17: 狙影猎手 | D17: =VLOOKUP(A17,Sheet1!A:B,2,0)
A18: 100010 | B18: Arbalétrier du Vent | C18: 风弩手 | D18: =VLOOKUP(A18,Sheet1!A:B,2,0)
A19: 100011 | B19: Guérisseur | C19: 愈灵师 | D19: =VLOOKUP(A19,Sheet1!A:B,2,0)
A20: 100012 | B20: Sorcier des Esprits | C20: 魔灵士 | D20: =VLOOKUP(A20,Sheet1!A:B,2,0)
A21: 100013 | B21: Grand Maître d'Épée | C21: 大剑士 | D21: =VLOOKUP(A21,Sheet1!A:B,2,0)
... A4418: 200094 | B4418: Voulez-vous consommer %s | C4418: 是否消耗%s | D4418: =VLOOKUP(A4418,Sheet1!A:B,2,0)
A4419: 700024509 | B4419: Voulez-vous consommer ##1*##2 | C4419: 是否消耗##1*##2
A4420: 200095 | B4420: Refonte | C4420: 重铸 | D4420: =VLOOKUP(A4420,Sheet1!A:B,2,0)
A4421: 200096 | B4421: <b><color=#544231>Objectif du jalon : Les points de jalon atteignent</color> <color=#ab630e>%s</color></b> | C4421: <b><color=#544231>里程目标：里程值达到</color><color=#ab630e>%s</color></b> | D4421: =VLOOKUP(A4421,Sheet1!A:B,2,0)
A4422: 200097 | B4422: <b><color=#544231>Objectif du jalon : Passer le donjon d’événement</color> <color=#ab630e>%s</color></b> | C4422: <b><color=#544231>里程目标：通关活动副本</color><color=#ab630e>%s</color></b> | D4422: =VLOOKUP(A4422,Sheet1!A:B,2,0)
A4423: 200098 | B4423: Effet de déploiement : %s | C4423: 上阵效果：%s | D4423: =VLOOKUP(A4423,Sheet1!A:B,2,0)
A4424: 200099 | B4424: PV & ATQ & DEF basiques +%s% | C4424: 基础生命&攻击&防御+%s% | D4424: =VLOOKUP(A4424,Sheet1!A:B,2,0)
A4425: 200100 | B4425: Aucun Acolyte disponible pour l’équiper | C4425: 没有可以装配的同伴 | D4425: =VLOOKUP(A4425,Sheet1!A:B,2,0)
A4426: 200101 | B4426: Débloquer | C4426: 解锁 | D4426: =VLOOKUP(A4426,Sheet1!A:B,2,0)
A4427: 200102 | B4427: Horaire de l'événement : %s | C4427: 活动时间：%s | D4427: =VLOOKUP(A4427,Sheet1!A:B,2,0)
A4428: 200103 | B4428: Attributs basiques | C4428: 基础属性 | D4428: =VLOOKUP(A4428,Sheet1!A:B,2,0)
A4429: 200104 | B4429: Attributs avancés | C4429: 高级属性 | D4429: =VLOOKUP(A4429,Sheet1!A:B,2,0)
A4430: 200105 | B4430: Attributs finaux | C4430: 最终属性 | D4430: =VLOOKUP(A4430,Sheet1!A:B,2,0)
A4431: 200106 | B4431: Niveau insuffisant | C4431: 等级不足 | D4431: =VLOOKUP(A4431,Sheet1!A:B,2,0)
... A5530: 201239 | B5530: Les opérations sont trop fréquentes, veuillez réessayer plus tard ! | C5530: 操作过于频繁，请稍后再试 | D5530: =VLOOKUP(A5530,Sheet1!A:B,2,0)
A5531: 201240 | B5531: Jeton stratégique | C5531: 策略筹码 | D5531: =VLOOKUP(A5531,Sheet1!A:B,2,0) | E5531: 4. Le garage d'une monture permet d'acquérir des points de modification qui augmentent au fil du temps. Améliorez le niveau de modification de la monture correspondante pour gagner des bonus d'attributs supplémentaires, et le niveau de modification de la monture spécifiée peut aussi être augmenté via les guides de modification.\n 5. Stationnez votre monture pendant un certain temps pour Aperçu des récompenses d'aventure supplémentaires, et les récompenses varient en fonction des montures.\n6. Au-delà de 8 heures de garage continu, aucun gain n'est généré, veuillez récupérer vos gains régulièrement.
A5532: 201241 | B5532: Valeur stratégique | C5532: 策略值 | D5532: =VLOOKUP(A5532,Sheet1!A:B,2,0) | E5532: 7. Une fois que les 12 heures de garage quotidien sont atteintes pour une monture, le taux de gain en Pièces de Parking de Champignon est divisé par 2 et vous ne gagnez plus de points de modification ni de récompenses d'aventure.\n8. Vous recevez 5% du gain total en Pièces de Parking de Champignon de toutes les montures stationnées sur les places, ce qui n'influencent pas sur les gains du propriétaire de la monture.\n9. Vous pouvez choisir de piller les montures stationnées sur les places des autres, chaque monture ne peut être pillée qu'une seule fois, un pillage réussi met fin de force au garage en cours et le butin de Pièces de Parking de Champignon est partagé équitablement entre les pillards.
A5533: 201242 | B5533: Affection de Porky | C5533: 猪猪侠好感 | D5533: =VLOOKUP(A5533,Sheet1!A:B,2,0) | E5533: 10. Chaque pillage réussi permet d'accumuler une couche de débuff au combat, plus la couche est élevée, plus les attributs de combat sont réduits, une couche est déduite toutes les 30 minutes, le temps sera réinitialisé lorsque la couche augmente.\n11. En cas d'échec du pillage, vous ne pouvez pas lancer à nouveau le pillage pour un certain temps. Plus la couche de débuff au combat est nombreuse, plus la période de la pénalisation est longue.\n12. Si vous effectuez le pillage sur votre propre place, le débuff au combat ne s'accumule pas et vous ne subissez aucune pénalisation en cas d'échec.
A5534: 201243 | B5534: Gluten Épicé | C5534: 辣条 | D5534: =VLOOKUP(A5534,Sheet1!A:B,2,0)
A5535: 201244 | B5535: Chapeau de Hamburger | C5535: 汉堡帽子 | D5535: =VLOOKUP(A5535,Sheet1!A:B,2,0)
A5536: 201245 | B5536: Lunettes d'Omelette | C5536: 煎蛋眼镜 | D5536: =VLOOKUP(A5536,Sheet1!A:B,2,0)
A5537: 201246 | B5537: Chapeau de Sorcière Mystérieux | C5537: 幽幽巫帽 | D5537: =VLOOKUP(A5537,Sheet1!A:B,2,0)
A5538: 201247 | B5538: Chant du Dragon | C5538: 龙吟双声 | D5538: =VLOOKUP(A5538,Sheet1!A:B,2,0)
A5539: 201248 | B5539: Réseau Universel | C5539: 天下罗网 | D5539: =VLOOKUP(A5539,Sheet1!A:B,2,0)
A5540: 201249 | B5540: Formation d'Étoiles de Tarot | C5540: 塔罗星阵 | D5540: =VLOOKUP(A5540,Sheet1!A:B,2,0)
A5541: 201250 | B5541: Poppy | C5541: 波比 | D5541: =VLOOKUP(A5541,Sheet1!A:B,2,0)
A5542: 201252 | B5542: Épée Céleste | C5542: 开天宝剑 | D5542: =VLOOKUP(A5542,Sheet1!A:B,2,0)
A5543: 201253 | B5543: Âme Martiale Aléatoire Rouge 1 | C5543: 随机红色武魂1 | D5543: =VLOOKUP(A5543,Sheet1!A:B,2,0)
A5544: 201254 | B5544: Porte des Fleurs | C5544: 花门 | D5544: =VLOOKUP(A5544,Sheet1!A:B,2,0)
A5545: 201255 | B5545: Arche | C5545: 拱门 | D5545: =VLOOKUP(A5545,Sheet1!A:B,2,0)
... A11264: 14210003 | B11264: ATQ +2 000 points | C11264: 攻击力增加2000点 | D11264: =VLOOKUP(A11264,Sheet1!A:B,2,0)
A11265: 14210004 | B11265: Bonus d’ATQ +50% | C11265: 攻击加成50% | D11265: =VLOOKUP(A11265,Sheet1!A:B,2,0) | F11265: 建议删除，社区那边玩家反馈说有歧义
A11266: 14310001 | B11266: Un petit nombre de coupons d'accélération | C11266: 少量加速券 | D11266: =VLOOKUP(A11266,Sheet1!A:B,2,0)
A11267: 14310002 | B11267: Un sac de coupons d'accélération | C11267: 一袋加速券 | D11267: =VLOOKUP(A11267,Sheet1!A:B,2,0)
A11268: 14310003 | B11268: Une boîte de coupons d'accélération | C11268: 一箱加速券 | D11268: =VLOOKUP(A11268,Sheet1!A:B,2,0)
A11269: 14310004 | B11269: Un camion de coupons d'accélération | C11269: 一车加速券 | D11269: =VLOOKUP(A11269,Sheet1!A:B,2,0)
A11270: 14310005 | B11270: Un petit nombre de pièces d'or | C11270: 少量金币 | D11270: =VLOOKUP(A11270,Sheet1!A:B,2,0)
A11271: 14310006 | B11271: Un sac de pièces d'or | C11271: 一袋金币 | D11271: =VLOOKUP(A11271,Sheet1!A:B,2,0)
A11272: 14310007 | B11272: Une boîte de pièces d'or | C11272: 一箱金币 | D11272: =VLOOKUP(A11272,Sheet1!A:B,2,0)
A11273: 14310008 | B11273: Un camion de pièces d'or | C11273: 一车金币 | D11273: =VLOOKUP(A11273,Sheet1!A:B,2,0)
A11274: 14310009 | B11274: Un petit nombre de ressorts à durée illimitée | C11274: 少量无限时发条 | D11274: =VLOOKUP(A11274,Sheet1!A:B,2,0)
A11275: 14310010 | B11275: Un sac de ressorts à durée illimitée | C11275: 一袋无限时发条 | D11275: =VLOOKUP(A11275,Sheet1!A:B,2,0)
A11276: 14310011 | B11276: Une boîte de ressorts à durée illimitée | C11276: 一箱无限时发条 | D11276: =VLOOKUP(A11276,Sheet1!A:B,2,0)
A11277: 14310012 | B11277: Un camion de ressorts à durée illimitée | C11277: 一车无限时发条 | D11277: =VLOOKUP(A11277,Sheet1!A:B,2,0)
... A13203: 999300208 | B13203: Indice %s | C13203: 线索 %s | D13203: =VLOOKUP(A13203,Sheet1!A:B,2,0)
A13204: 700000002 | C13204: 悲伤蛙称号，不需要文字 | D13204: =VLOOKUP(A13204,Sheet1!A:B,2,0)
A13205: 202255 | B13205: Cher joueur, vous avez des récompenses d'e-mail non récupérées qui vont expirer. Veuillez les vérifier ! | C13205: 亲爱的菇菇，您有未领取的到期邮件奖励，菇妹已为您保管，请注意查收哟~ | D13205: =VLOOKUP(A13205,Sheet1!A:B,2,0)
A13206: 600000001 | B13206: Bonus de Dégâts d'Acolyte | C13206: 同伴伤害加成 | D13206: =VLOOKUP(A13206,Sheet1!A:B,2,0)
A13207: 202101 | B13207: Débloqué à l'étage %s | C13207: 达到%s层解锁 | D13207: =VLOOKUP(A13207,Sheet1!A:B,2,0)
A13208: 700000001 | B13208: Toutes les ##1 secondes, inflige des dégâts de zone égaux à ##2% de l'ATQ normale actuelle et plonge la cible dans le statut de confusion : à chaque attaque de la cible (ATQ normale, combo, contre-attaque, compétence), elle subit des dégâts supplémentaires égaux à ##3% de ses dégâts d'ATQ normale actuels pendant ##4s. (Cette compétence est déclenchée immédiatement une fois au début du combat) | C13208: 每隔##1秒造成##2%当前普攻范围伤害，并使目标陷入混乱状态：目标每次攻击（普攻，连击，反击，技能）时会额外对自身造成##3%目标当前普攻伤害，持续##4秒。（战斗开始后立刻释放一次） | D13208: =VLOOKUP(A13208,Sheet1!A:B,2,0)
A13209: 400080 | B13209: À trouver | C13209: 待寻找 | D13209: =VLOOKUP(A13209,Sheet1!A:B,2,0)
A13210: 400534 | B13210: Le raid sera débloqué après 3 jours d'ouverture de la difficulté actuelle et avec la DEF de 10 à la fin du niveau. | C13210: 当前难度开放满3天且通关时防御值为10解锁扫荡 | D13210: =VLOOKUP(A13210,Sheet1!A:B,2,0)
A13211: 400535 | B13211: Le raid sera débloqué une fois le niveau actuel terminé avec la DEF de 10. | C13211: 通关当前难度且防御值为10时解锁扫荡 | D13211: =VLOOKUP(A13211,Sheet1!A:B,2,0)
A13212: 400536 | B13212: Affection de Pepe : | C13212: 悲伤蛙好感： | D13212: =VLOOKUP(A13212,Sheet1!A:B,2,0)
A13213: 400537 | B13213: Univers de Pepe Triste | C13213: 悲伤蛙宇宙 | D13213: =VLOOKUP(A13213,Sheet1!A:B,2,0)
A13214: 400538 | B13214: Cache-cache avec Pepe | C13214: 躲蛙蛙 | D13214: =VLOOKUP(A13214,Sheet1!A:B,2,0)
A13215: 400539 | B13215: Protéger Pepe Détendu | C13215: 守卫佛系蛙 | D13215: =VLOOKUP(A13215,Sheet1!A:B,2,0)
A13216: 400540 | B13216: Pepe Insomniaque | C13216: 失眠蛙 | D13216: =VLOOKUP(A13216,Sheet1!A:B,2,0)
... A14632: 301877 | B14632: 1. Chaque attaque consomme 1 Activité.\n2. Lors de l'attaque, les joueurs entrent dans la file d'attente d'attaque après être arrivés à la parcelle cible et défient les défenseurs dans l'ordre.\n2. Si l'attaque réussit et que l'attaquant bat tous les défenseurs, la propriété de la parcelle change.\n3. Si l'attaque échoue et que le joueur meurt, le joueur sera ressuscité au point de résurrection défini après 10 minutes (le quartier général et le bastion Niv. 3 peuvent être utilisés comme points de résurrection). | C14632: 1、每次进攻，都需消耗1点行动力\n2、发起进攻操作，玩家到达目标地块后进入进攻队列，按队列顺序先后挑战守军\n2、若进攻成功，进攻方击败了所有守军，则该地块的所有权变更\n3、若进攻失败，玩家阵亡，则玩家会在10分钟后在设置的复活点复活（大本营、据点Lv3均可作为复活点） | D14632: =VLOOKUP(A14632,Sheet1!A:B,2,0)
A14633: 301878 | D14633: =VLOOKUP(A14633,Sheet1!A:B,2,0)
A14634: 301879 | B14634: Règles du raid | C14634: 扫荡规则 | D14634: =VLOOKUP(A14634,Sheet1!A:B,2,0)
A14635: 301880 | B14635: 1. Vous pouvez effectuer le raid sur les parcelles de ressources occupées.\n2. Chaque raid consomme 1 Activité. Battez les défenseurs lors du raid pour obtenir des [mérites JcE] et des [lingots de fer] (identique à l'attaque). | C14635: 1、对已占领的资源地块，可进行扫荡操作\n2、每次扫荡将消耗1点行动力，扫荡时击败守军，可获得【PVE战功】及【铁锭】（同进攻操作） | D14635: =VLOOKUP(A14635,Sheet1!A:B,2,0)
A14636: 301881 | B14636: Règles de défense | C14636: 防守规则 | D14636: =VLOOKUP(A14636,Sheet1!A:B,2,0)
A14637: 301882 | B14637: 1. Après la garnison, le joueur sera inclus dans la file d'attente de défense de la parcelle.\n2. En statut de garnison, 10 % des PV max peuvent être restaurés toutes les 1 minute.\n3. Si la défense réussit et que le défenseur bat tous les attaquants, la propriété de la parcelle ne change pas.\n4. Si la défense échoue et que tous les défenseurs sont battus, la propriété de la parcelle change. | C14637: 1、驻守后将玩家算进该地块的防守队列\n2、驻守状态，每1分钟可恢复10%最大生命值的血量\n3、若防守成功，防守者击败了所有进攻者，则该地块的所有权维持原状\n4、若防守失败，所有防守者被击败，则地块归属权变更 | D14637: =VLOOKUP(A14637,Sheet1!A:B,2,0)
A14638: 301883 | D14638: =VLOOKUP(A14638,Sheet1!A:B,2,0)
A14639: 301884 | B14639: Règles de résurrection | C14639: 复活规则 | D14639: =VLOOKUP(A14639,Sheet1!A:B,2,0)
A14640: 301885 | B14640: 1. Après la défaite, vous serez ressuscité au point de résurrection défini après 50 minutes (le quartier général et le bastion Niv. 3 peuvent être définis comme points de résurrection).\n2 Vous pouvez sauter le temps de résurrection et ressusciter rapidement en consommant l'objet [Rosée de l'arbre du monde]. | C14640: 1、被击败后，将于50分钟后在设置的复活点复活（大本营、据点Lv3均可设置为复活点）\n2、消耗【世界树晨露】道具可跳过复活时间，快速复活 | D14640: =VLOOKUP(A14640,Sheet1!A:B,2,0)
A14641: 301886 | B14641: Règles de retraite | C14641: 撤退规则 | D14641: =VLOOKUP(A14641,Sheet1!A:B,2,0)
A14642: 301887 | B14642: 1. Vous pouvez battre en retraite pendant le combat.\n2. Si vous battez en retraite avant la publication du premier rapport de combat, l'Activité de cette attaque sera remboursée.\n3. Si vous battez en retraite après avoir combattu et que le rapport de combat est publié, l'Activité ne sera pas remboursée.\n4. Aucune autre opération ne peut être effectuée pendant la retraite. | C14642: 1、战斗中可主动进行撤退\n2、未出首个战报前进行撤退，将返还本次进攻的行动力\n3、若已经进行了战斗且出了战报结果后进行撤退，将不返还行动力\n4、撤退过程中无法进行其他操作 | D14642: =VLOOKUP(A14642,Sheet1!A:B,2,0)
A14643: 301888 | B14643: Règles de combat | C14643: 战斗规则 | D14643: =VLOOKUP(A14643,Sheet1!A:B,2,0)
A14644: 301890 | B14644: Règles de partie nulle | C14644: 平局规则 | D14644: =VLOOKUP(A14644,Sheet1!A:B,2,0)
A14645: 301891 | B14645: 1. Si après 1 combat, il n'y a pas de vainqueur (les PV restants des deux parties > 0), les PV de la partie précédente seront gardés et le combat continuera (la limite supérieure est de 3 parties)\n2. S'il n'y a toujours pas de vainqueur après 3 combats consécutifs, l'attaquant se recule automatiquement vers le point de résurrection. | C14645: 1、若1场战斗后，双方未分出胜负（剩余血量均>0），则将保持上一场的血量继续战斗（上限为3场）\n2、连续战斗3场后仍然未分出胜负，则进攻方自动撤退回复活点 | D14645: =VLOOKUP(A14645,Sheet1!A:B,2,0)
A14646: 301892 | B14646: Diminution de dégâts JcJ | C14646: PVP伤害衰减 | D14646: =VLOOKUP(A14646,Sheet1!A:B,2,0)
A14647: 301893 | B14647: 1. Les effets de diminution de dégâts, de restauration de PV et autres effets dans le combat JcJ prennent effet dans le combat de la Mer Mystérieuse. | C14647: 1、PVP战斗中的所有伤害衰减、回血衰减等效果，在神秘海域的战斗中均生效 | D14647: =VLOOKUP(A14647,Sheet1!A:B,2,0)
A14648: 301894 | B14648: Règles de règlement saisonnier | C14648: 赛季结算规则 | D14648: =VLOOKUP(A14648,Sheet1!A:B,2,0)
A14649: 301895 | B14649: 1. Une fois la saison terminée, le niveau d'étoile de [coque] sera gardé et tous les autres contenus d'amélioration seront réinitialisés lors de la prochaine saison.\n2. Après le règlement saisonnier, à l'exception des objets d'échange de [billet argent] et de [mérites] et tous les objets de [fragment de coque], tous les autres objets de la saison seront effacés.\n3. Après le règlement saisonnier, les récompenses de la saison seront réglées en fonction du classement personnel des mérites et du classement des mérites du serveur.\n4. Après le règlement saisonnier, le nombre de tirages et les chances garanties dans le [Tirage de navire de combat] ne seront pas réinitialisé.\n5. Après le règlement saisonnier, le nombre de tirages dans le [Lieu du Trésor] sera réinitialisé. | C14649: 1、赛季结束后，将保留【船身】的星级，其他的养成内容将在下赛季中全部重置\n2、赛季结算后，除了【白银船票】、【战功】兑换道具和所有【船身碎片】道具，所有赛季内的其他道具将被全部清除\n3、赛季结算后，将根据个人战功排名和服务器战功排名，结算赛季奖励\n4、赛季结算后，【战船抽奖】中的抽奖次数和保底次数不会被重置\n5、赛季结算后，【藏宝地】中的抽奖次数将被重置 | D14649: =VLOOKUP(A14649,Sheet1!A:B,2,0)
A14650: 301896 | B14650: Règles de mérites JcE | C14650: PVE战功规则 | D14650: =VLOOKUP(A14650,Sheet1!A:B,2,0)
... A16312: 600004366 | B16312: 3000K | C16312: 3000K | D16312: =VLOOKUP(A16312,Sheet1!A:B,2,0)
A16313: 600004367 | B16313: 10 | C16313: 10 | D16313: =VLOOKUP(A16313,Sheet1!A:B,2,0)
...

Sheet Sheet1
A1: 0
A2: 语言总表
A3: 索引ID | B3: 内容
A4: 1*1 | B4: stack_error,n_list
A5: id | B5: text
A6: int | B6: string
A7: id | B7: text
A8: int | B8: ori_string
A9: 100001 | B9: T后台纯文本邮件模板
A10: 100002 | B10: T后台文本+奖励邮件模板
A11: 100003 | B11: 菇勇者
A12: 100004 | B12: 战士
A13: 100005 | B13: 弓箭手
A14: 100006 | B14: 法师
A15: 100007 | B15: 剑客
A16: 100008 | B16: 斧武士
A17: 100009 | B17: 狙影猎手
A18: 100010 | B18: 风弩手
A19: 100011 | B19: 愈灵师
A20: 100012 | B20: 魔灵士
... A13293: 700000003 | B13293: 增加##1%暴击,笨尼攻击有##2%概率击飞目标##3秒
A13294: 700000002
A13295: 400080 | B13295: 待寻找
A13296: 400534 | B13296: 当前难度开放满3天且通关时防御值为10解锁扫荡
A13297: 400535 | B13297: 通关当前难度且防御值为10时解锁扫荡
A13298: 400536 | B13298: 悲伤蛙好感：
A13299: 400537 | B13299: 悲伤蛙宇宙
A13300: 400538 | B13300: 躲蛙蛙
A13301: 400539 | B13301: 守卫佛系蛙
A13302: 400540 | B13302: 失眠蛙
A13303: 400541 | B13303: 星球之旅
A13304: 400542 | B13304: 高光时刻
A13305: 400543 | B13305: 打爆不开心
A13306: 400544 | B13306: 太空历险蛙
... A14889: 301877 | B14889: 1、每次进攻，都需消耗1点行动力\n2、发起进攻操作，玩家到达目标地块后进入进攻队列，按队列顺序先后挑战守军\n2、若进攻成功，进攻方击败了所有守军，则该地块的所有权变更\n3、若进攻失败，玩家阵亡，则玩家会在10分钟后在设置的复活点复活（大本营、据点Lv3均可作为复活点）
A14890: 301878
A14891: 301879 | B14891: 扫荡规则
A14892: 301880 | B14892: 1、对已占领的资源地块，可进行扫荡操作\n2、每次扫荡将消耗1点行动力，扫荡时击败守军，可获得【PVE战功】及【铁锭】（同进攻操作）
A14893: 301881 | B14893: 防守规则
A14894: 301882 | B14894: 1、驻守后将玩家算进该地块的防守队列\n2、驻守状态，每1分钟可恢复10%最大生命值的血量\n3、若防守成功，防守者击败了所有进攻者，则该地块的所有权维持原状\n4、若防守失败，所有防守者被击败，则地块归属权变更
A14895: 301883
A14896: 301884 | B14896: 复活规则
A14897: 301885 | B14897: 1、被击败后，将于50分钟后在设置的复活点复活（大本营、据点Lv3均可设置为复活点）\n2、消耗【世界树晨露】道具可跳过复活时间，快速复活
A14898: 301886 | B14898: 撤退规则
A14899: 301887 | B14899: 1、战斗中可主动进行撤退\n2、未出首个战报前进行撤退，将返还本次进攻的行动力\n3、若已经进行了战斗且出了战报结果后进行撤退，将不返还行动力\n4、撤退过程中无法进行其他操作
A14900: 301888 | B14900: 战斗规则
A14901: 301889 | B14901: 0、以下所有公式中的局外属性，为去掉局外同伴的上阵效果后的值！！\n1、局内主角生命=【局内船只生命】*(1+局外基础生命加成百分比^0.6+【局内船只生命加成】)*(1+局外全局生命加成百分比)\n2、局内主角攻击力=【局内船只攻击】*(1+局外基础攻击加成百分比^0.6+【局内船只攻击加成】）*(1+局外全局攻击加成百分比）\n3、局内主角防御=【局内船只防御】*(1+局外基础防御加成百分比^0.6+【局内船只防御加成】)*(1+局外全局防御加成百分比)\n4、局内攻速 = 局外最终攻速（除同伴加成）\n5、局内主/副炮攻击力=【局内主角攻击】\n6、局内主/副炮攻速=【局内主角攻速】 +【船炮攻速加成】\n7、局内主炮伤害=(【局内主炮攻击】-【局内对手防御】) *【普攻系数】*【1-普攻减伤】*【1+船炮伤害比例】*【1 - 船炮减伤百分比】\n8、局内副炮伤害=(【局内副炮攻击】-【【局内对手防御】) *【普攻系数】*【1-普攻减伤】*【1+船炮伤害比例 】*【副炮伤害百分比】*【1-船炮减伤百分比】\n9、局内的船长【全局连击伤害】/【全局反击伤害】/【全局技能伤害】=局外的【全局连击伤害】^0.6/【全局反击伤害】^0.6/【全局技能伤害】^0.6\n10、局内的船长【普攻减伤】/【连击减伤】/【反击减伤】/【技能减伤】/【同伴减伤】属性数值=局外的【普攻减伤】* 0.7/【连击减伤】* 0.7/【反击减伤】* 0.7/【技能减伤】* 0.7/【同伴减伤】* 0.7
A14902: 301890 | B14902: 平局规则
A14903: 301891 | B14903: 1、若1场战斗后，双方未分出胜负（剩余血量均>0），则将保持上一场的血量继续战斗（上限为3场）\n2、连续战斗3场后仍然未分出胜负，则进攻方自动撤退回复活点
A14904: 301892 | B14904: PVP伤害衰减
A14905: 301893 | B14905: 1、PVP战斗中的所有伤害衰减、回血衰减等效果，在神秘海域的战斗中均生效
A14906: 301894 | B14906: 赛季结算规则
A14907: 301895 | B14907: 1、赛季结束后，将保留【船身】的星级，其他的养成内容将在下赛季中全部重置\n2、赛季结算后，除了【白银船票】、【战功】兑换道具和所有【船身碎片】道具，所有赛季内的其他道具将被全部清除\n3、赛季结算后，将根据个人战功排名和服务器战功排名，结算赛季奖励\n4、赛季结算后，【战船抽奖】中的抽奖次数和保底次数不会被重置\n5、赛季结算后，【藏宝地】中的抽奖次数将被重置
... A17053: 600004366 | B17053: 3000K
A17054: 600004367 | B17054: 10
A17055: 600004368 | B17055: 20
A17056: 600004369 | B17056: 50
A17057: 600004370 | B17057: 100
A17058: 600004371 | B17058: 200
A17059: 600004372 | B17059: 150
A17060: 600004373 | B17060: 500
A17061: 600004374 | B17061: 5
A17062: 600004375 | B17062: 30
A17063: 600004376 | B17063: 40
A17064: 600004377 | B17064: 1
A17065: 600004378 | B17065: 300
A17066: 600004379 | B17066: 50K
A17067: 600004380 | B17067: 150K
A17068: 600004381 | B17068: 3
A17069: 600004382 | B17069: 15
A17070: 600004383 | B17070: 7
A17071: 600004384 | B17071: 25
A17072: 700030102 | B17072: 骑羽令
A17073: 700030103 | B17073: 用于在冲刺商店中兑换坐骑和背饰
A17074: 700030104 | B17074: 同心
A17075: 700030105 | B17075: 钟情
A17076: 700030106 | B17076: 烈焰啸天
A17077: 700030107 | B17077: 用于解锁坐骑烈焰啸天的道具
A17078: 700030108 | B17078: 解锁高级坐骑\n“烈焰啸天”
A17079: 700030109 | B17079: 狂风烈焰越千尺，亘古巨龙啸长空！恭喜~s解锁超级坐骑烈焰啸天！（全服同享礼盒待大佬发送）
A17080: 700030110 | B17080: 每隔10秒造成##1%当前普攻范围伤害，并使目标受到灼烧，每秒受到##2%当前普攻伤害，持续至战斗结束，最多叠加3次；提高自身##3%攻击和防御，增加##4%减伤，持续至战斗结束，最多叠加3次。（战斗开始后立刻释放一次）
A17081: 700030111 | B17081: 玩家最大生命、攻击和防御各下降##1%，10分钟内没有增加击败数则击败数减一
A17082: 700030112 | B17082: 1、每次进攻，都需消耗1点行动力\n2、发起进攻操作，玩家到达目标地块后进入进攻队列，按队列顺序先后挑战守军\n2、若进攻成功，进攻方击败了所有守军，则该地块的所有权变更\n3、若进攻失败，玩家阵亡，则玩家会在50分钟后在设置的复活点复活（大本营、据点Lv3均可作为复活点）
A17083: 700030113 | B17083: 1、玩家连续击败其他玩家达到对应数量后，获得debuff效果，百分比削弱最大生命、攻击、防御属性（每10min未再增加击败数，则击败数-1）：\n击败数【3-4】:玩家生命、攻击和防御各下降15%\n击败数【5-6】:玩家生命、攻击和防御各下降25%\n击败数【7-8】:玩家生命、攻击和防御各下降35%\n击败数【9-10】:玩家生命、攻击和防御各下降45%\n击败数【11-12】:玩家生命、攻击和防御各下降55%\n击败数【13-14】:玩家生命、攻击和防御各下降65%\n击败数【15-17】:玩家生命、攻击和防御各下降75%\n击败数【18-20】:玩家生命、攻击和防御各下降80%\n击败数【21-24】:玩家生命、攻击和防御各下降85%\n击败数【>24】:玩家生命、攻击和防御各下降90%
... A17696: 205682 | B17696: 使用完全升级，前提天赋也将升至最高等级，是否确定使用
