Workbook

Sheet out_language_pt
A1: 0
A2: 语言总表
A3: 索引ID | B3: 内容 | C3: 中文，用于导出（不要在原表简转繁）
A4: 1*1 | B4: stack_error,n_list
A5: id | B5: text
A6: int | B6: string
A7: id | B7: text
A8: int | B8: ori_string
A9: 100001 | B9: Modelo de e-mail em texto para a plataforma T | C9: T后台纯文本邮件模板 | D9: =VLOOKUP(A9,Sheet1!A:B,2,0) | E9: D列为简中语言表的文本，若CD列中文本冲突，以D列为准
A10: 100002 | B10: Texto da plataforma T + modelo de e-mail de recompensa | C10: T后台文本+奖励邮件模板 | D10: =VLOOKUP(A10,Sheet1!A:B,2,0)
A11: 100003 | B11: Guerreiro Cogumelo | C11: 菇勇者 | D11: =VLOOKUP(A11,Sheet1!A:B,2,0)
A12: 100004 | B12: Guerreiro | C12: 战士 | D12: =VLOOKUP(A12,Sheet1!A:B,2,0)
A13: 100005 | B13: Arqueiro | C13: 弓箭手 | D13: =VLOOKUP(A13,Sheet1!A:B,2,0)
A14: 100006 | B14: Mago | C14: 法师 | D14: =VLOOKUP(A14,Sheet1!A:B,2,0)
A15: 100007 | B15: Espadachim | C15: 剑客 | D15: =VLOOKUP(A15,Sheet1!A:B,2,0)
A16: 100008 | B16: Escoteiro | C16: 斧武士 | D16: =VLOOKUP(A16,Sheet1!A:B,2,0)
A17: 100009 | B17: Caçador das Sombras | C17: 狙影猎手 | D17: =VLOOKUP(A17,Sheet1!A:B,2,0)
A18: 100010 | B18: Arqueiro do Vento | C18: 风弩手 | D18: =VLOOKUP(A18,Sheet1!A:B,2,0)
A19: 100011 | B19: Curandeiro | C19: 愈灵师 | D19: =VLOOKUP(A19,Sheet1!A:B,2,0)
A20: 100012 | B20: Espiritista | C20: 魔灵士 | D20: =VLOOKUP(A20,Sheet1!A:B,2,0)
A21: 100013 | B21: Paladino | C21: 大剑士 | D21: =VLOOKUP(A21,Sheet1!A:B,2,0)
... A4418: 200094 | B4418: Consumir %s? | C4418: 是否消耗%s | D4418: =VLOOKUP(A4418,Sheet1!A:B,2,0)
A4419: 700024509 | B4419: Consumir ##1*##2? | C4419: 是否消耗##1*##2
A4420: 200095 | B4420: Reforjar | C4420: 重铸 | D4420: =VLOOKUP(A4420,Sheet1!A:B,2,0)
A4421: 200096 | B4421: <b><color=#544231>Meta de Milhagem: alcançar Milhagem</color> <color=#ab630e>%s</color></b> | C4421: <b><color=#544231>里程目标：里程值达到</color><color=#ab630e>%s</color></b> | D4421: =VLOOKUP(A4421,Sheet1!A:B,2,0)
A4422: 200097 | B4422: <b><color=#544231>Meta de Milhagem: concluir a instância do evento</color> <color=#ab630e>%s</color></b> | C4422: <b><color=#544231>里程目标：通关活动副本</color><color=#ab630e>%s</color></b> | D4422: =VLOOKUP(A4422,Sheet1!A:B,2,0)
A4423: 200098 | B4423: Efeitos em batalha: %s | C4423: 上阵效果：%s | D4423: =VLOOKUP(A4423,Sheet1!A:B,2,0)
A4424: 200099 | B4424: Vida básica, ATQ e Defesa +%s% | C4424: 基础生命&攻击&防御+%s% | D4424: =VLOOKUP(A4424,Sheet1!A:B,2,0)
A4425: 200100 | B4425: Sem companheiro para equipar | C4425: 没有可以装配的同伴 | D4425: =VLOOKUP(A4425,Sheet1!A:B,2,0)
A4426: 200101 | B4426: Desbloquear | C4426: 解锁 | D4426: =VLOOKUP(A4426,Sheet1!A:B,2,0)
A4427: 200102 | B4427: Horário do evento: %s | C4427: 活动时间：%s | D4427: =VLOOKUP(A4427,Sheet1!A:B,2,0)
A4428: 200103 | B4428: Atributos básicos | C4428: 基础属性 | D4428: =VLOOKUP(A4428,Sheet1!A:B,2,0)
A4429: 200104 | B4429: Atributos avançados | C4429: 高级属性 | D4429: =VLOOKUP(A4429,Sheet1!A:B,2,0)
A4430: 200105 | B4430: Atributos finais | C4430: 最终属性 | D4430: =VLOOKUP(A4430,Sheet1!A:B,2,0)
A4431: 200106 | B4431: Nível insuficiente | C4431: 等级不足 | D4431: =VLOOKUP(A4431,Sheet1!A:B,2,0)
... A5004: 200685 | B5004: Dano: %s | C5004: 伤害：%s | D5004: =VLOOKUP(A5004,Sheet1!A:B,2,0)
A5005: 200686 | B5005: 1 | C5005: 一个 | D5005: =VLOOKUP(A5005,Sheet1!A:B,2,0)
A5006: 200687 | B5006: 2 | C5006: 两个 | D5006: =VLOOKUP(A5006,Sheet1!A:B,2,0)
A5007: 200688 | B5007: 3 | C5007: 三个 | D5007: =VLOOKUP(A5007,Sheet1!A:B,2,0)
A5008: 200689 | B5008: 4 | C5008: 四个 | D5008: =VLOOKUP(A5008,Sheet1!A:B,2,0)
A5009: 200690 | B5009: 5 | C5009: 五个 | D5009: =VLOOKUP(A5009,Sheet1!A:B,2,0)
A5010: 200691 | B5010: 6 | C5010: 六个 | D5010: =VLOOKUP(A5010,Sheet1!A:B,2,0)
A5011: 200692 | B5011: 7 | C5011: 七个 | D5011: =VLOOKUP(A5011,Sheet1!A:B,2,0)
A5012: 200693 | B5012: 8 | C5012: 八个 | D5012: =VLOOKUP(A5012,Sheet1!A:B,2,0)
A5013: 200694 | B5013: 9 | C5013: 九个 | D5013: =VLOOKUP(A5013,Sheet1!A:B,2,0)
A5014: 200695 | B5014: 10 | C5014: 十个 | D5014: =VLOOKUP(A5014,Sheet1!A:B,2,0)
A5015: 200696 | B5015: Picareta | C5015: 镐子 | D5015: =VLOOKUP(A5015,Sheet1!A:B,2,0)
A5016: 200697 | B5016: Broca | C5016: 钻头 | D5016: =VLOOKUP(A5016,Sheet1!A:B,2,0)
A5017: 200698 | B5017: Bomba | C5017: 炸弹 | D5017: =VLOOKUP(A5017,Sheet1!A:B,2,0)
A5018: 200699 | B5018: Falha na verificação de login no servidor | C5018: 登录服校验失败 | D5018: =VLOOKUP(A5018,Sheet1!A:B,2,0)
A5019: 200700 | B5019: Verificação de login na plataforma expirada | C5019: 平台登录验证超时 | D5019: =VLOOKUP(A5019,Sheet1!A:B,2,0)
A5020: 200701 | B5020: Falha na verificação de login na plataforma | C5020: 平台登录验证失败 | D5020: =VLOOKUP(A5020,Sheet1!A:B,2,0)
A5021: 200702 | B5021: Ocorreu um erro desconhecido na verificação de login na plataforma | C5021: 平台登录验证遇见不明错误 | D5021: =VLOOKUP(A5021,Sheet1!A:B,2,0)
A5022: 200703 | B5022: Servidor em manutenção | C5022: 服务器当前处于维护状态 | D5022: =VLOOKUP(A5022,Sheet1!A:B,2,0)
A5023: 200704 | B5023: Pedido errado | C5023: 错误的请求 | D5023: =VLOOKUP(A5023,Sheet1!A:B,2,0)
A5024: 200705 | B5024: Falha na verificação | C5024: 验证失败 | D5024: =VLOOKUP(A5024,Sheet1!A:B,2,0)
A5025: 200706 | B5025: Erro de parâmetro | C5025: 参数错误 | D5025: =VLOOKUP(A5025,Sheet1!A:B,2,0)
A5026: 200707 | B5026: Fechar | C5026: 关闭注册 | D5026: =VLOOKUP(A5026,Sheet1!A:B,2,0)
... A13203: 999300208 | B13203: Pista %s | C13203: 线索 %s | D13203: =VLOOKUP(A13203,Sheet1!A:B,2,0)
A13204: 700000002 | C13204: 悲伤蛙称号，不需要文字 | D13204: =VLOOKUP(A13204,Sheet1!A:B,2,0)
A13205: 202255 | B13205: Querido Cogumelo, você tem recompensas de e-mail pendentes de expiração. Irmã cogumelo está cuidando delas para você. Por favor, verifique! | C13205: 亲爱的菇菇，您有未领取的到期邮件奖励，菇妹已为您保管，请注意查收哟~ | D13205: =VLOOKUP(A13205,Sheet1!A:B,2,0)
A13206: 600000001 | B13206: Bônus de Dano de Companheiro | C13206: 同伴伤害加成 | D13206: =VLOOKUP(A13206,Sheet1!A:B,2,0)
A13207: 202101 | B13207: Desbloqueável ao alcançar o piso %s | C13207: 达到%s层解锁 | D13207: =VLOOKUP(A13207,Sheet1!A:B,2,0)
A13208: 700000001 | B13208: A cada ##1s, causa Dano em Área igual a ##2% do ATQ Normal atual, e deixa o alvo em um estado caótico: Toda vez que este lançar um ataque (ATQ Normal, Combo, Contra-ataque e Habilidade), ele causará adicionalmente a si mesmo dano igual a ##3% do próprio ATQ Normal atual durante ##4s. (O efeito é liberado uma vez imediatamente após o início da batalha) | C13208: 每隔##1秒造成##2%当前普攻范围伤害，并使目标陷入混乱状态：目标每次攻击（普攻，连击，反击，技能）时会额外对自身造成##3%目标当前普攻伤害，持续##4秒。（战斗开始后立刻释放一次） | D13208: =VLOOKUP(A13208,Sheet1!A:B,2,0)
A13209: 400080 | B13209: Não procurado | C13209: 待寻找 | D13209: =VLOOKUP(A13209,Sheet1!A:B,2,0)
A13210: 400534 | B13210: 3 dias após a abertura, concluir a dificuldade atual com 10 de Defesa desbloqueia a Raide | C13210: 当前难度开放满3天且通关时防御值为10解锁扫荡 | D13210: =VLOOKUP(A13210,Sheet1!A:B,2,0)
A13211: 400535 | B13211: Concluir a dificuldade atual com 10 de Defesa desbloqueia a Raide | C13211: 通关当前难度且防御值为10时解锁扫荡 | D13211: =VLOOKUP(A13211,Sheet1!A:B,2,0)
A13212: 400536 | B13212: Afinidade de Pepe: | C13212: 悲伤蛙好感： | D13212: =VLOOKUP(A13212,Sheet1!A:B,2,0)
A13213: 400537 | B13213: Universo do Pepe | C13213: 悲伤蛙宇宙 | D13213: =VLOOKUP(A13213,Sheet1!A:B,2,0)
A13214: 400538 | B13214: Pepe Esconde | C13214: 躲蛙蛙 | D13214: =VLOOKUP(A13214,Sheet1!A:B,2,0)
A13215: 400539 | B13215: Proteja o Pepe Zen | C13215: 守卫佛系蛙 | D13215: =VLOOKUP(A13215,Sheet1!A:B,2,0)
A13216: 400540 | B13216: Pepe Sem Sono | C13216: 失眠蛙 | D13216: =VLOOKUP(A13216,Sheet1!A:B,2,0)
... A14632: 301877 | B14632: 1. Cada ataque consome 1 ponto de energia.\n2. Ao começar a atacar, o jogador entra na fila de ataque após alcançar o bloco alvo, desafiando os defensores na ordem da fila.\n2. Se o ataque for bem-sucedido e os atacantes derrotarem todos os defensores, a propriedade do bloco é transferida para os atacantes.\n3. Se o ataque falhar e o jogador morrer, ele ressuscitará no ponto de ressurreição configurado após 10 minutos (Base principal ou um Ponto Nv.3 pode ser usado como ponto de ressurreição). | C14632: 1、每次进攻，都需消耗1点行动力\n2、发起进攻操作，玩家到达目标地块后进入进攻队列，按队列顺序先后挑战守军\n2、若进攻成功，进攻方击败了所有守军，则该地块的所有权变更\n3、若进攻失败，玩家阵亡，则玩家会在10分钟后在设置的复活点复活（大本营、据点Lv3均可作为复活点） | D14632: =VLOOKUP(A14632,Sheet1!A:B,2,0)
A14633: 301878 | D14633: =VLOOKUP(A14633,Sheet1!A:B,2,0)
A14634: 301879 | B14634: Regras de Raide | C14634: 扫荡规则 | D14634: =VLOOKUP(A14634,Sheet1!A:B,2,0)
A14635: 301880 | B14635: 1. Os Blocos de recursos já ocupados podem ser Raide.\n2. Cada Raide consumirá 1 ponto de energia. Quando está Raide, derrotar as forças inimigas concederá [Mérito de Batalha PVE] e [Lingotes de Ferro] (igual às operações de ataque) | C14635: 1、对已占领的资源地块，可进行扫荡操作\n2、每次扫荡将消耗1点行动力，扫荡时击败守军，可获得【PVE战功】及【铁锭】（同进攻操作） | D14635: =VLOOKUP(A14635,Sheet1!A:B,2,0)
A14636: 301881 | B14636: Regras de Defesa | C14636: 防守规则 | D14636: =VLOOKUP(A14636,Sheet1!A:B,2,0)
A14637: 301882 | B14637: 1. Após a guarnição, o jogador está na fila de defesa daquele bloco.\n2. Durante o estado da guarnição, a cada 1 minuto, é possível recuperar 10% da vida máxima.\n3. Se a defesa for bem-sucedida e o defensor derrota todos os atacantes, então a propriedade do bloco permanece inalterada.\n4. Se a defesa falhar e todos os defensores forem derrotados, então a propriedade do bloco é transferida para os atacantes. | C14637: 1、驻守后将玩家算进该地块的防守队列\n2、驻守状态，每1分钟可恢复10%最大生命值的血量\n3、若防守成功，防守者击败了所有进攻者，则该地块的所有权维持原状\n4、若防守失败，所有防守者被击败，则地块归属权变更 | D14637: =VLOOKUP(A14637,Sheet1!A:B,2,0)
A14638: 301883 | D14638: =VLOOKUP(A14638,Sheet1!A:B,2,0)
A14639: 301884 | B14639: Regras de ressurreição | C14639: 复活规则 | D14639: =VLOOKUP(A14639,Sheet1!A:B,2,0)
A14640: 301885 | B14640: 1. Após ser derrotado, você será ressuscitado no ponto de ressurreição configurado após 50 minutos (tanto a base principal quanto o ponto Nv.3 podem ser configurados como pontos de ressurreição).\n2. Consumir o item [Orvalho da Árvore Mundial] pode ignorar o tempo de ressurreição, permitindo uma ressurreição rápida. | C14640: 1、被击败后，将于50分钟后在设置的复活点复活（大本营、据点Lv3均可设置为复活点）\n2、消耗【世界树晨露】道具可跳过复活时间，快速复活 | D14640: =VLOOKUP(A14640,Sheet1!A:B,2,0)
A14641: 301886 | B14641: Regras de retirada | C14641: 撤退规则 | D14641: =VLOOKUP(A14641,Sheet1!A:B,2,0)
A14642: 301887 | B14642: 1. Durante a batalha, é possível se retirar voluntariamente.\n2. Se retirar antes do primeiro relatório de batalha, receberá retorno da energia neste ataque.\n3. Se se retirar após realizar a batalha e ter o relatório de batalha, nenhum retorno de energia será dado.\n4. Durante a retirada, não é possível realizar outras operações. | C14642: 1、战斗中可主动进行撤退\n2、未出首个战报前进行撤退，将返还本次进攻的行动力\n3、若已经进行了战斗且出了战报结果后进行撤退，将不返还行动力\n4、撤退过程中无法进行其他操作 | D14642: =VLOOKUP(A14642,Sheet1!A:B,2,0)
A14643: 301888 | B14643: Regras de Batalha | C14643: 战斗规则 | D14643: =VLOOKUP(A14643,Sheet1!A:B,2,0)
A14644: 301890 | B14644: Regras de empate | C14644: 平局规则 | D14644: =VLOOKUP(A14644,Sheet1!A:B,2,0)
A14645: 301891 | B14645: 1. Se após uma batalha nenhuma dos lados sair vitoriosa (ambos os lados têm vida restante > 0), então eles continuarão a batalha com a mesma vida que tinham no final da rodada anterior (até um máximo de 3 rodadas).\n2. Se após três batalhas consecutivas nenhum lado sair vitorioso, então o lado que iniciou o ataque se retira automaticamente de volta ao ponto de ressurreição. | C14645: 1、若1场战斗后，双方未分出胜负（剩余血量均>0），则将保持上一场的血量继续战斗（上限为3场）\n2、连续战斗3场后仍然未分出胜负，则进攻方自动撤退回复活点 | D14645: =VLOOKUP(A14645,Sheet1!A:B,2,0)
A14646: 301892 | B14646: Debuff de dano em PVP | C14646: PVP伤害衰减 | D14646: =VLOOKUP(A14646,Sheet1!A:B,2,0)
A14647: 301893 | B14647: 1. Todos os efeitos de debuff de dano e cura em PVP são eficazes nas batalhas do Mar Misterioso. | C14647: 1、PVP战斗中的所有伤害衰减、回血衰减等效果，在神秘海域的战斗中均生效 | D14647: =VLOOKUP(A14647,Sheet1!A:B,2,0)
A14648: 301894 | B14648: Regras de Balanço de Temporada | C14648: 赛季结算规则 | D14648: =VLOOKUP(A14648,Sheet1!A:B,2,0)
A14649: 301895 | B14649: 1. Ao final da temporada, as estrelas de [casco de navio] serão preservadas, enquanto outros de desenvolvimento serão resetados para a próxima temporada.\n2. Após o balanço da temporada, todos os itens obtidos durante a temporada, exceto os itens usado trocar como[bilhetes de prata]e[méritos de batalha] e todos os [fragmentos de casco de navio], serão removidos.\n3. Após o balanço da temporada, as recompensas da temporada serão distribuídas com base no ranking individual de méritos de batalha e no ranking do servidor de méritos de batalha.\n4. Após o balanço da temporada, as tentativas de sorteio e as garantias de recompensa no [Sorteio de Navios] não serão resetadas.\n5. Após o balanço da temporada, as tentativas de sorteio no [Terra do Tesouro] serão resetadas. | C14649: 1、赛季结束后，将保留【船身】的星级，其他的养成内容将在下赛季中全部重置\n2、赛季结算后，除了【白银船票】、【战功】兑换道具和所有【船身碎片】道具，所有赛季内的其他道具将被全部清除\n3、赛季结算后，将根据个人战功排名和服务器战功排名，结算赛季奖励\n4、赛季结算后，【战船抽奖】中的抽奖次数和保底次数不会被重置\n5、赛季结算后，【藏宝地】中的抽奖次数将被重置 | D14649: =VLOOKUP(A14649,Sheet1!A:B,2,0)
A14650: 301896 | B14650: Regras de méritos de batalha em PVE | C14650: PVE战功规则 | D14650: =VLOOKUP(A14650,Sheet1!A:B,2,0)
... A16312: 600004366 | B16312: 3000K | C16312: 3000K | D16312: =VLOOKUP(A16312,Sheet1!A:B,2,0)
A16313: 600004367 | B16313: 10 | C16313: 10 | D16313: =VLOOKUP(A16313,Sheet1!A:B,2,0)
A16314: 600004368 | B16314: 20 | C16314: 20 | D16314: =VLOOKUP(A16314,Sheet1!A:B,2,0)
A16315: 600004369 | B16315: 50 | C16315: 50 | D16315: =VLOOKUP(A16315,Sheet1!A:B,2,0)
A16316: 600004370 | B16316: 100 | C16316: 100 | D16316: =VLOOKUP(A16316,Sheet1!A:B,2,0)
A16317: 600004371 | B16317: 200 | C16317: 200 | D16317: =VLOOKUP(A16317,Sheet1!A:B,2,0)
A16318: 600004372 | B16318: 150 | C16318: 150 | D16318: =VLOOKUP(A16318,Sheet1!A:B,2,0)
A16319: 600004373 | B16319: 500 | C16319: 500 | D16319: =VLOOKUP(A16319,Sheet1!A:B,2,0)
A16320: 600004374 | B16320: 5 | C16320: 5 | D16320: =VLOOKUP(A16320,Sheet1!A:B,2,0)
...

Sheet Sheet1
A1: 0
A2: 语言总表
A3: 索引ID | B3: 内容
A4: 1*1 | B4: stack_error,n_list | D4: 外语查找用这列
A5: id | B5: text
A6: int | B6: string
A7: id | B7: text
A8: int | B8: ori_string
A9: 100001 | B9: T后台纯文本邮件模板 | D9: T后台纯文本邮件模板
A10: 100002 | B10: T后台文本+奖励邮件模板 | D10: T后台文本+奖励邮件模板
A11: 100003 | B11: 菇勇者 | D11: 菇勇者
A12: 100004 | B12: 战士 | D12: 战士
A13: 100005 | B13: 弓箭手 | D13: 弓箭手
A14: 100006 | B14: 法师 | D14: 法师
A15: 100007 | B15: 剑客 | D15: 剑客
A16: 100008 | B16: 斧武士 | D16: 斧武士
A17: 100009 | B17: 狙影猎手 | D17: 狙影猎手
A18: 100010 | B18: 风弩手 | D18: 风弩手
A19: 100011 | B19: 愈灵师 | D19: 愈灵师
A20: 100012 | B20: 魔灵士 | D20: 魔灵士
... A13293: 700000003 | B13293: 增加##1%暴击,笨尼攻击有##2%概率击飞目标##3秒 | D13293: 当前难度开放满3天且通关时防御值为10解锁扫荡
A13294: 700000002 | D13294: 通关当前难度且防御值为10时解锁扫荡
A13295: 400080 | B13295: 待寻找 | D13295: 悲伤蛙好感：
A13296: 400534 | B13296: 当前难度开放满3天且通关时防御值为10解锁扫荡 | D13296: 悲伤蛙宇宙
A13297: 400535 | B13297: 通关当前难度且防御值为10时解锁扫荡 | D13297: 躲蛙蛙
A13298: 400536 | B13298: 悲伤蛙好感： | D13298: 守卫佛系蛙
A13299: 400537 | B13299: 悲伤蛙宇宙 | D13299: 失眠蛙
A13300: 400538 | B13300: 躲蛙蛙 | D13300: 星球之旅
A13301: 400539 | B13301: 守卫佛系蛙 | D13301: 高光时刻
A13302: 400540 | B13302: 失眠蛙 | D13302: 打爆不开心
A13303: 400541 | B13303: 星球之旅 | D13303: 太空历险蛙
A13304: 400542 | B13304: 高光时刻 | D13304: 以剩余守卫点≥5通关关卡1
A13305: 400543 | B13305: 打爆不开心 | D13305: 以剩余守卫点≥3通关关卡1
A13306: 400544 | B13306: 太空历险蛙 | D13306: 以剩余守卫点≥1通关关卡1
... A14257: 600000339 | B14257: 解锁高级背饰\n“天外来物” | D14257: 0点-8点为休战期，无法发起抢占
A14258: 600000340 | B14258: 用于解锁背饰天外来物的道具
A14259: 600000341 | B14259: 万仞穿刺
A14260: 600000342 | B14260: 流血（普攻伤害）
A14261: 600000343 | B14261: 使敌人受到伤害增加陷阱
A14262: 600000344 | B14262: 使敌人受到伤害增加
A14263: 600000345 | B14263: 普攻和连击触发对自己造成伤害
A14264: 600000346 | B14264: 反击触发对自己造成伤害
A14265: 600000347 | B14265: 释放技能对自己造成伤害
A14266: 600000348 | B14266: 对自身造成自身普攻伤害
A14267: 600000349 | B14267: 使所有敌人受到伤害增加##1% | D14267: <b><color=#544231>王城占领期间，服务器战功</color><color=#6fdb6e><outline color=#47372f width=2>+%s/min</outline></color></size>
A14268: 600000350 | B14268: 开局且每隔11秒，对目标造成##1%范围技能伤害并附带##2%最大生命值伤害，且有60%几率再次释放此技能，造成##3%范围技能伤害和##4%最大生命值伤害(再次释放的技能仍有几率再次释放，但每次连续释放几率-20%，直至不再释放时重置） | D14268: <b><color=#544231>全服务器玩家行动力</color><color=#6fdb6e><outline color=#47372f width=2>+%s</outline></color></size>
A14269: 600000351 | B14269: 当受到的最终伤害大于1%自身最大生命值时，格挡##1%伤害；当受到的最终伤害大于2%自身最大生命值时，格挡##2%伤害；当受到的最终伤害大于5%自身最大生命值时，格挡##3%伤害。 | D14269: <b><color=#544231>海战战斗中船只基础攻击、基础生命、基础防御属性提升</color><color=#6fdb6e><outline color=#47372f width=2>+%s%</outline></color></size>，<color=#544231>持续</color><color=#6fdb6e><outline color=#47372f width=2>24h</outline></color></size>
A14270: 600000352 | B14270: 每隔##1秒，连续造成5段##2%当前普攻范围流血伤害（无视伤害免疫），每段伤害有##3%几率额外造成##4%最大生命值伤害（战斗开始后立刻释放一次） | D14270: <b><color=#544231>王城占领期间，每5min获得</color><color=#6fdb6e><outline color=#47372f width=2>%s个战功道具</outline></color></size>
A14271: 204576 | B14271: 今日购买奶茶次数已满 | D14271: 赛季王城首占奖励
A14272: 700000301 | B14272: ##1-个人调整 | D14272: 赛季空投占领奖励
A14273: 700000302 | B14273: 移至##1 | D14273: 恭喜您的服务器首个占领王城！首占奖励已发送，请查收以下奖励。
A14274: 700000303 | B14274: 无变化 | D14274: 恭喜您的服务器成功占领空投！占领奖励已发送，请查收以下奖励。
A14275: 700000304 | B14275: 调整时间已结束 | D14275: %s\n后出现在地图（%s, %s）
A14276: 700000305 | B14276: 已有其他玩家修改此分路 | D14276: 无人占领
A14277: 700000306 | B14277: 取消移动 | D14277: 未被占领
A14278: 700000307 | B14278: 无延时 | D14278: 【s%s】占领中
... A14684: 301672 | B14684: 神秘海域挑战守卫单位增伤 | D14684: 1、每次进攻，都需消耗1点行动力\n2、发起进攻操作，玩家到达目标地块后进入进攻队列，按队列顺序先后挑战守军\n2、若进攻成功，进攻方击败了所有守军，则该地块的所有权变更\n3、若进攻失败，玩家阵亡，则玩家会在10分钟后在设置的复活点复活（大本营、据点Lv3均可作为复活点）
A14685: 301673 | B14685: 神秘海域挑战守卫伤害提升
A14686: 301674 | B14686: 船炮伤害 | D14686: 扫荡规则
A14687: 301675 | B14687: 赛季船只船炮伤害百分比 | D14687: 1、对已占领的资源地块，可进行扫荡操作\n2、每次扫荡将消耗1点行动力，扫荡时击败守军，可获得【PVE战功】及【铁锭】（同进攻操作）
A14688: 301676 | B14688: 战斗后恢复行动力概率 | D14688: 防守规则
A14689: 301677 | B14689: 战斗后恢复船只血量 | D14689: 1、驻守后将玩家算进该地块的防守队列\n2、驻守状态，每1分钟可恢复10%最大生命值的血量\n3、若防守成功，防守者击败了所有进攻者，则该地块的所有权维持原状\n4、若防守失败，所有防守者被击败，则地块归属权变更
A14690: 301678 | B14690: 战斗后修复船只血量百分比
A14691: 301679 | B14691: S1王城首占奖励 | D14691: 复活规则
A14692: 301680 | B14692: S1个人战功榜前三名可获得 | D14692: 1、被击败后，将于50分钟后在设置的复活点复活（大本营、据点Lv3均可设置为复活点）\n2、消耗【世界树晨露】道具可跳过复活时间，快速复活
A14693: 301681 | B14693: 航海pvp战斗 | D14693: 撤退规则
A14694: 301682 | B14694: 微信游戏道具商城获取 | D14694: 1、战斗中可主动进行撤退\n2、未出首个战报前进行撤退，将返还本次进攻的行动力\n3、若已经进行了战斗且出了战报结果后进行撤退，将不返还行动力\n4、撤退过程中无法进行其他操作
A14695: 301683 | B14695: S1服务器战功榜第一名可获得，限时30天 | D14695: 战斗规则
A14696: 301684 | B14696: 低于全服最高等级50级，无法停车 | D14696: 0、以下所有公式中的局外属性，为去掉局外同伴的上阵效果后的值！！\n1、局内主角生命=【局内船只生命】*(1+局外基础生命加成百分比^0.6+【局内船只生命加成】)*(1+局外全局生命加成百分比)\n2、局内主角攻击力=【局内船只攻击】*(1+局外基础攻击加成百分比^0.6+【局内船只攻击加成】）*(1+局外全局攻击加成百分比）\n3、局内主角防御=【局内船只防御】*(1+局外基础防御加成百分比^0.6+【局内船只防御加成】)*(1+局外全局防御加成百分比)\n4、局内攻速 = 局外最终攻速（除同伴加成）\n5、局内主/副炮攻击力=【局内主角攻击】\n6、局内主/副炮攻速=【局内主角攻速】 +【船炮攻速加成】\n7、局内主炮伤害=(【局内主炮攻击】-【局内对手防御】) *【普攻系数】*【1-普攻减伤】*【1+船炮伤害比例】*【1 - 船炮减伤百分比】\n8、局内副炮伤害=(【局内副炮攻击】-【【局内对手防御】) *【普攻系数】*【1-普攻减伤】*【1+船炮伤害比例 】*【副炮伤害百分比】*【1-船炮减伤百分比】\n9、局内的船长【全局连击伤害】/【全局反击伤害】/【全局技能伤害】=局外的【全局连击伤害】^0.6/【全局反击伤害】^0.6/【全局技能伤害】^0.6\n10、局内的船长【普攻减伤】/【连击减伤】/【反击减伤】/【技能减伤】/【同伴减伤】属性数值=局外的【普攻减伤】* 0.7/【连击减伤】* 0.7/【反击减伤】* 0.7/【技能减伤】* 0.7/【同伴减伤】* 0.7
A14697: 301685 | B14697: 主船经验 | D14697: 平局规则
A14698: 301686 | B14698: 用于提升主船等级 | D14698: 1、若1场战斗后，双方未分出胜负（剩余血量均>0），则将保持上一场的血量继续战斗（上限为3场）\n2、连续战斗3场后仍然未分出胜负，则进攻方自动撤退回复活点
A14699: 301687 | B14699: 海洋霸主 | D14699: PVP伤害衰减
A14700: 301688 | B14700: 迷失之海赛季活动获得 | D14700: 1、PVP战斗中的所有伤害衰减、回血衰减等效果，在神秘海域的战斗中均生效
A14701: 301689 | B14701: 扬帆起航（限时） | D14701: 赛季结算规则
A14702: 301690 | B14702: 航海赛季个人战功榜前三名可获得，限时30天 | D14702: 1、赛季结束后，将保留【船身】的星级，其他的养成内容将在下赛季中全部重置\n2、赛季结算后，除了【白银船票】、【战功】兑换道具和所有【船身碎片】道具，所有赛季内的其他道具将被全部清除\n3、赛季结算后，将根据个人战功排名和服务器战功排名，结算赛季奖励\n4、赛季结算后，【战船抽奖】中的抽奖次数和保底次数不会被重置\n5、赛季结算后，【藏宝地】中的抽奖次数将被重置
... A14882: 301870 | B14882: 行动力恢复 | D14882: 进攻
A14883: 301871 | B14883: 1、自然恢复：每60分钟可恢复1点行动力\n(自然恢复上限为10，超过上限后不再恢复)\n2、使用1个【燃料】道具可恢复1点行动力
A14884: 301872 | B14884: 侦查、标记规则
A14885: 301873 | B14885: 1、每次侦查需要消耗1点行动力（仅可侦查非我方占领地块）\n2、侦查后分享情报到聊天频道，其他玩家可通过分享消息快速定位到被侦查点\n3、侦查效果持续15分钟，期间可选中地块，点击【查看】按钮查看被侦查点的驻守信息\n4、标记操作不需要消耗行动力（仅可标记非我方占领地块），标记后分享信息到聊天频道，其他玩家可通过消息快速定位到被标记点
A14886: 301874 | B14886: 小地图规则
A14887: 301875 | B14887: 1、小地图上展示地图全貌，点击小地图任意位置可将视角跳转到点击的位置\n2、小地图上的各点位颜色对应当前占领该点位的势力方，白色代表该点位未被占领
A14888: 301876 | B14888: 进攻规则
A14889: 301877 | B14889: 1、每次进攻，都需消耗1点行动力\n2、发起进攻操作，玩家到达目标地块后进入进攻队列，按队列顺序先后挑战守军\n2、若进攻成功，进攻方击败了所有守军，则该地块的所有权变更\n3、若进攻失败，玩家阵亡，则玩家会在10分钟后在设置的复活点复活（大本营、据点Lv3均可作为复活点）
A14890: 301878
A14891: 301879 | B14891: 扫荡规则
A14892: 301880 | B14892: 1、对已占领的资源地块，可进行扫荡操作\n2、每次扫荡将消耗1点行动力，扫荡时击败守军，可获得【PVE战功】及【铁锭】（同进攻操作）
A14893: 301881 | B14893: 防守规则
A14894: 301882 | B14894: 1、驻守后将玩家算进该地块的防守队列\n2、驻守状态，每1分钟可恢复10%最大生命值的血量\n3、若防守成功，防守者击败了所有进攻者，则该地块的所有权维持原状\n4、若防守失败，所有防守者被击败，则地块归属权变更
A14895: 301883
A14896: 301884 | B14896: 复活规则
A14897: 301885 | B14897: 1、被击败后，将于50分钟后在设置的复活点复活（大本营、据点Lv3均可设置为复活点）\n2、消耗【世界树晨露】道具可跳过复活时间，快速复活
A14898: 301886 | B14898: 撤退规则
A14899: 301887 | B14899: 1、战斗中可主动进行撤退\n2、未出首个战报前进行撤退，将返还本次进攻的行动力\n3、若已经进行了战斗且出了战报结果后进行撤退，将不返还行动力\n4、撤退过程中无法进行其他操作
A14900: 301888 | B14900: 战斗规则
A14901: 301889 | B14901: 0、以下所有公式中的局外属性，为去掉局外同伴的上阵效果后的值！！\n1、局内主角生命=【局内船只生命】*(1+局外基础生命加成百分比^0.6+【局内船只生命加成】)*(1+局外全局生命加成百分比)\n2、局内主角攻击力=【局内船只攻击】*(1+局外基础攻击加成百分比^0.6+【局内船只攻击加成】）*(1+局外全局攻击加成百分比）\n3、局内主角防御=【局内船只防御】*(1+局外基础防御加成百分比^0.6+【局内船只防御加成】)*(1+局外全局防御加成百分比)\n4、局内攻速 = 局外最终攻速（除同伴加成）\n5、局内主/副炮攻击力=【局内主角攻击】\n6、局内主/副炮攻速=【局内主角攻速】 +【船炮攻速加成】\n7、局内主炮伤害=(【局内主炮攻击】-【局内对手防御】) *【普攻系数】*【1-普攻减伤】*【1+船炮伤害比例】*【1 - 船炮减伤百分比】\n8、局内副炮伤害=(【局内副炮攻击】-【【局内对手防御】) *【普攻系数】*【1-普攻减伤】*【1+船炮伤害比例 】*【副炮伤害百分比】*【1-船炮减伤百分比】\n9、局内的船长【全局连击伤害】/【全局反击伤害】/【全局技能伤害】=局外的【全局连击伤害】^0.6/【全局反击伤害】^0.6/【全局技能伤害】^0.6\n10、局内的船长【普攻减伤】/【连击减伤】/【反击减伤】/【技能减伤】/【同伴减伤】属性数值=局外的【普攻减伤】* 0.7/【连击减伤】* 0.7/【反击减伤】* 0.7/【技能减伤】* 0.7/【同伴减伤】* 0.7
A14902: 301890 | B14902: 平局规则
A14903: 301891 | B14903: 1、若1场战斗后，双方未分出胜负（剩余血量均>0），则将保持上一场的血量继续战斗（上限为3场）\n2、连续战斗3场后仍然未分出胜负，则进攻方自动撤退回复活点
A14904: 301892 | B14904: PVP伤害衰减
A14905: 301893 | B14905: 1、PVP战斗中的所有伤害衰减、回血衰减等效果，在神秘海域的战斗中均生效
A14906: 301894 | B14906: 赛季结算规则
...
