Workbook

Sheet out_language_ar
A1: 0
A2: 语言总表
A3: 索引ID | B3: 内容
A4: 1*1 | B4: stack_error,n_list
A5: id | B5: text
A6: int | B6: string
A7: id | B7: text
A8: int | B8: ori_string
A9: 100001 | B9: قالب بريد بنص عادي بخلفية T | C9: T后台纯文本邮件模板 | E9: D列为简中语言表的文本，若CD列中文本冲突，以D列为准
A10: 100002 | B10: قالب بريد المكافآت + نص خلفية T | C10: T后台文本+奖励邮件模板
A11: 100003 | B11: المشروم الشجاع | C11: 菇勇者
A12: 100004 | B12: محارب | C12: 战士
A13: 100005 | B13: رامي السهام | C13: 弓箭手
A14: 100006 | B14: ساحر | C14: 法师
A15: 100007 | B15: مبارز | C15: 剑客
A16: 100008 | B16: محارب الفأس | C16: 斧武士
A17: 100009 | B17: صياد الظل | C17: 狙影猎手
A18: 100010 | B18: نشّاب | C18: 风弩手
A19: 100011 | B19: مُعالج | C19: 愈灵师
A20: 100012 | B20: الروح الشيطانية | C20: 魔灵士
A21: 100013 | B21: مبارز عظيم | C21: 大剑士
... A14322: 301876 | B14322: القواعد الهجومية | C14322: 进攻规则
A14323: 301878
A14324: 301879 | B14324: قواعد التمشيط | C14324: 扫荡规则
A14325: 301881 | B14325: القواعد الدفاعية | C14325: 防守规则
A14326: 301883
A14327: 301884 | B14327: قواعد الإحياء | C14327: 复活规则
A14328: 301886 | B14328: قواعد التراجع | C14328: 撤退规则
A14329: 301888 | B14329: قواعد القتال | C14329: 战斗规则
A14330: 301890 | B14330: قواعد التعادل | C14330: 平局规则
A14331: 301892 | B14331: إضعاف ضرر PVP | C14331: PVP伤害衰减
A14332: 301894 | B14332: قواعد تسوية الموسم | C14332: 赛季结算规则
A14333: 301896 | B14333: قواعد مآثر الحرب PVE | C14333: PVE战功规则
A14334: 301898 | B14334: قوانين مآثر الحرب PVP | C14334: PVP战功规则
A14335: 301900 | B14335: قواعد مآثر الحرب للخادم | C14335: 服务器战功规则
A14336: 301902 | B14336: الحامية | C14336: 驻守
A14337: 301903 | B14337: التحقيق | C14337: 侦查
A14338: 301904 | B14338: مشاركة | C14338: 分享
... A14603: 204837 | B14603: يتعذر بدء الاستيلاء، فترة الهُدنة من الساعة 0 إلى 8 | C14603: 0点-8点为休战期，无法发起抢占
A14604: 700000002 | C14604: 悲伤蛙称号，不需要文字
A14605: 201342 | B14605: تأثير السلاح الجبار | C14605: 神器拥有效果
A14606: 201344 | B14606: تأثير المطية | C14606: 坐骑拥有效果
A14607: 400709 | B14607: تأثير زينة الظهر | C14607: 背饰拥有效果
A14608: 201712 | B14608: مواقف عبر الخوادم ##1 | C14608: 跨服车位##1
A14609: 201724 | B14609: مكافآت ترتيب الخادم لـ مواقف عبر الخوادم | C14609: 跨服车位区服排行榜奖励
A14610: 201725 | B14610: مكافآت ترتيب الاستيلاء الشخصي لـ مواقف عبر الخوادم | C14610: 跨服车位个人抢占排行榜奖励
A14611: 201726 | B14611: مكافآت ترتيب الحامية الشخصي لـ مواقف عبر الخوادم | C14611: 跨服车位个人驻守排行榜奖励
A14612: 201731 | B14612: مواقف عبر الخوادم | C14612: 跨服车位
A14613: 401406 | B14613: mushroopy | C14613: mushroopy
A14614: 401407 | B14614: دوام الباب المكشوف | C14614: 露门永存
A14615: 401408 | B14615: DancingKing | C14615: DancingKing
A14616: 401409 | B14616: تحدث مع العالم | C14616: 与世界对话
... A15949: 600004366 | B15949: K3000 | C15949: 3000K
A15950: 600004367 | B15950: 10 | C15950: 10
A15951: 600004368 | B15951: 20 | C15951: 20
A15952: 600004369 | B15952: 50 | C15952: 50
A15953: 600004370 | B15953: 100 | C15953: 100
A15954: 600004371 | B15954: 200 | C15954: 200
A15955: 600004372 | B15955: 150 | C15955: 150
A15956: 600004373 | B15956: 500 | C15956: 500
A15957: 600004374 | B15957: 5 | C15957: 5
A15958: 600004375 | B15958: 30 | C15958: 30
A15959: 600004376 | B15959: 40 | C15959: 40
A15960: 600004377 | B15960: 1 | C15960: 1
A15961: 600004378 | B15961: 300 | C15961: 300
A15962: 600004379 | B15962: K50 | C15962: 50K
A15963: 600004380 | B15963: K150 | C15963: 150K
A15964: 600004381 | B15964: 3 | C15964: 3
A15965: 600004382 | B15965: 15 | C15965: 15
A15966: 600004383 | B15966: 7 | C15966: 7
A15967: 600004384 | B15967: 25 | C15967: 25
A15968: 104454 | B15968: 1. على اللاعب استهلاك الدعامات لفتح صدفة المحار والحصول على المكافآت بداخلها\n 2. تنقسم الجائزة الكبرى إلى نوعين اختيارية وغير اختيارية: يمكن للاعبين اختيار الجائزة الكبرى المقابلة للطبقة التي تكون فيها الجائزة الكبرى اختيارية، والحصول على دعائم الجائزة الكبرى المحددة فقط في الطبقة الغير اختيارية؛ سيتم إهداء مكافآت جميع الوحوش المتبقية في هذا المستوى للاعب بعد الفوز بالجائزة الكبرى في كل طبقة.\n 3. يمكن فتح خاصية فتح الصدفة بنقرة بعد وصول اللاعب إلى الطبقة 16 بنجاح\n 4. يمكن أيضًا تبادل دعامة اللؤلؤة التي تم الحصول عليها بالبضائع الموجودة في المتجر. | C15968: 1、玩家需要消耗道具打开蚌壳，获取蚌内的奖励\n2、大奖分为可自选和不可自选两种类型，可自选大奖的楼层中，玩家可以自主选择对应层数的大奖，而不可自选大奖的楼层中，玩家只能获得指定的大奖道具。砸中每层的大奖后，会将该层剩余所有其余蚌壳的奖励赠送给玩家\n3、玩家成功到达16层后，可以开启一键开蚌功能\n4、获取到的海珍珠道具还可以前往商店进行商品兑换
A15969: 104455 | B15969: حزمة هدايا ركوب الأمواج Ⅰ | C15969: 冲浪解暑礼包Ⅰ
A15970: 104456 | B15970: حزمة هدايا ركوب الأمواج Ⅱ | C15970: 冲浪解暑礼包Ⅱ
A15971: 104457 | B15971: حزمة هدايا ركوب الأمواج Ⅲ | C15971: 冲浪解暑礼包Ⅲ
A15972: 104458 | B15972: حزمة هدايا ركوب الأمواج Ⅳ | C15972: 冲浪解暑礼包Ⅳ
A15973: 104459 | B15973: حزمة هدايا ركوب الأمواج Ⅴ | C15973: 冲浪解暑礼包Ⅴ
A15974: 104460 | B15974: حزمة هدايا ركوب الأمواج Ⅵ | C15974: 冲浪解暑礼包Ⅵ
A15975: 104461 | B15975: حزمة فتح الصدفة Ⅰ | C15975: 开蚌礼包Ⅰ
A15976: 104462 | B15976: حزمة فتح الصدفة Ⅱ | C15976: 开蚌礼包Ⅱ
A15977: 104463 | B15977: حزمة فتح الصدفة Ⅲ | C15977: 开蚌礼包Ⅲ
A15978: 104464 | B15978: حزمة فتح الصدفة Ⅳ | C15978: 开蚌礼包Ⅳ
A15979: 104465 | B15979: حزمة فتح الصدفة Ⅴ | C15979: 开蚌礼包Ⅴ
... A18871: 104524 | B18871: تأثير الشارة: | C18871: 徽章效果:
A18872: 104525 | C18872: 职业描述：
A18873: 104509 | B18873: مشاركة الطائر الأليف في المعركة | C18873: 飞宠上阵
A18874: 104510 | B18874: تم الرهان:\n%s | C18874: 已下注：\n%s
A18875: 104511 | B18875: الرتبة: %s | C18875: 段位：%s
A18876: 104512 | B18876: وصول هذه الوظيفة إلى %s | C18876: 该职业达到%s
A18877: 104513 | B18877: عملة الشجاعة غير كافية | C18877: 勇者币不足
A18878: 104514 | B18878: السلاح | C18878: 武器
A18879: 104515 | B18879: المعدات | C18879: 装备
A18880: 104516 | B18880: الدرع | C18880: 防具
A18881: 104517 | B18881: خاص | C18881: 特殊
A18882: 104518 | B18882: الشريك | C18882: 同伴
A18883: 104519 | B18883: الجواهر | C18883: 宝石
A18884: 104520 | B18884: دعامة خاصة | C18884: 特殊道具
... A19423: 403477 | B19423: مضاعف\n +9.99 | C19423: 双倍\n+9.99
A19424: 403478 | B19424: 1000 | C19424: 1000
A19425: 403479 | B19425: 2400 | C19425: 2400
...

Sheet 注意事项
C2: 阿拉伯语从右往左阅读 程序自己拼的文本会出现问题
B5: 需要修改的内容
C6: 标黄或文本改红
B8: 1 | C8: 包装修改：
C9: 冰龙巢穴——熔焰遗迹
C10: 红包——礼盒
C11: 冰龙——火龙
B14: 2 | C14: 麻烦检查一下变量的位置 比如103528，~的位置错了
F15: 103528 | G15: يا له من محظوظ! لقد أحرز ~s 18 نقطة! | H15: 手气爆棚！##1投出了18点！
F16: 200408 | G16: وقت الفعالية: %s-%s | H16: 活动时间：##1-##2
F17: 200411 | G17: حجم العشيرة (%s/%s) | H17: 家族人数(##1/##2)
B20: 3 | D20: 变量改成
C21: n\ | D21: \n | E21: \n一定要挨在一起，不然无法导进游戏；目前的语言表是研发手动改的，可能有错误，翻译老师注意下
C22: s% | D22: 改成:点进格子是##1
C23: s~ | D23: 改成:点进格子是##1
C24: 1## | D24: 改成:点进格子是##1

Sheet 阿拉伯中文检查表
A1: 0
A2: 语言总表
A3: 索引ID | B3: 中文，用于导出（不要在原表简转繁）
A4: 1*1
A5: id
A6: int
A7: id
A8: int | B8: 英语 | D8: 中文不一样 | E8: 是否需要重新翻译
A9: 100001 | B9: T后台纯文本邮件模板 | C9: =VLOOKUP(A9,out_language_ar!A:C,3,0) | D9: =IF(C9=B9,"")
A10: 100002 | B10: T后台文本+奖励邮件模板 | C10: =VLOOKUP(A10,out_language_ar!A:C,3,0) | D10: =IF(C10=B10,"")
A11: 100003 | B11: 菇勇者 | C11: =VLOOKUP(A11,out_language_ar!A:C,3,0) | D11: =IF(C11=B11,"")
A12: 100004 | B12: 战士 | C12: =VLOOKUP(A12,out_language_ar!A:C,3,0) | D12: =IF(C12=B12,"")
A13: 100005 | B13: 弓箭手 | C13: =VLOOKUP(A13,out_language_ar!A:C,3,0) | D13: =IF(C13=B13,"")
A14: 100006 | B14: 法师 | C14: =VLOOKUP(A14,out_language_ar!A:C,3,0) | D14: =IF(C14=B14,"")
A15: 100007 | B15: 剑客 | C15: =VLOOKUP(A15,out_language_ar!A:C,3,0) | D15: =IF(C15=B15,"")
A16: 100008 | B16: 斧武士 | C16: =VLOOKUP(A16,out_language_ar!A:C,3,0) | D16: =IF(C16=B16,"")
A17: 100009 | B17: 狙影猎手 | C17: =VLOOKUP(A17,out_language_ar!A:C,3,0) | D17: =IF(C17=B17,"")
A18: 100010 | B18: 风弩手 | C18: =VLOOKUP(A18,out_language_ar!A:C,3,0) | D18: =IF(C18=B18,"")
A19: 100011 | B19: 愈灵师 | C19: =VLOOKUP(A19,out_language_ar!A:C,3,0) | D19: =IF(C19=B19,"")
A20: 100012 | B20: 魔灵士 | C20: =VLOOKUP(A20,out_language_ar!A:C,3,0) | D20: =IF(C20=B20,"")
... A1287: 101289 | B1287: 七彩葫芦 | C1287: =VLOOKUP(A1287,out_language_ar!A:C,3,0) | D1287: =IF(C1287=B1287,"")
A1288: 101290 | B1288: ~s加入家族 | C1288: =VLOOKUP(A1288,out_language_ar!A:C,3,0) | D1288: =IF(C1288=B1288,"") | E1288: 0
A1289: 101291 | B1289: ~s职务调整为~s | C1289: =VLOOKUP(A1289,out_language_ar!A:C,3,0) | D1289: =IF(C1289=B1289,"") | E1289: 0
A1290: 101292 | B1290: 族长 | C1290: =VLOOKUP(A1290,out_language_ar!A:C,3,0) | D1290: =IF(C1290=B1290,"")
A1291: 101293 | B1291: 长老 | C1291: =VLOOKUP(A1291,out_language_ar!A:C,3,0) | D1291: =IF(C1291=B1291,"")
A1292: 101294 | B1292: 家族宝贝 | C1292: =VLOOKUP(A1292,out_language_ar!A:C,3,0) | D1292: =IF(C1292=B1292,"")
A1293: 101295 | B1293: 精英 | C1293: =VLOOKUP(A1293,out_language_ar!A:C,3,0) | D1293: =IF(C1293=B1293,"")
A1294: 101296 | B1294: 成员 | C1294: =VLOOKUP(A1294,out_language_ar!A:C,3,0) | D1294: =IF(C1294=B1294,"")
A1295: 101297 | B1295: 剑首 | C1295: =VLOOKUP(A1295,out_language_ar!A:C,3,0) | D1295: =IF(C1295=B1295,"")
A1296: 101298 | B1296: 战狂 | C1296: =VLOOKUP(A1296,out_language_ar!A:C,3,0) | D1296: =IF(C1296=B1296,"")
A1297: 101299 | B1297: 影狩 | C1297: =VLOOKUP(A1297,out_language_ar!A:C,3,0) | D1297: =IF(C1297=B1297,"")
A1298: 101300 | B1298: 箭神 | C1298: =VLOOKUP(A1298,out_language_ar!A:C,3,0) | D1298: =IF(C1298=B1298,"")
A1299: 101301 | B1299: 圣导 | C1299: =VLOOKUP(A1299,out_language_ar!A:C,3,0) | D1299: =IF(C1299=B1299,"")
A1300: 101302 | B1300: 主教 | C1300: =VLOOKUP(A1300,out_language_ar!A:C,3,0) | D1300: =IF(C1300=B1300,"")
A1301: 101303 | B1301: 棒球 | C1301: =VLOOKUP(A1301,out_language_ar!A:C,3,0) | D1301: =IF(C1301=B1301,"")
... A1684: 101686 | B1684: 萌猫小耳 | C1684: =VLOOKUP(A1684,out_language_ar!A:C,3,0) | D1684: =IF(C1684=B1684,"")
A1685: 101687 | B1685: 噗叽西红柿头饰 | C1685: =VLOOKUP(A1685,out_language_ar!A:C,3,0) | D1685: =IF(C1685=B1685,"") | E1685: 0
A1686: 101688 | B1686: 萝卜头饰 | C1686: =VLOOKUP(A1686,out_language_ar!A:C,3,0) | D1686: =IF(C1686=B1686,"")
A1687: 101689 | B1687: 团圆绿粽头饰 | C1687: =VLOOKUP(A1687,out_language_ar!A:C,3,0) | D1687: =IF(C1687=B1687,"")
A1688: 101690 | B1688: 粉红章鱼头饰 | C1688: =VLOOKUP(A1688,out_language_ar!A:C,3,0) | D1688: =IF(C1688=B1688,"")
A1689: 101691 | B1689: 蛙王趴趴头饰 | C1689: =VLOOKUP(A1689,out_language_ar!A:C,3,0) | D1689: =IF(C1689=B1689,"")
A1690: 101692 | B1690: 蟾宫玉兔头饰 | C1690: =VLOOKUP(A1690,out_language_ar!A:C,3,0) | D1690: =IF(C1690=B1690,"")
A1691: 101693 | B1691: 老酋长头饰 | C1691: =VLOOKUP(A1691,out_language_ar!A:C,3,0) | D1691: =IF(C1691=B1691,"")
A1692: 101694 | B1692: 豹耳头饰 | C1692: =VLOOKUP(A1692,out_language_ar!A:C,3,0) | D1692: =IF(C1692=B1692,"")
A1693: 101695 | B1693: 懒懒企鹅头饰 | C1693: =VLOOKUP(A1693,out_language_ar!A:C,3,0) | D1693: =IF(C1693=B1693,"")
A1694: 101696 | B1694: 清爽瓜瓜帽 | C1694: =VLOOKUP(A1694,out_language_ar!A:C,3,0) | D1694: =IF(C1694=B1694,"")
A1695: 101697 | B1695: 优雅蝴蝶结 | C1695: =VLOOKUP(A1695,out_language_ar!A:C,3,0) | D1695: =IF(C1695=B1695,"")
A1696: 101698 | B1696: 花灵触角 | C1696: =VLOOKUP(A1696,out_language_ar!A:C,3,0) | D1696: =IF(C1696=B1696,"")
A1697: 101699 | B1697: 微笑南瓜角 | C1697: =VLOOKUP(A1697,out_language_ar!A:C,3,0) | D1697: =IF(C1697=B1697,"")
... A2220: 102222 | B2220: 神圣战靴 | C2220: =VLOOKUP(A2220,out_language_ar!A:C,3,0) | D2220: =IF(C2220=B2220,"")
A2221: 102223 | B2221: 恭喜~s获得~s | C2221: =VLOOKUP(A2221,out_language_ar!A:C,3,0) | D2221: =IF(C2221=B2221,"") | E2221: 0
A2222: 102232 | B2222: 点亮神灯1次 | C2222: =VLOOKUP(A2222,out_language_ar!A:C,3,0) | D2222: =IF(C2222=B2222,"")
A2223: 102233 | B2223: 击败5次敌人 | C2223: =VLOOKUP(A2223,out_language_ar!A:C,3,0) | D2223: =IF(C2223=B2223,"")
A2224: 102234 | B2224: 点亮神灯3次 | C2224: =VLOOKUP(A2224,out_language_ar!A:C,3,0) | D2224: =IF(C2224=B2224,"")
A2225: 102235 | B2225: 击败5次敌人 | C2225: =VLOOKUP(A2225,out_language_ar!A:C,3,0) | D2225: =IF(C2225=B2225,"")
A2226: 102236 | B2226: 通过关卡1-2 | C2226: =VLOOKUP(A2226,out_language_ar!A:C,3,0) | D2226: =IF(C2226=B2226,"")
A2227: 102237 | B2227: 点亮神灯5次 | C2227: =VLOOKUP(A2227,out_language_ar!A:C,3,0) | D2227: =IF(C2227=B2227,"")
A2228: 102238 | B2228: 通过关卡1-4 | C2228: =VLOOKUP(A2228,out_language_ar!A:C,3,0) | D2228: =IF(C2228=B2228,"")
A2229: 102239 | B2229: 点亮神灯5次 | C2229: =VLOOKUP(A2229,out_language_ar!A:C,3,0) | D2229: =IF(C2229=B2229,"")
A2230: 102240 | B2230: 击败5次敌人 | C2230: =VLOOKUP(A2230,out_language_ar!A:C,3,0) | D2230: =IF(C2230=B2230,"")
A2231: 102241 | B2231: 通过关卡1-5 | C2231: =VLOOKUP(A2231,out_language_ar!A:C,3,0) | D2231: =IF(C2231=B2231,"")
A2232: 102242 | B2232: 累计抽取技能15次 | C2232: =VLOOKUP(A2232,out_language_ar!A:C,3,0) | D2232: =IF(C2232=B2232,"")
A2233: 102243 | B2233: 强化技能1次 | C2233: =VLOOKUP(A2233,out_language_ar!A:C,3,0) | D2233: =IF(C2233=B2233,"")
... A3027: 103038 | B3027: 您与家族成员共同讨伐了郁郁胖头鱼，以下为本次讨伐中的伤害贡献情况。 | C3027: =VLOOKUP(A3027,out_language_ar!A:C,3,0) | D3027: =IF(C3027=B3027,"")
A3028: 103039 | B3028: 截止至上周，您已成功突破第%s层时序塔，请查收以下奖励。 | C3028: =VLOOKUP(A3028,out_language_ar!A:C,3,0) | D3028: =IF(C3028=B3028,"") | E3028: 0
A3029: 103040 | B3029: 光耀头盔 | C3029: =VLOOKUP(A3029,out_language_ar!A:C,3,0) | D3029: =IF(C3029=B3029,"")
A3030: 103041 | B3030: 光能护目镜 | C3030: =VLOOKUP(A3030,out_language_ar!A:C,3,0) | D3030: =IF(C3030=B3030,"")
A3031: 103042 | B3031: 光能刃 | C3031: =VLOOKUP(A3031,out_language_ar!A:C,3,0) | D3031: =IF(C3031=B3031,"")
A3032: 103043 | B3032: 游戏圈礼包奖励 | C3032: =VLOOKUP(A3032,out_language_ar!A:C,3,0) | D3032: =IF(C3032=B3032,"")
A3033: 103045 | B3033: 家族经验值 | C3033: =VLOOKUP(A3033,out_language_ar!A:C,3,0) | D3033: =IF(C3033=B3033,"")
A3034: 103046 | B3034: 果蔬贡品 | C3034: =VLOOKUP(A3034,out_language_ar!A:C,3,0) | D3034: =IF(C3034=B3034,"")
A3035: 103047 | B3035: 建筑点 | C3035: =VLOOKUP(A3035,out_language_ar!A:C,3,0) | D3035: =IF(C3035=B3035,"")
A3036: 103048 | B3036: 坐骑皮肤碎片 | C3036: =VLOOKUP(A3036,out_language_ar!A:C,3,0) | D3036: =IF(C3036=B3036,"")
A3037: 103049 | B3037: 初级种子 | C3037: =VLOOKUP(A3037,out_language_ar!A:C,3,0) | D3037: =IF(C3037=B3037,"")
A3038: 103050 | B3038: 高级种子 | C3038: =VLOOKUP(A3038,out_language_ar!A:C,3,0) | D3038: =IF(C3038=B3038,"")
A3039: 103051 | B3039: 特级种子 | C3039: =VLOOKUP(A3039,out_language_ar!A:C,3,0) | D3039: =IF(C3039=B3039,"")
A3040: 103052 | B3040: 高产肥料 | C3040: =VLOOKUP(A3040,out_language_ar!A:C,3,0) | D3040: =IF(C3040=B3040,"")
... A3260: 103282 | B3260: 祈灵冲刺 | C3260: =VLOOKUP(A3260,out_language_ar!A:C,3,0) | D3260: =IF(C3260=B3260,"")
A3261: 103283 | B3261: 1、家族捐献可以获得家族经验和家族贡献，家族当前每日可获得经验上限为%s \n2、提升家族等级可以增加人数上限和解锁更多家族商店的商品\n3、族长2日未上线时，将自动禅让给其他族员 | C3261: =VLOOKUP(A3261,out_language_ar!A:C,3,0) | D3261: =IF(C3261=B3261,"") | E3261: 0
A3262: 103284 | B3262: 活动排行榜奖励 | C3262: =VLOOKUP(A3262,out_language_ar!A:C,3,0) | D3262: =IF(C3262=B3262,"")
A3263: 103285 | B3263: 活动未领取奖励 | C3263: =VLOOKUP(A3263,out_language_ar!A:C,3,0) | D3263: =IF(C3263=B3263,"")
A3264: 103286 | B3264: 族长禅让 | C3264: =VLOOKUP(A3264,out_language_ar!A:C,3,0) | D3264: =IF(C3264=B3264,"")
A3265: 103287 | B3265: 禅让 | C3265: =VLOOKUP(A3265,out_language_ar!A:C,3,0) | D3265: =IF(C3265=B3265,"")
A3266: 103288 | B3266: 消耗果蔬贡品1500个 | C3266: =VLOOKUP(A3266,out_language_ar!A:C,3,0) | D3266: =IF(C3266=B3266,"")
A3267: 103289 | B3267: 消耗果蔬贡品4500个 | C3267: =VLOOKUP(A3267,out_language_ar!A:C,3,0) | D3267: =IF(C3267=B3267,"")
A3268: 103290 | B3268: 消耗果蔬贡品7500个 | C3268: =VLOOKUP(A3268,out_language_ar!A:C,3,0) | D3268: =IF(C3268=B3268,"")
A3269: 103291 | B3269: 消耗果蔬贡品12000个 | C3269: =VLOOKUP(A3269,out_language_ar!A:C,3,0) | D3269: =IF(C3269=B3269,"")
A3270: 103292 | B3270: 消耗果蔬贡品16500个 | C3270: =VLOOKUP(A3270,out_language_ar!A:C,3,0) | D3270: =IF(C3270=B3270,"")
A3271: 103293 | B3271: 消耗果蔬贡品21000个 | C3271: =VLOOKUP(A3271,out_language_ar!A:C,3,0) | D3271: =IF(C3271=B3271,"")
A3272: 103294 | B3272: 消耗果蔬贡品25500个 | C3272: =VLOOKUP(A3272,out_language_ar!A:C,3,0) | D3272: =IF(C3272=B3272,"")
A3273: 103295 | B3273: 消耗果蔬贡品27000个 | C3273: =VLOOKUP(A3273,out_language_ar!A:C,3,0) | D3273: =IF(C3273=B3273,"")
... A3422: 103447 | B3422: 1、玩家首次通过该层数关卡，可以获得一次首通奖励。\n2、根据玩家昨日达到的最高层数，发放对应的每日奖励。 | C3422: =VLOOKUP(A3422,out_language_ar!A:C,3,0) | D3422: =IF(C3422=B3422,"")
A3423: 103448 | B3423: 1、星钻可用于购买游戏内的付费内容。\n2、星钻仅可在本角色的消费中使用，其他游戏、区服角色不可使用也不可转移。\n3、星钻按照1新台币:星钻1枚的比例为您充值，并且为您付费。 | C3423: =VLOOKUP(A3423,out_language_ar!A:C,3,0) | D3423: =IF(C3423=B3423,"") | E3423: 1
A3424: 103449 | B3424: 每次抽取武魂时，会增加一点祝福值，抽中紫色品质以上的武魂时会将祝福值清空，若祝福值达到最大值后，下一抽必定会从紫色品质以上的武魂中抽取一个作为奖励 | C3424: =VLOOKUP(A3424,out_language_ar!A:C,3,0) | D3424: =IF(C3424=B3424,"")
A3425: 103450 | B3425: 星钻 | C3425: =VLOOKUP(A3425,out_language_ar!A:C,3,0) | D3425: =IF(C3425=B3425,"")
A3426: 103451 | B3426: 武魂精华 | C3426: =VLOOKUP(A3426,out_language_ar!A:C,3,0) | D3426: =IF(C3426=B3426,"")
A3427: 103452 | B3427: 武魂水晶 | C3427: =VLOOKUP(A3427,out_language_ar!A:C,3,0) | D3427: =IF(C3427=B3427,"")
A3428: 103453 | B3428: 随机绿色武魂 | C3428: =VLOOKUP(A3428,out_language_ar!A:C,3,0) | D3428: =IF(C3428=B3428,"")
A3429: 103454 | B3429: 随机蓝色武魂 | C3429: =VLOOKUP(A3429,out_language_ar!A:C,3,0) | D3429: =IF(C3429=B3429,"")
A3430: 103455 | B3430: 随机紫色武魂 | C3430: =VLOOKUP(A3430,out_language_ar!A:C,3,0) | D3430: =IF(C3430=B3430,"")
...

Sheet 翻译进度确认表
A1: 0
A2: 语言总表
A3: 索引ID | B3: 内容 | C3: 中文，用于导出（不要在原表简转繁）
A4: 1*1 | B4: stack_error,n_list
A5: id | B5: text
A6: int | B6: string
A7: id | B7: text
A8: int | B8: ori_string
A9: 100001 | B9: T Backend Text-Only Mail Template | C9: T后台纯文本邮件模板 | D9: =IFERROR(VLOOKUP(A9,out_language_ar!A:C,1,0),AAA未翻译)
A10: 100002 | B10: T Backend Text&Rewards Mail Template | C10: T后台文本+奖励邮件模板 | D10: =IFERROR(VLOOKUP(A10,out_language_ar!A:C,1,0),AAA未翻译)
A11: 100003 | B11: Shroomie | C11: 菇勇者 | D11: =IFERROR(VLOOKUP(A11,out_language_ar!A:C,1,0),AAA未翻译)
A12: 100004 | B12: Warrior | C12: 战士 | D12: =IFERROR(VLOOKUP(A12,out_language_ar!A:C,1,0),AAA未翻译)
A13: 100005 | B13: Archer | C13: 弓箭手 | D13: =IFERROR(VLOOKUP(A13,out_language_ar!A:C,1,0),AAA未翻译)
A14: 100006 | B14: Mage | C14: 法师 | D14: =IFERROR(VLOOKUP(A14,out_language_ar!A:C,1,0),AAA未翻译)
A15: 100007 | B15: Swordsman | C15: 剑客 | D15: =IFERROR(VLOOKUP(A15,out_language_ar!A:C,1,0),AAA未翻译)
A16: 100008 | B16: Axe Warrior | C16: 斧武士 | D16: =IFERROR(VLOOKUP(A16,out_language_ar!A:C,1,0),AAA未翻译)
A17: 100009 | B17: Shadow Sniper | C17: 狙影猎手 | D17: =IFERROR(VLOOKUP(A17,out_language_ar!A:C,1,0),AAA未翻译)
A18: 100010 | B18: Wind Crossbower | C18: 风弩手 | D18: =IFERROR(VLOOKUP(A18,out_language_ar!A:C,1,0),AAA未翻译)
A19: 100011 | B19: Healer | C19: 愈灵师 | D19: =IFERROR(VLOOKUP(A19,out_language_ar!A:C,1,0),AAA未翻译)
A20: 100012 | B20: Spellcaster | C20: 魔灵士 | D20: =IFERROR(VLOOKUP(A20,out_language_ar!A:C,1,0),AAA未翻译)
... A4982: 200662 | B4982: Exchange | C4982: 兑换 | D4982: =IFERROR(VLOOKUP(A4982,out_language_ar!A:C,1,0),AAA未翻译)
A4983: 200663 | B4983: 1 | C4983: 一 | D4983: =IFERROR(VLOOKUP(A4983,out_language_ar!A:C,1,0),AAA未翻译)
A4984: 200664 | B4984: 2 | C4984: 二 | D4984: =IFERROR(VLOOKUP(A4984,out_language_ar!A:C,1,0),AAA未翻译)
A4985: 200665 | B4985: 3 | C4985: 三 | D4985: =IFERROR(VLOOKUP(A4985,out_language_ar!A:C,1,0),AAA未翻译)
A4986: 200666 | B4986: 4 | C4986: 四 | D4986: =IFERROR(VLOOKUP(A4986,out_language_ar!A:C,1,0),AAA未翻译)
A4987: 200667 | B4987: 5 | C4987: 五 | D4987: =IFERROR(VLOOKUP(A4987,out_language_ar!A:C,1,0),AAA未翻译)
A4988: 200668 | B4988: 6 | C4988: 六 | D4988: =IFERROR(VLOOKUP(A4988,out_language_ar!A:C,1,0),AAA未翻译)
A4989: 200669 | B4989: 7 | C4989: 七 | D4989: =IFERROR(VLOOKUP(A4989,out_language_ar!A:C,1,0),AAA未翻译)
A4990: 200670 | B4990: 8 | C4990: 八 | D4990: =IFERROR(VLOOKUP(A4990,out_language_ar!A:C,1,0),AAA未翻译)
A4991: 200671 | B4991: 9 | C4991: 九 | D4991: =IFERROR(VLOOKUP(A4991,out_language_ar!A:C,1,0),AAA未翻译)
A4992: 200672 | B4992: Handbook | C4992: 图鉴 | D4992: =IFERROR(VLOOKUP(A4992,out_language_ar!A:C,1,0),AAA未翻译)
A4993: 200673 | B4993: Courage Challenges | C4993: 常规勇气挑战 | D4993: =IFERROR(VLOOKUP(A4993,out_language_ar!A:C,1,0),AAA未翻译)
A4994: 200674 | B4994: Exclusive Battle Trial | C4994: 专属战斗试炼 | D4994: =IFERROR(VLOOKUP(A4994,out_language_ar!A:C,1,0),AAA未翻译)
A4995: 200675 | B4995: Farm Experience | C4995: 农庄体验 | D4995: =IFERROR(VLOOKUP(A4995,out_language_ar!A:C,1,0),AAA未翻译)
A4996: 200676 | B4996: Invited Tour | C4996: 特邀行程 | D4996: =IFERROR(VLOOKUP(A4996,out_language_ar!A:C,1,0),AAA未翻译)
A4997: 200677 | B4997: World | C4997: 世界 | D4997: =IFERROR(VLOOKUP(A4997,out_language_ar!A:C,1,0),AAA未翻译)
A4998: 200678 | B4998: Family | C4998: 家族 | D4998: =IFERROR(VLOOKUP(A4998,out_language_ar!A:C,1,0),AAA未翻译)
A4999: 200679 | B4999: Private | C4999: 私聊 | D4999: =IFERROR(VLOOKUP(A4999,out_language_ar!A:C,1,0),AAA未翻译)
A5000: 200680 | B5000: News | C5000: 新闻 | D5000: =IFERROR(VLOOKUP(A5000,out_language_ar!A:C,1,0),AAA未翻译)
A5001: 200681 | B5001: Server Ranking | C5001: 服务器排名 | D5001: =IFERROR(VLOOKUP(A5001,out_language_ar!A:C,1,0),AAA未翻译)
A5002: 200682 | B5002: Personal Ranking | C5002: 个人排名 | D5002: =IFERROR(VLOOKUP(A5002,out_language_ar!A:C,1,0),AAA未翻译)
A5003: 200683 | B5003: Defense Ranking | C5003: 御敌排名 | D5003: =IFERROR(VLOOKUP(A5003,out_language_ar!A:C,1,0),AAA未翻译)
... A5005: 200685 | B5005: DMG: %s | C5005: 伤害：%s | D5005: =IFERROR(VLOOKUP(A5005,out_language_ar!A:C,1,0),AAA未翻译)
A5006: 200686 | B5006: 1 | C5006: 一个 | D5006: =IFERROR(VLOOKUP(A5006,out_language_ar!A:C,1,0),AAA未翻译)
A5007: 200687 | B5007: 2 | C5007: 两个 | D5007: =IFERROR(VLOOKUP(A5007,out_language_ar!A:C,1,0),AAA未翻译)
A5008: 200688 | B5008: 3 | C5008: 三个 | D5008: =IFERROR(VLOOKUP(A5008,out_language_ar!A:C,1,0),AAA未翻译)
A5009: 200689 | B5009: 4 | C5009: 四个 | D5009: =IFERROR(VLOOKUP(A5009,out_language_ar!A:C,1,0),AAA未翻译)
A5010: 200690 | B5010: 5 | C5010: 五个 | D5010: =IFERROR(VLOOKUP(A5010,out_language_ar!A:C,1,0),AAA未翻译)
A5011: 200691 | B5011: 6 | C5011: 六个 | D5011: =IFERROR(VLOOKUP(A5011,out_language_ar!A:C,1,0),AAA未翻译)
A5012: 200692 | B5012: 7 | C5012: 七个 | D5012: =IFERROR(VLOOKUP(A5012,out_language_ar!A:C,1,0),AAA未翻译)
A5013: 200693 | B5013: 8 | C5013: 八个 | D5013: =IFERROR(VLOOKUP(A5013,out_language_ar!A:C,1,0),AAA未翻译)
A5014: 200694 | B5014: 9 | C5014: 九个 | D5014: =IFERROR(VLOOKUP(A5014,out_language_ar!A:C,1,0),AAA未翻译)
A5015: 200695 | B5015: 10 | C5015: 十个 | D5015: =IFERROR(VLOOKUP(A5015,out_language_ar!A:C,1,0),AAA未翻译)
A5016: 200696 | B5016: Pickaxe | C5016: 镐子 | D5016: =IFERROR(VLOOKUP(A5016,out_language_ar!A:C,1,0),AAA未翻译)
A5017: 200697 | B5017: Drill | C5017: 钻头 | D5017: =IFERROR(VLOOKUP(A5017,out_language_ar!A:C,1,0),AAA未翻译)
A5018: 200698 | B5018: Bomb | C5018: 炸弹 | D5018: =IFERROR(VLOOKUP(A5018,out_language_ar!A:C,1,0),AAA未翻译)
A5019: 200699 | B5019: Login server verification failed | C5019: 登录服校验失败 | D5019: =IFERROR(VLOOKUP(A5019,out_language_ar!A:C,1,0),AAA未翻译)
A5020: 200700 | B5020: Platform login verification timeout | C5020: 平台登录验证超时 | D5020: =IFERROR(VLOOKUP(A5020,out_language_ar!A:C,1,0),AAA未翻译)
A5021: 200701 | B5021: Platform login verification failed | C5021: 平台登录验证失败 | D5021: =IFERROR(VLOOKUP(A5021,out_language_ar!A:C,1,0),AAA未翻译)
A5022: 200702 | B5022: Platform login verification encountered unknown error | C5022: 平台登录验证遇见不明错误 | D5022: =IFERROR(VLOOKUP(A5022,out_language_ar!A:C,1,0),AAA未翻译)
A5023: 200703 | B5023: Server currently under maintenance | C5023: 服务器当前处于维护状态 | D5023: =IFERROR(VLOOKUP(A5023,out_language_ar!A:C,1,0),AAA未翻译)
A5024: 200704 | B5024: Invalid Request | C5024: 错误的请求 | D5024: =IFERROR(VLOOKUP(A5024,out_language_ar!A:C,1,0),AAA未翻译)
A5025: 200705 | B5025: Verification failed | C5025: 验证失败 | D5025: =IFERROR(VLOOKUP(A5025,out_language_ar!A:C,1,0),AAA未翻译)
A5026: 200706 | B5026: Parameter error | C5026: 参数错误 | D5026: =IFERROR(VLOOKUP(A5026,out_language_ar!A:C,1,0),AAA未翻译)
A5027: 200707 | B5027: Registration closed | C5027: 关闭注册 | D5027: =IFERROR(VLOOKUP(A5027,out_language_ar!A:C,1,0),AAA未翻译)
... A5682: 201386 | B5682: Unable to teleport to this area. | C5682: 此区域无法传送 | D5682: =IFERROR(VLOOKUP(A5682,out_language_ar!A:C,1,0),AAA未翻译)
A5683: 201387 | B5683: 1 | C5683: 一个 | D5683: =IFERROR(VLOOKUP(A5683,out_language_ar!A:C,1,0),AAA未翻译)
A5684: 201388 | B5684: 2 | C5684: 两个 | D5684: =IFERROR(VLOOKUP(A5684,out_language_ar!A:C,1,0),AAA未翻译)
A5685: 201389 | B5685: 3 | C5685: 三个 | D5685: =IFERROR(VLOOKUP(A5685,out_language_ar!A:C,1,0),AAA未翻译)
A5686: 201390 | B5686: 4 | C5686: 四个 | D5686: =IFERROR(VLOOKUP(A5686,out_language_ar!A:C,1,0),AAA未翻译)
A5687: 201391 | B5687: 5 | C5687: 五个 | D5687: =IFERROR(VLOOKUP(A5687,out_language_ar!A:C,1,0),AAA未翻译)
A5688: 201392 | B5688: 6 | C5688: 六个 | D5688: =IFERROR(VLOOKUP(A5688,out_language_ar!A:C,1,0),AAA未翻译)
A5689: 201393 | B5689: 7 | C5689: 七个 | D5689: =IFERROR(VLOOKUP(A5689,out_language_ar!A:C,1,0),AAA未翻译)
A5690: 201394 | B5690: 8 | C5690: 八个 | D5690: =IFERROR(VLOOKUP(A5690,out_language_ar!A:C,1,0),AAA未翻译)
A5691: 201395 | B5691: 9 | C5691: 九个 | D5691: =IFERROR(VLOOKUP(A5691,out_language_ar!A:C,1,0),AAA未翻译)
A5692: 201396 | B5692: 10 | C5692: 十个 | D5692: =IFERROR(VLOOKUP(A5692,out_language_ar!A:C,1,0),AAA未翻译)
A5693: 201397 | B5693: Login server verification failed | C5693: 登录服校验失败 | D5693: =IFERROR(VLOOKUP(A5693,out_language_ar!A:C,1,0),AAA未翻译)
A5694: 201398 | B5694: Platform login verification timeout | C5694: 平台登录验证超时 | D5694: =IFERROR(VLOOKUP(A5694,out_language_ar!A:C,1,0),AAA未翻译)
A5695: 201399 | B5695: Platform login verification failed | C5695: 平台登录验证失败 | D5695: =IFERROR(VLOOKUP(A5695,out_language_ar!A:C,1,0),AAA未翻译)
A5696: 201400 | B5696: Platform login verification encountered unknown error | C5696: 平台登录验证遇见不明错误 | D5696: =IFERROR(VLOOKUP(A5696,out_language_ar!A:C,1,0),AAA未翻译)
A5697: 201401 | B5697: Server currently under maintenance | C5697: 服务器当前处于维护状态 | D5697: =IFERROR(VLOOKUP(A5697,out_language_ar!A:C,1,0),AAA未翻译)
A5698: 201402 | B5698: Invalid Request | C5698: 错误的请求 | D5698: =IFERROR(VLOOKUP(A5698,out_language_ar!A:C,1,0),AAA未翻译)
A5699: 201403 | B5699: Verification failed | C5699: 验证失败 | D5699: =IFERROR(VLOOKUP(A5699,out_language_ar!A:C,1,0),AAA未翻译)
A5700: 201404 | B5700: Parameter error | C5700: 参数错误 | D5700: =IFERROR(VLOOKUP(A5700,out_language_ar!A:C,1,0),AAA未翻译)
A5701: 201405 | B5701: Registration closed | C5701: 关闭注册 | D5701: =IFERROR(VLOOKUP(A5701,out_language_ar!A:C,1,0),AAA未翻译)
A5702: 201406 | B5702: All servers not opened yet | C5702: 所有服务器未开放过 | D5702: =IFERROR(VLOOKUP(A5702,out_language_ar!A:C,1,0),AAA未翻译)
A5703: 201407 | B5703: New version detected. Please restart the game for a better experience. | C5703: 检测到有新版本，请重启游戏以获得更好体验。 | D5703: =IFERROR(VLOOKUP(A5703,out_language_ar!A:C,1,0),AAA未翻译)
A5704: 201409 | B5704: In cooldown | C5704: CD冷却中 | D5704: =IFERROR(VLOOKUP(A5704,out_language_ar!A:C,1,0),AAA未翻译)
... A13262: 999300208 | B13262: Clue %s | C13262: 线索 %s | D13262: =IFERROR(VLOOKUP(A13262,out_language_ar!A:C,1,0),AAA未翻译)
A13263: 700000002 | C13263: 悲伤蛙称号，不需要文字 | D13263: =IFERROR(VLOOKUP(A13263,out_language_ar!A:C,1,0),AAA未翻译)
A13264: 202255 | B13264: You have unclaimed rewards in Mail which are about to expire. Don't forget to check them out! | C13264: 亲爱的菇菇，您有未领取的到期邮件奖励，菇妹已为您保管，请注意查收哟~ | D13264: =IFERROR(VLOOKUP(A13264,out_language_ar!A:C,1,0),AAA未翻译)
A13265: 600000001 | B13265: Pal DMG Bonus | C13265: 同伴伤害加成 | D13265: =IFERROR(VLOOKUP(A13265,out_language_ar!A:C,1,0),AAA未翻译)
A13266: 202101 | B13266: Unlocks at Floor %s | C13266: 达到%s层解锁 | D13266: =IFERROR(VLOOKUP(A13266,out_language_ar!A:C,1,0),AAA未翻译)
A13267: 700000001 | B13267: Every ##1 second(s), deal ##2% of current basic attack AoE DMG and confuse targets: each of their own attacks (basic attacks, combos, counterstrikes, and skills) will deal an extra ##3% of their current basic attack DMG to themselves. The confusion lasts ##4 second(s). (Casts 1 time immediately after battle starts.) | C13267: 每隔##1秒造成##2%当前普攻范围伤害，并使目标陷入混乱状态：目标每次攻击（普攻，连击，反击，技能）时会额外对自身造成##3%目标当前普攻伤害，持续##4秒。（战斗开始后立刻释放一次） | D13267: =IFERROR(VLOOKUP(A13267,out_language_ar!A:C,1,0),AAA未翻译)
A13268: 201062 | B13268: Please purchase Pass Pack: %s first | C13268: 请先购买通行证礼包%s | D13268: =IFERROR(VLOOKUP(A13268,out_language_ar!A:C,1,0),AAA未翻译)
A13269: 400080 | B13269: Pending Search | C13269: 待寻找 | D13269: =IFERROR(VLOOKUP(A13269,out_language_ar!A:C,1,0),AAA未翻译)
A13270: 400534 | B13270: Unlocks after clearing the stage with 10 DEF when the current Difficulty has been available for 3 days | C13270: 当前难度开放满3天且通关时防御值为10解锁扫荡 | D13270: =IFERROR(VLOOKUP(A13270,out_language_ar!A:C,1,0),AAA未翻译)
A13271: 400535 | B13271: Unlocks after clearing the stage with 10 DEF | C13271: 通关当前难度且防御值为10时解锁扫荡 | D13271: =IFERROR(VLOOKUP(A13271,out_language_ar!A:C,1,0),AAA未翻译)
A13272: 400536 | B13272: Pepe Friendship: | C13272: 悲伤蛙好感： | D13272: =IFERROR(VLOOKUP(A13272,out_language_ar!A:C,1,0),AAA未翻译)
A13273: 400537 | B13273: Pepe Universe | C13273: 悲伤蛙宇宙 | D13273: =IFERROR(VLOOKUP(A13273,out_language_ar!A:C,1,0),AAA未翻译)
...

Sheet Sheet1
A1: 0
A2: 语言总表
A3: 索引ID | B3: 内容
A4: 1*1 | B4: stack_error,n_list
A5: id | B5: text
A6: int | B6: string
A7: id | B7: text
A8: int | B8: ori_string
A9: 100001 | B9: T后台纯文本邮件模板
A10: 100002 | B10: T后台文本+奖励邮件模板
A11: 100003 | B11: 菇勇者
A12: 100004 | B12: 战士
A13: 100005 | B13: 弓箭手
A14: 100006 | B14: 法师
A15: 100007 | B15: 剑客
A16: 100008 | B16: 斧武士
A17: 100009 | B17: 狙影猎手
A18: 100010 | B18: 风弩手 | E18: ط-سيتم استبدال جميع عملات الرهان بنقاط الرهان في نهاية الفاعلية، ويستطيع اللاعبون استخدام نقاط الرهان الخاصة بهم لتبادل الدعائم في المتجر. ح-يستطيع الاعبين اكتساب أو شراء عملات الرهان في المتجر خلال مراحل الكل ضد الكل والإقصاء، وأفضل لاعب يمكن تقديم اسمه عن طريق الرهان خلال جولة الكل ضد الكل وسيتوقف الرهان عند الساعة 18:30 في يوم انتهاء الجولة، بينما تتوقف الفرق التي يمكنها التقدم خلال مرحلة الكل ضد الكل عن الرهان عند الساعة 19:30 في يوم مرحلة الإقصاء، وسيحصلون على عملات الرهان مع الإحتمالات المقابلة عند فوزهم، وسيتم إعادة نصف قطع التخمين إذا فشل الرهان.\n ز-المرحلة السادسة هي فترة الاحتفال، والتي يتم خلالها تقدير بطل هذه الدورة.\nو-المرحلة الخامسة هي المرحلة الإقصائية، حيث يتم تقسيم اللاعبين في أزواج ويتقاتلون في الساعة 20:00 من نفس اليوم، ويتقدم الفريق الفائز حتى يتم تحديد البطل.\n ه‎-المرحلة الرابعة هي مرحلة الكل ضد الكل، حيث يتم تقسيم أفضل 128 لاعبًا إلى 16 مجموعة. سيتنافس اللاعبون الثمانية في كل مجموعة في أزواج الساعة 19:00 يوم المباراة بإجمالي 7 مباريات، سيدخل أفضل لاعبين ذوي أكبر عدد من المباريات إلى أفضل 32 لاعبًا بإستخدام طريقة أفضل محاولتان من أصل ثلاثة، وسيتم تقسيم ال32 لاعبًا بعدها إلى 4 مجموعات وسيتأهل أفضل فريقين في كل مجموعة إلى المرحلة الإقصائية من ربع النهائي. إذا تماثلت الفرق الفائزة فسيحصل الفريق ذو أكبر عدد من الانتصارات الصافية على مرتبة أعلى، وسيعتمد الترتيب على علاقة الفوز بالخسارة للفريق في حال التساوي، وإذا كانت هناك حلقة مغلقة بين الفوز والخسارة فسيعتمد الترتيب على نقاط الجولة التمهيدية.\nد-المرحلة الثالثة هي فترة الإعداد، حيث يمكن للاعبين تحديد قوة الخصوم المختلفين في مرحلة الكل ضد الكل من خلال استكشاف أفضل 128 لاعبًا.\nج-المرحلة الثانية هي فترة التصنيف، وبها يستطيع اللاعبون تحدي الفرق الأُخرى من الساعة 10:00 إلى الساعة 22:00 يوميًا بعد تشكيل الفريق، ويحصل اللاعبون على 10 فرص تحدي عند تشكيل فريقًا فرديًا و 5 فرص تحدي عند تشكيل فريقًا زوجيًا. ستحصل على نتائج مختلفة بعد التحدي والانتصار على الفرق المختلفة، كما ستحصل على نقاط إضافية كلما قصر الوقت المستغرق لهزيمة الخصم، وسيتم خصم النقاط المقابلة للفرق المهزومة، وسيتأهل أعلى 128 لاعب إلى مرحلة الكل ضد الكل في نهاية فترة التصفيات.\nب-المرحلة الأولى هي فترة التسجيل، حيث يمكن للاعبين إنشاء فرقهم الخاصة أو الإنضمام إلى فرق الآخرين من خلال البحث عن تعريفات الفرق.\nأ-رابطة الفطر للفنون القتالية عبارة عن لعبة قتال جماعية مكونة من لاعبين تمتد عبر الخادم بأكمله في المنطقة، وتنقسم إلى ست مراحل.\n
A19: 100011 | B19: 愈灵师
A20: 100012 | B20: 魔灵士
A21: 100013 | B21: 大剑士
A22: 100014 | B22: 狂斗士
A23: 100015 | B23: 神射手
A24: 100016 | B24: 双弩英雄
A25: 100017 | B25: 时空咏者
A26: 100018 | B26: 风暴祭司
A27: 100019 | B27: 金币
A28: 100020 | B28: 钻石
A29: 100021 | B29: 经验
A30: 100022 | B30: 遗物碎片
... A13293: 700000003 | B13293: 增加##1%暴击,笨尼攻击有##2%概率击飞目标##3秒
A13294: 700000002
A13295: 400080 | B13295: 待寻找
A13296: 400534 | B13296: 当前难度开放满3天且通关时防御值为10解锁扫荡
A13297: 400535 | B13297: 通关当前难度且防御值为10时解锁扫荡
A13298: 400536 | B13298: 悲伤蛙好感：
A13299: 400537 | B13299: 悲伤蛙宇宙
A13300: 400538 | B13300: 躲蛙蛙
A13301: 400539 | B13301: 守卫佛系蛙
A13302: 400540 | B13302: 失眠蛙
A13303: 400541 | B13303: 星球之旅
A13304: 400542 | B13304: 高光时刻
A13305: 400543 | B13305: 打爆不开心
A13306: 400544 | B13306: 太空历险蛙
... A14889: 301877 | B14889: 1、每次进攻，都需消耗1点行动力\n2、发起进攻操作，玩家到达目标地块后进入进攻队列，按队列顺序先后挑战守军\n2、若进攻成功，进攻方击败了所有守军，则该地块的所有权变更\n3、若进攻失败，玩家阵亡，则玩家会在10分钟后在设置的复活点复活（大本营、据点Lv3均可作为复活点）
A14890: 301878
A14891: 301879 | B14891: 扫荡规则
A14892: 301880 | B14892: 1、对已占领的资源地块，可进行扫荡操作\n2、每次扫荡将消耗1点行动力，扫荡时击败守军，可获得【PVE战功】及【铁锭】（同进攻操作）
A14893: 301881 | B14893: 防守规则
A14894: 301882 | B14894: 1、驻守后将玩家算进该地块的防守队列\n2、驻守状态，每1分钟可恢复10%最大生命值的血量\n3、若防守成功，防守者击败了所有进攻者，则该地块的所有权维持原状\n4、若防守失败，所有防守者被击败，则地块归属权变更
A14895: 301883
A14896: 301884 | B14896: 复活规则
A14897: 301885 | B14897: 1、被击败后，将于50分钟后在设置的复活点复活（大本营、据点Lv3均可设置为复活点）\n2、消耗【世界树晨露】道具可跳过复活时间，快速复活
A14898: 301886 | B14898: 撤退规则
A14899: 301887 | B14899: 1、战斗中可主动进行撤退\n2、未出首个战报前进行撤退，将返还本次进攻的行动力\n3、若已经进行了战斗且出了战报结果后进行撤退，将不返还行动力\n4、撤退过程中无法进行其他操作
A14900: 301888 | B14900: 战斗规则
A14901: 301889 | B14901: 0、以下所有公式中的局外属性，为去掉局外同伴的上阵效果后的值！！\n1、局内主角生命=【局内船只生命】*(1+局外基础生命加成百分比^0.6+【局内船只生命加成】)*(1+局外全局生命加成百分比)\n2、局内主角攻击力=【局内船只攻击】*(1+局外基础攻击加成百分比^0.6+【局内船只攻击加成】）*(1+局外全局攻击加成百分比）\n3、局内主角防御=【局内船只防御】*(1+局外基础防御加成百分比^0.6+【局内船只防御加成】)*(1+局外全局防御加成百分比)\n4、局内攻速 = 局外最终攻速（除同伴加成）\n5、局内主/副炮攻击力=【局内主角攻击】\n6、局内主/副炮攻速=【局内主角攻速】 +【船炮攻速加成】\n7、局内主炮伤害=(【局内主炮攻击】-【局内对手防御】) *【普攻系数】*【1-普攻减伤】*【1+船炮伤害比例】*【1 - 船炮减伤百分比】\n8、局内副炮伤害=(【局内副炮攻击】-【【局内对手防御】) *【普攻系数】*【1-普攻减伤】*【1+船炮伤害比例 】*【副炮伤害百分比】*【1-船炮减伤百分比】\n9、局内的船长【全局连击伤害】/【全局反击伤害】/【全局技能伤害】=局外的【全局连击伤害】^0.6/【全局反击伤害】^0.6/【全局技能伤害】^0.6\n10、局内的船长【普攻减伤】/【连击减伤】/【反击减伤】/【技能减伤】/【同伴减伤】属性数值=局外的【普攻减伤】* 0.7/【连击减伤】* 0.7/【反击减伤】* 0.7/【技能减伤】* 0.7/【同伴减伤】* 0.7
A14902: 301890 | B14902: 平局规则
A14903: 301891 | B14903: 1、若1场战斗后，双方未分出胜负（剩余血量均>0），则将保持上一场的血量继续战斗（上限为3场）\n2、连续战斗3场后仍然未分出胜负，则进攻方自动撤退回复活点
A14904: 301892 | B14904: PVP伤害衰减
A14905: 301893 | B14905: 1、PVP战斗中的所有伤害衰减、回血衰减等效果，在神秘海域的战斗中均生效
A14906: 301894 | B14906: 赛季结算规则
A14907: 301895 | B14907: 1、赛季结束后，将保留【船身】的星级，其他的养成内容将在下赛季中全部重置\n2、赛季结算后，除了【白银船票】、【战功】兑换道具和所有【船身碎片】道具，所有赛季内的其他道具将被全部清除\n3、赛季结算后，将根据个人战功排名和服务器战功排名，结算赛季奖励\n4、赛季结算后，【战船抽奖】中的抽奖次数和保底次数不会被重置\n5、赛季结算后，【藏宝地】中的抽奖次数将被重置
... A17053: 600004366 | B17053: 3000K
A17054: 600004367 | B17054: 10
A17055: 600004368 | B17055: 20
A17056: 600004369 | B17056: 50
A17057: 600004370 | B17057: 100
A17058: 600004371 | B17058: 200
A17059: 600004372 | B17059: 150
A17060: 600004373 | B17060: 500
A17061: 600004374 | B17061: 5
A17062: 600004375 | B17062: 30
A17063: 600004376 | B17063: 40
A17064: 600004377 | B17064: 1
A17065: 600004378 | B17065: 300
A17066: 600004379 | B17066: 50K
A17067: 600004380 | B17067: 150K
A17068: 600004381 | B17068: 3
A17069: 600004382 | B17069: 15
A17070: 600004383 | B17070: 7
A17071: 600004384 | B17071: 25
A17072: 700030102 | B17072: 骑羽令
A17073: 700030103 | B17073: 用于在冲刺商店中兑换坐骑和背饰
A17074: 700030104 | B17074: 同心
A17075: 700030105 | B17075: 钟情
A17076: 700030106 | B17076: 烈焰啸天
A17077: 700030107 | B17077: 用于解锁坐骑烈焰啸天的道具
A17078: 700030108 | B17078: 解锁高级坐骑\n“烈焰啸天”
A17079: 700030109 | B17079: 狂风烈焰越千尺，亘古巨龙啸长空！恭喜~s解锁超级坐骑烈焰啸天！（全服同享礼盒待大佬发送）
A17080: 700030110 | B17080: 每隔10秒造成##1%当前普攻范围伤害，并使目标受到灼烧，每秒受到##2%当前普攻伤害，持续至战斗结束，最多叠加3次；提高自身##3%攻击和防御，增加##4%减伤，持续至战斗结束，最多叠加3次。（战斗开始后立刻释放一次）
A17081: 700030111 | B17081: 玩家最大生命、攻击和防御各下降##1%，10分钟内没有增加击败数则击败数减一
A17082: 700030112 | B17082: 1、每次进攻，都需消耗1点行动力\n2、发起进攻操作，玩家到达目标地块后进入进攻队列，按队列顺序先后挑战守军\n2、若进攻成功，进攻方击败了所有守军，则该地块的所有权变更\n3、若进攻失败，玩家阵亡，则玩家会在50分钟后在设置的复活点复活（大本营、据点Lv3均可作为复活点）
A17083: 700030113 | B17083: 1、玩家连续击败其他玩家达到对应数量后，获得debuff效果，百分比削弱最大生命、攻击、防御属性（每10min未再增加击败数，则击败数-1）：\n击败数【3-4】:玩家生命、攻击和防御各下降15%\n击败数【5-6】:玩家生命、攻击和防御各下降25%\n击败数【7-8】:玩家生命、攻击和防御各下降35%\n击败数【9-10】:玩家生命、攻击和防御各下降45%\n击败数【11-12】:玩家生命、攻击和防御各下降55%\n击败数【13-14】:玩家生命、攻击和防御各下降65%\n击败数【15-17】:玩家生命、攻击和防御各下降75%\n击败数【18-20】:玩家生命、攻击和防御各下降80%\n击败数【21-24】:玩家生命、攻击和防御各下降85%\n击败数【>24】:玩家生命、攻击和防御各下降90%
... A17696: 205682 | B17696: 使用完全升级，前提天赋也将升至最高等级，是否确定使用
