Workbook

Sheet out_language_ui_de
A1: 0
A2: 語言總表
A3: 索引ID | B3: 內容
A4: 1*1
A5: id | B5: text
A6: int | B6: string
A9: 100001 | B9: Handbuch | C9: 图鉴 | D9: =VLOOKUP(A9,Sheet3!A:B,2,0) | E9: D列为简中语言表的文本，若CD列中文本冲突，以D列为准
A10: 100002 | B10: Verstärken | C10: 强化 | D10: =VLOOKUP(A10,Sheet3!A:B,2,0)
A11: 100003 | B11: Fähigkeiten | C11: 技能 | D11: =VLOOKUP(A11,Sheet3!A:B,2,0)
A12: 100004 | B12: Kumpel | C12: 同伴 | D12: =VLOOKUP(A12,Sheet3!A:B,2,0)
A13: 100005 | B13: Maximales Level erreicht | C13: 已满级 | D13: =VLOOKUP(A13,Sheet3!A:B,2,0)
A14: 100006 | B14: Tägliche Aktivität | C14: 日活跃 | D14: =VLOOKUP(A14,Sheet3!A:B,2,0)
A15: 100007 | B15: Abholen | C15: 领取 | D15: =VLOOKUP(A15,Sheet3!A:B,2,0)
A16: 100008 | B16: Gehe zu | C16: 前往 | D16: =VLOOKUP(A16,Sheet3!A:B,2,0)
A17: 100009 | B17: Tägliche Aufgaben werden um 00:00 Uhr zurückgesetzt | C17: 每日0点重置每日任务 | D17: =VLOOKUP(A17,Sheet3!A:B,2,0)
A18: 100010 | B18: Aufgabe | C18: 任务 | D18: =VLOOKUP(A18,Sheet3!A:B,2,0)
A19: 100011 | B19: Tägliche kumulative Aufladung | C19: 每日累计充值 | D19: =VLOOKUP(A19,Sheet3!A:B,2,0)
A20: 100012 | B20: Kumulative Eventaufladung | C20: 活动累计充值 | D20: =VLOOKUP(A20,Sheet3!A:B,2,0)
A21: 100013 | B21: Kumulative Event-Tagesaufladung | C21: 活动累天充值 | D21: =VLOOKUP(A21,Sheet3!A:B,2,0)
... A447: 100442 | B447: Anmeldung erfolgreich: Trete der Spielgemeinschaft bei und like 2 Beiträge | C447: 签到成功判定：加入游戏圈并点赞2个帖子 | D447: =VLOOKUP(A447,Sheet3!A:B,2,0)
A448: 100443 | B448: 1 | C448: 1.游戏圈点赞2次（） | D448: =VLOOKUP(A448,Sheet3!A:B,2,0)
A449: 100444 | B449: Keine Bewerbungen vorhanden | C449: 暂无申请 | D449: =VLOOKUP(A449,Sheet3!A:B,2,0)
A450: 100445 | B450: Clanverwaltung | C450: 家族管理 | D450: =VLOOKUP(A450,Sheet3!A:B,2,0)
A451: 100446 | B451: Einlass | C451: 设置申请条件 | D451: =VLOOKUP(A451,Sheet3!A:B,2,0)
A452: 100447 | B452: Automatische Zustimmung zu Bewerbungen | C452: 自动同意申请 | D452: =VLOOKUP(A452,Sheet3!A:B,2,0)
A453: 100448 | B453: Clan gründen | C453: 创建家族 | D453: =VLOOKUP(A453,Sheet3!A:B,2,0)
A454: 100449 | B454: Gib den Clan-Namen ein | C454: 请输入家族名称 | D454: =VLOOKUP(A454,Sheet3!A:B,2,0)
A455: 100450 | B455: Maximal 6 Zeichen | C455: 最多6个字符 | D455: =VLOOKUP(A455,Sheet3!A:B,2,0)
A456: 100451 | B456: Clan auflösen | C456: 解散家族 | D456: =VLOOKUP(A456,Sheet3!A:B,2,0)
A457: 100452 | B457: Nach Eingabe von „Clan auflösen“ wird der aktuelle Clan aufgelöst | C457: 输入“解散家族”后，解散当前家族 | D457: =VLOOKUP(A457,Sheet3!A:B,2,0)
A458: 100453 | B458: Clanspende | C458: 家族捐献 | D458: =VLOOKUP(A458,Sheet3!A:B,2,0)
A459: 100454 | B459: Clanname | C459: 家族名称 | D459: =VLOOKUP(A459,Sheet3!A:B,2,0)
A460: 100455 | B460: Clan-Größe | C460: 家族人数 | D460: =VLOOKUP(A460,Sheet3!A:B,2,0)
... A3805: 700004104 | B3805: Clanpunkte | C3805: 家族积分 | D3805: =VLOOKUP(A3805,Sheet3!A:B,2,0)
A3806: 700004105 | B3806: Siegespunkte | C3806: 胜利积分
A3807: 700004106 | B3807: Niederlagenpunkte | C3807: 失败积分
A3808: 700004107 | B3808: Garantierte Punkte | C3808: 保底积分
A3809: 700004108 | B3809: Straßendurchbruch-Punkte | C3809: 破路积分
A3810: 700004109 | B3810: Clan-Platzpunkte | C3810: 家族档位积分
A3811: 700004110 | B3811: Überlebene+Tötungen | C3811: 存活数+击杀数
A3812: 700004111 | B3812: Punkte | C3812: 积分
A3813: 401319 | B3813: Begrenztes Aufladeangebot ist da | C3813: 充值优惠限定来袭
A3814: 600040038 | B3814: Frei | C3814: 空闲中
A3815: 600040039 | B3815: Die Zucht bestätigen | C3815: 确定培育
A3816: 600040037 | B3816: Nur Züchtbare anzeigen | C3816: 只显示可培育
A3817: 600040040 | B3817: Beitritt abbrechen | C3817: 取消加入
... A4601: 301643 | B4601: Kein Flugtier | C4601: 暂无飞宠
A4602: 401408 | B4602: NOT-401408
A4603: 401448 | B4603: NOT-401448 | C4603: 原语言可能挪到language了，联系策划挪回来
A4604: 401451 | B4604: NOT-401451 | C4604: 原语言可能挪到language了，联系策划挪回来
A4605: 401452 | B4605: NOT-401452 | C4605: 原语言可能挪到language了，联系策划挪回来
A4606: 401453 | B4606: NOT-401453 | C4606: 原语言可能挪到language了，联系策划挪回来
A4607: 401461 | B4607: NOT-401461 | C4607: 原语言可能挪到language了，联系策划挪回来
A4608: 401464 | B4608: NOT-401464 | C4608: 原语言可能挪到language了，联系策划挪回来
A4609: 401466 | B4609: NOT-401466 | C4609: 原语言可能挪到language了，联系策划挪回来
A4610: 401484 | B4610: NOT-401484 | C4610: 原语言可能挪到language了，联系策划挪回来
A4611: 401486 | B4611: NOT-401486 | C4611: 原语言可能挪到language了，联系策划挪回来
A4612: 401490 | B4612: NOT-401490 | C4612: 原语言可能挪到language了，联系策划挪回来
A4613: 401491 | B4613: NOT-401491 | C4613: 原语言可能挪到language了，联系策划挪回来
A4614: 401492 | B4614: NOT-401492 | C4614: 原语言可能挪到language了，联系策划挪回来
... A6273: 700023300 | B6273: Belohnungen aktualisieren in | C6273: 奖励刷新倒计时：
A6274: 700023329 | B6274: 0 | C6274: 0
A6275: 700023330 | B6275: 0.5 | C6275: 0.5
A6276: 700023331 | B6276: 1 | C6276: 1
A6277: 700023301 | B6277: Gefallene Dimension | C6277: 陷落异次元
A6278: 700023302 | B6278: Entschlüsselungssystem | C6278: 破译系统
A6279: 700023303 | B6279: Datenentschlüsselungs-Ei | C6279: 解码数据蛋
A6280: 700023304 | B6280: Erkundungsfortschritt | C6280: 探索进度
A6281: 700023305 | B6281: Top-Spieler | C6281: 顶级玩家
A6282: 700023306 | B6282: Verfolgung ausweichen | C6282: 躲避追捕
A6283: 700023307 | B6283: Ressourcenladen | C6283: 资源商店
A6284: 700023308 | B6284: Gemeinsam Bugs suchen | C6284: 一起来找bug
A6285: 700023309 | B6285: Abschlussplan | C6285: 通关计划
A6286: 700023310 | B6286: Versorgungsstation | C6286: 补给站
A6287: 700023311 | B6287: Erkundungspaket | C6287: 探索礼包
A6288: 700023312 | B6288: Datensturm | C6288: 数据风暴
... A6820: 1100136 | B6820: Heimat-Attribute | C6820: 家园词条

Sheet Sheet3
A1: 0
A2: 語言總表
A3: 索引ID | B3: 内容
A4: 1*1
A5: id | B5: text
A6: int | B6: string
A9: 100001 | B9: 图鉴
A10: 100002 | B10: 强化
A11: 100003 | B11: 技能
A12: 100004 | B12: 同伴
A13: 100005 | B13: 已满级
A14: 100006 | B14: 日活跃
A15: 100007 | B15: 领取
A16: 100008 | B16: 前往
A17: 100009 | B17: 每日0点重置每日任务
A18: 100010 | B18: 任务
A19: 100011 | B19: 每日累计充值
A20: 100012 | B20: 活动累计充值
... A1261: 300204 | B1261: 关注
A1262: 300205 | B1262: #NAME?
A1263: 300206 | B1263: 玩啊啊啊啊啊啊啊啊啊啊啊啊啊啊
A1264: 300207 | B1264: 玩家名字有点长哦：
A1265: 300208 | B1265: 乌鲁木齐
A1266: 300209 | B1266: 玩家名字六个字
A1267: 300210 | B1267: 神器拥有效果
A1268: 300211 | B1268: 百分比生命&攻击&防御：
A1269: 300212 | B1269: 招财猫猫怪
A1270: 300213 | B1270: [s1040]名字六个字符
A1271: 300214 | B1271: [s1001]\n菇勇者ssssss
A1272: 300215 | B1272: 召唤15次
A1273: 300216 | B1273: 抽卡15次
A1274: 300217 | B1274: 掉落符石数量：
... A3854: 700004111 | B3854: 积分
