Workbook

Sheet out_language_de
A1: 0
A2: 语言总表 | C2: \
A3: 索引ID | B3: 内容
A4: 1*1 | B4: stack_error,n_list
A5: id | B5: text
A6: int | B6: string
A7: id | B7: text
A8: int | B8: ori_string
A9: 100001 | B9: T Hintergrund-Plaintext-E-Mail-Vorlage | C9: T后台纯文本邮件模板 | D9: =VLOOKUP(A9,Sheet1!A:B,2,0) | E9: D列为简中语言表的文本，若CD列中文本冲突，以D列为准
A10: 100002 | B10: T Hintergrund-Text+Belohnung-E-Mail-Vorlage | C10: T后台文本+奖励邮件模板 | D10: =VLOOKUP(A10,Sheet1!A:B,2,0)
A11: 100003 | B11: Einsamer Krieger | C11: 菇勇者 | D11: =VLOOKUP(A11,Sheet1!A:B,2,0)
A12: 100004 | B12: Kämpfer | C12: 战士 | D12: =VLOOKUP(A12,Sheet1!A:B,2,0)
A13: 100005 | B13: Schütze | C13: 弓箭手 | D13: =VLOOKUP(A13,Sheet1!A:B,2,0)
A14: 100006 | B14: Magier | C14: 法师 | D14: =VLOOKUP(A14,Sheet1!A:B,2,0)
A15: 100007 | B15: Schwertkämpfer | C15: 剑客 | D15: =VLOOKUP(A15,Sheet1!A:B,2,0)
A16: 100008 | B16: Axtkrieger | C16: 斧武士 | D16: =VLOOKUP(A16,Sheet1!A:B,2,0)
A17: 100009 | B17: Scharfschützenjäger | C17: 狙影猎手 | D17: =VLOOKUP(A17,Sheet1!A:B,2,0)
A18: 100010 | B18: Windarmbrustschütze | C18: 风弩手 | D18: =VLOOKUP(A18,Sheet1!A:B,2,0)
A19: 100011 | B19: Heiler | C19: 愈灵师 | D19: =VLOOKUP(A19,Sheet1!A:B,2,0)
A20: 100012 | B20: Magus | C20: 魔灵士 | D20: =VLOOKUP(A20,Sheet1!A:B,2,0)
A21: 100013 | B21: Großschwertkämpfer | C21: 大剑士 | D21: =VLOOKUP(A21,Sheet1!A:B,2,0)
... A4418: 200094 | B4418: %s verbrauchen? | C4418: 是否消耗%s | D4418: =VLOOKUP(A4418,Sheet1!A:B,2,0)
A4419: 700024509 | B4419: ##1*##2 verbrauchen? | C4419: 是否消耗##1*##2
A4420: 200095 | B4420: Neuguss | C4420: 重铸 | D4420: =VLOOKUP(A4420,Sheet1!A:B,2,0)
A4421: 200096 | B4421: <b><color=#544231>Meilenstein: Meilenwert erreicht </color> <color=#ab630e>%s</color></b> | C4421: <b><color=#544231>里程目标：里程值达到</color><color=#ab630e>%s</color></b> | D4421: =VLOOKUP(A4421,Sheet1!A:B,2,0)
A4422: 200097 | B4422: <b><color=#544231>Meilenstein: Durchgang der Eventinstanz </color> <color=#ab630e>%s</color></b> | C4422: <b><color=#544231>里程目标：通关活动副本</color><color=#ab630e>%s</color></b> | D4422: =VLOOKUP(A4422,Sheet1!A:B,2,0)
A4423: 200098 | B4423: Aufstellungseffekt: %s | C4423: 上阵效果：%s | D4423: =VLOOKUP(A4423,Sheet1!A:B,2,0)
A4424: 200099 | B4424: Grundlegende HP & Angriff & VTD +%s% | C4424: 基础生命&攻击&防御+%s% | D4424: =VLOOKUP(A4424,Sheet1!A:B,2,0)
A4425: 200100 | B4425: Es gibt keinen Kumpel auszurüsten | C4425: 没有可以装配的同伴 | D4425: =VLOOKUP(A4425,Sheet1!A:B,2,0)
A4426: 200101 | B4426: Freischalten | C4426: 解锁 | D4426: =VLOOKUP(A4426,Sheet1!A:B,2,0)
A4427: 200102 | B4427: Eventzeit: %s | C4427: 活动时间：%s | D4427: =VLOOKUP(A4427,Sheet1!A:B,2,0)
A4428: 200103 | B4428: Grundattribute | C4428: 基础属性 | D4428: =VLOOKUP(A4428,Sheet1!A:B,2,0)
A4429: 200104 | B4429: Hochwertiges Attribut | C4429: 高级属性 | D4429: =VLOOKUP(A4429,Sheet1!A:B,2,0)
A4430: 200105 | B4430: Endgültiges Attibut | C4430: 最终属性 | D4430: =VLOOKUP(A4430,Sheet1!A:B,2,0)
A4431: 200106 | B4431: Nicht genügend Level | C4431: 等级不足 | D4431: =VLOOKUP(A4431,Sheet1!A:B,2,0)
... A13199: 999100279 | B13199: Nach Start des Kampfes, jeder Grundangriff erhöht die VTD um ##1%, bis zu 40-mal stapelbar, nach Vollstapelung ##2% Angriffsbonus | C13199: 战斗开始后，每次普攻提高##1%防御，最多叠加40次，叠满后获得##2%攻击 | D13199: =VLOOKUP(A13199,Sheet1!A:B,2,0)
A13200: 700000002 | C13200: 悲伤蛙称号，不需要文字 | D13200: =VLOOKUP(A13200,Sheet1!A:B,2,0)
A13201: 202255 | B13201: Lieber Pilz, du hast eine abgelaufene E-Mail-Belohnung, die du noch nicht abgeholt hast. Ich habe sie für dich aufbewahrt, bitte hole sie rechtzeitig ab! | C13201: 亲爱的菇菇，您有未领取的到期邮件奖励，菇妹已为您保管，请注意查收哟~ | D13201: =VLOOKUP(A13201,Sheet1!A:B,2,0)
A13202: 600000001 | B13202: Kumpel-Schaden Bonus | C13202: 同伴伤害加成 | D13202: =VLOOKUP(A13202,Sheet1!A:B,2,0)
A13203: 202101 | B13203: Nach Erreichen der Ebene %s freischalten | C13203: 达到%s层解锁 | D13203: =VLOOKUP(A13203,Sheet1!A:B,2,0)
A13204: 700000001 | B13204: Verursacht alle ##1 Sek. ##2% des aktuellen Bereichsschadens des Grundangriffs und versetzt das Ziel in Verwirrung: Jeder vom Ziel ausgeführte Angriff (Grundangriff, Kombo, Konter, Fähigkeit) verursacht zusätzlich ##3% Sek. lang ##4 des aktuellen Grundangriffsschadens des Ziels an ihm selbst. (wird einmal sofort bei Kampfbeginn freigegeben) | C13204: 每隔##1秒造成##2%当前普攻范围伤害，并使目标陷入混乱状态：目标每次攻击（普攻，连击，反击，技能）时会额外对自身造成##3%目标当前普攻伤害，持续##4秒。（战斗开始后立刻释放一次） | D13204: =VLOOKUP(A13204,Sheet1!A:B,2,0)
A13205: 400080 | B13205: Zu finden | C13205: 待寻找 | D13205: =VLOOKUP(A13205,Sheet1!A:B,2,0)
A13206: 400534 | B13206: Überfall wird freigeschaltet, sobald die aktuelle Schwierigkeit 3 Tage lange verfügbar ist und die VTD beim Abschluss 10 beträgt | C13206: 当前难度开放满3天且通关时防御值为10解锁扫荡 | D13206: =VLOOKUP(A13206,Sheet1!A:B,2,0)
A13207: 400535 | B13207: Bestehe die aktuelle Schwierigkeit mit 10 VTD, um Überfall freizuschalten | C13207: 通关当前难度且防御值为10时解锁扫荡 | D13207: =VLOOKUP(A13207,Sheet1!A:B,2,0)
A13208: 400536 | B13208: Sympathie von Frosch Pepe: | C13208: 悲伤蛙好感： | D13208: =VLOOKUP(A13208,Sheet1!A:B,2,0)
A13209: 400537 | B13209: Universum von Pepe | C13209: 悲伤蛙宇宙 | D13209: =VLOOKUP(A13209,Sheet1!A:B,2,0)
A13210: 400538 | B13210: Pepe verstecken | C13210: 躲蛙蛙 | D13210: =VLOOKUP(A13210,Sheet1!A:B,2,0)
A13211: 400539 | B13211: Bewache Beschaulichen Pepe | C13211: 守卫佛系蛙 | D13211: =VLOOKUP(A13211,Sheet1!A:B,2,0)
A13212: 400540 | B13212: Schlafloser Pepe | C13212: 失眠蛙 | D13212: =VLOOKUP(A13212,Sheet1!A:B,2,0)
... A14627: 301877 | B14627: 1. Jeder Angriff verbraucht 1 Punkt Aktionskraft\n2. Beim Angriff trittst du in die Angriffswarteschlange ein, wenn du auf dem Zielgrundstück ankommst, und forderst die VTDeidiger entsprechend der Reihenfolge in der Warteschlange heraus\n3. Wenn der Angriff erfolgreich ist und die Angriffseite alle VTDeidiger besiegt hat, gehört dieses Grundstück dem Angreifer\n4. Wenn der Angriff fehlschlägt und du getötet wirst, wirst du nach 10 Minuten an dem eingestellten Wiederbelebungspunkt wiederbelebt (Basislager und Stützpunkt Lv.3 können als Wiederbelebungspunkt dienen) | C14627: 1、每次进攻，都需消耗1点行动力\n2、发起进攻操作，玩家到达目标地块后进入进攻队列，按队列顺序先后挑战守军\n2、若进攻成功，进攻方击败了所有守军，则该地块的所有权变更\n3、若进攻失败，玩家阵亡，则玩家会在10分钟后在设置的复活点复活（大本营、据点Lv3均可作为复活点） | D14627: =VLOOKUP(A14627,Sheet1!A:B,2,0)
A14628: 301878 | D14628: =VLOOKUP(A14628,Sheet1!A:B,2,0)
A14629: 301879 | B14629: Überfallregeln | C14629: 扫荡规则 | D14629: =VLOOKUP(A14629,Sheet1!A:B,2,0)
A14630: 301880 | B14630: 1. Du kannst die besetzten Ressource-Grundstücke überfallen\n2. Jeder Überfall verbraucht 1 Punkt Aktionskraft. Wenn du beim Überfall die VTDeidiger besiegst, erhältst du [PVE-Kampfleistung] und [Eisenbarren] (wie beim Angriff) | C14630: 1、对已占领的资源地块，可进行扫荡操作\n2、每次扫荡将消耗1点行动力，扫荡时击败守军，可获得【PVE战功】及【铁锭】（同进攻操作） | D14630: =VLOOKUP(A14630,Sheet1!A:B,2,0)
A14631: 301881 | B14631: VTDeidungsregeln | C14631: 防守规则 | D14631: =VLOOKUP(A14631,Sheet1!A:B,2,0)
A14632: 301882 | B14632: 1. Für Stationierung trittst du in die VTDsschlange des Grundstücks ein\n2. Während der Stationierung werden 10% deiner maximalen HP pro Minute wiederhergestellt\n3. Wenn die VTD erfolgreich ist und die VTDsseite alle Angreifer besiegt hat, bleibt der Besitz dieses Grundstücks bei den VTDeidigern\n4. Wenn die VTD fehlschlägt und alle VTDeidiger besiegt werden, geht der Besitz dieses Grundstücks an die Angreifer über | C14632: 1、驻守后将玩家算进该地块的防守队列\n2、驻守状态，每1分钟可恢复10%最大生命值的血量\n3、若防守成功，防守者击败了所有进攻者，则该地块的所有权维持原状\n4、若防守失败，所有防守者被击败，则地块归属权变更 | D14632: =VLOOKUP(A14632,Sheet1!A:B,2,0)
A14633: 301883 | D14633: =VLOOKUP(A14633,Sheet1!A:B,2,0)
A14634: 301884 | B14634: Wiederbelebungsregeln | C14634: 复活规则 | D14634: =VLOOKUP(A14634,Sheet1!A:B,2,0)
A14635: 301885 | B14635: 1. Wenn du besiegt wirst, wirst du nach 50 Minuten an dem eingestellten Wiederbelebungspunkt wiederbelebt (Basislager und Stützpunkt Lv.3 können als Wiederbelebungspunkt dienen)\n2. Durch Verbrauchen des Gegenstands [Tau vom Weltenbaum] kannst du sofort wiederbelebt werden, ohne 50 Minuten zu warten | C14635: 1、被击败后，将于50分钟后在设置的复活点复活（大本营、据点Lv3均可设置为复活点）\n2、消耗【世界树晨露】道具可跳过复活时间，快速复活 | D14635: =VLOOKUP(A14635,Sheet1!A:B,2,0)
A14636: 301886 | B14636: Rückzugsregeln | C14636: 撤退规则 | D14636: =VLOOKUP(A14636,Sheet1!A:B,2,0)
A14637: 301887 | B14637: 1. Du kannst dich während des Kampfes aktiv zurückziehen\n2. Wenn du dich vor dem ersten Kampfbericht zurückziehst, erhältst du die Aktionskraft dieses Angriffs zurück\n3. Wenn du dich nach Beginn des Kampfes und Veröffentlichung des Kampfberichts zurückziehst, erhältst du keine Aktionskraft zurück\n4. Keine andere Aktionen während des Rückzugs möglich | C14637: 1、战斗中可主动进行撤退\n2、未出首个战报前进行撤退，将返还本次进攻的行动力\n3、若已经进行了战斗且出了战报结果后进行撤退，将不返还行动力\n4、撤退过程中无法进行其他操作 | D14637: =VLOOKUP(A14637,Sheet1!A:B,2,0)
A14638: 301888 | B14638: Kampfregeln | C14638: 战斗规则 | D14638: =VLOOKUP(A14638,Sheet1!A:B,2,0)
A14639: 301890 | B14639: Gleichstandregeln | C14639: 平局规则 | D14639: =VLOOKUP(A14639,Sheet1!A:B,2,0)
A14640: 301891 | B14640: 1. Wenn nach einem Kampf keine der beiden Seiten als Sieger hervorgegangen ist (beide Seite mit verbleibenden HP >0), führen sie einen weiteren Kampf mit HP des vorherigen Kampfes durch (maximal 3 aufeinanderfolgende Kämpfe)\n2. Wenn es nach 3 aufeinanderfolgenden Kämpfen immer noch keinen Sieger gibt, ziehen sich die Angreifer automatisch zum Wiederbelebungspunkt zurück | C14640: 1、若1场战斗后，双方未分出胜负（剩余血量均>0），则将保持上一场的血量继续战斗（上限为3场）\n2、连续战斗3场后仍然未分出胜负，则进攻方自动撤退回复活点 | D14640: =VLOOKUP(A14640,Sheet1!A:B,2,0)
A14641: 301892 | B14641: PVP-Schadensabschwächung | C14641: PVP伤害衰减 | D14641: =VLOOKUP(A14641,Sheet1!A:B,2,0)
A14642: 301893 | B14642: 1. Alle Abschwächungseffekte wie Schadensabschwächung und HP-Erholungsabschwächung in PVP-Kämpfen werden auch in Kämpfen im Mystischen Meer wirksam | C14642: 1、PVP战斗中的所有伤害衰减、回血衰减等效果，在神秘海域的战斗中均生效 | D14642: =VLOOKUP(A14642,Sheet1!A:B,2,0)
A14643: 301894 | B14643: Saisonabrechnungsregeln | C14643: 赛季结算规则 | D14643: =VLOOKUP(A14643,Sheet1!A:B,2,0)
A14644: 301895 | B14644: 1. Nach dem Ende der Saison wird die Sternstufe von [Schiffskörper] beibehalten. Alle anderen Entwicklungsinhalte werden in der nächsten Saison zurückgesetzt\n2. Nach der Saisonabrechnung werden alle Gegenstände in der Saison gelöscht, mit Ausnahme von [Silber-Fahrkarte], Gegenständen zum Tauschen von [Kampferfolg] und allen [Splitter vom Schiffskörper]\n3. Nach der Saisonabrechnung werden die Saisonbelohnungen entsprechend der persönlichen Kampferfolgsrangliste und der Server-Kampferfolgsrangliste abgerechnet\n4. Nach der Saisonabrechnung werden die Ziehungsanzahl und die garantierte Ziehungsanzahl in [Schlachtschiff-Verlosung] nicht zurückgesetzt\n5. Nach der Saisonabrechnung wird die Ziehungsanzahl in [Schatzversteck] zurückgesetzt | C14644: 1、赛季结束后，将保留【船身】的星级，其他的养成内容将在下赛季中全部重置\n2、赛季结算后，除了【白银船票】、【战功】兑换道具和所有【船身碎片】道具，所有赛季内的其他道具将被全部清除\n3、赛季结算后，将根据个人战功排名和服务器战功排名，结算赛季奖励\n4、赛季结算后，【战船抽奖】中的抽奖次数和保底次数不会被重置\n5、赛季结算后，【藏宝地】中的抽奖次数将被重置 | D14644: =VLOOKUP(A14644,Sheet1!A:B,2,0)
A14645: 301896 | B14645: Regeln für PVE-Kampfleistung | C14645: PVE战功规则 | D14645: =VLOOKUP(A14645,Sheet1!A:B,2,0)
... A16307: 600004366 | B16307: 3000K | C16307: 3000K | D16307: =VLOOKUP(A16307,Sheet1!A:B,2,0)
A16308: 600004367 | B16308: 10 | C16308: 10 | D16308: =VLOOKUP(A16308,Sheet1!A:B,2,0)
A16309: 600004368 | B16309: 20 | C16309: 20 | D16309: =VLOOKUP(A16309,Sheet1!A:B,2,0)
A16310: 600004369 | B16310: 50 | C16310: 50 | D16310: =VLOOKUP(A16310,Sheet1!A:B,2,0)
A16311: 600004370 | B16311: 100 | C16311: 100 | D16311: =VLOOKUP(A16311,Sheet1!A:B,2,0)
A16312: 600004371 | B16312: 200 | C16312: 200 | D16312: =VLOOKUP(A16312,Sheet1!A:B,2,0)
A16313: 600004372 | B16313: 150 | C16313: 150 | D16313: =VLOOKUP(A16313,Sheet1!A:B,2,0)
A16314: 600004373 | B16314: 500 | C16314: 500 | D16314: =VLOOKUP(A16314,Sheet1!A:B,2,0)
A16315: 600004374 | B16315: 5 | C16315: 5 | D16315: =VLOOKUP(A16315,Sheet1!A:B,2,0)
A16316: 600004375 | B16316: 30 | C16316: 30 | D16316: =VLOOKUP(A16316,Sheet1!A:B,2,0)
A16317: 600004376 | B16317: 40 | C16317: 40 | D16317: =VLOOKUP(A16317,Sheet1!A:B,2,0)
A16318: 600004377 | B16318: 1 | C16318: 1 | D16318: =VLOOKUP(A16318,Sheet1!A:B,2,0)
A16319: 600004378 | B16319: 300 | C16319: 300 | D16319: =VLOOKUP(A16319,Sheet1!A:B,2,0)
A16320: 600004379 | B16320: 50K | C16320: 50K | D16320: =VLOOKUP(A16320,Sheet1!A:B,2,0)
A16321: 600004380 | B16321: 150K | C16321: 150K | D16321: =VLOOKUP(A16321,Sheet1!A:B,2,0)
A16322: 600004381 | B16322: 3 | C16322: 3 | D16322: =VLOOKUP(A16322,Sheet1!A:B,2,0)
A16323: 600004382 | B16323: 15 | C16323: 15 | D16323: =VLOOKUP(A16323,Sheet1!A:B,2,0)
A16324: 600004383 | B16324: 7 | C16324: 7 | D16324: =VLOOKUP(A16324,Sheet1!A:B,2,0)
A16325: 600004384 | B16325: 25 | C16325: 25 | D16325: =VLOOKUP(A16325,Sheet1!A:B,2,0)
A16326: 104454 | B16326: 1. Du musst Gegenstände verbrauchen, um eine Muschel zu öffnen und die Belohnung darin zu erhalten.\n2. Es gibt 2 Arten von Hauptpreisen: wählbarer Hauptpreis und nicht wählbarer Hauptpreis. In der Ebene von wählbaren Hauptpreisen kannst du Hauptpreise selbst wählen, während du in der Ebene von nicht wählbaren Hauptpreisen nur die angegebenen Hauptpreise erhalten kannst. Wenn du den Hauptpreis einer Ebene erhältst, werden dir die Belohnungen in allen verbleibenden Muscheln dieser Ebene vergeben.\n3. Du kannst die Funktion „Muschelöffnen mit einem Klick“ aktivieren, nachdem du die 16. Ebene erreicht hast.\n4. Die erhaltenen Perlen können auch gegen Waren im Laden eingetauscht werden. | C16326: 1、玩家需要消耗道具打开蚌壳，获取蚌内的奖励\n2、大奖分为可自选和不可自选两种类型，可自选大奖的楼层中，玩家可以自主选择对应层数的大奖，而不可自选大奖的楼层中，玩家只能获得指定的大奖道具。砸中每层的大奖后，会将该层剩余所有其余蚌壳的奖励赠送给玩家\n3、玩家成功到达16层后，可以开启一键开蚌功能\n4、获取到的海珍珠道具还可以前往商店进行商品兑换 | D16326: =VLOOKUP(A16326,Sheet1!A:B,2,0)
A16327: 104455 | B16327: Surfenpaket I | C16327: 冲浪解暑礼包Ⅰ | D16327: =VLOOKUP(A16327,Sheet1!A:B,2,0)
A16328: 104456 | B16328: Surfenpaket II | C16328: 冲浪解暑礼包Ⅱ | D16328: =VLOOKUP(A16328,Sheet1!A:B,2,0)
A16329: 104457 | B16329: Surfenpaket III | C16329: 冲浪解暑礼包Ⅲ | D16329: =VLOOKUP(A16329,Sheet1!A:B,2,0)
A16330: 104458 | B16330: Surfenpaket IV | C16330: 冲浪解暑礼包Ⅳ | D16330: =VLOOKUP(A16330,Sheet1!A:B,2,0)
A16331: 104459 | B16331: Surfenpaket V | C16331: 冲浪解暑礼包Ⅴ | D16331: =VLOOKUP(A16331,Sheet1!A:B,2,0)
A16332: 104460 | B16332: Surfenpaket VI | C16332: 冲浪解暑礼包Ⅵ | D16332: =VLOOKUP(A16332,Sheet1!A:B,2,0)
A16333: 104461 | B16333: Muschelöffnen-Paket I | C16333: 开蚌礼包Ⅰ | D16333: =VLOOKUP(A16333,Sheet1!A:B,2,0)
A16334: 104462 | B16334: Muschelöffnen-Paket II | C16334: 开蚌礼包Ⅱ | D16334: =VLOOKUP(A16334,Sheet1!A:B,2,0)
A16335: 104463 | B16335: Muschelöffnen-Paket III | C16335: 开蚌礼包Ⅲ | D16335: =VLOOKUP(A16335,Sheet1!A:B,2,0)
A16336: 104464 | B16336: Muschelöffnen-Paket IV | C16336: 开蚌礼包Ⅳ | D16336: =VLOOKUP(A16336,Sheet1!A:B,2,0)
A16337: 104465 | B16337: Muschelöffnen-Paket V | C16337: 开蚌礼包Ⅴ | D16337: =VLOOKUP(A16337,Sheet1!A:B,2,0)
... A17248: 700030321 | B17248: Überlebenszeit nicht weniger als 60 Sek. im Herausforderungslevel | C17248: 在挑战关卡中存活60秒 | D17248: =VLOOKUP(A17248,Sheet1!A:B,2,0)
...

Sheet Sheet1
A1: 0
A2: 语言总表
A3: 索引ID | B3: 内容
A4: 1*1 | B4: stack_error,n_list
A5: id | B5: text
A6: int | B6: string
A7: id | B7: text
A8: int | B8: ori_string
A9: 100001 | B9: T后台纯文本邮件模板
A10: 100002 | B10: T后台文本+奖励邮件模板
A11: 100003 | B11: 菇勇者
A12: 100004 | B12: 战士
A13: 100005 | B13: 弓箭手
A14: 100006 | B14: 法师
A15: 100007 | B15: 剑客
A16: 100008 | B16: 斧武士
A17: 100009 | B17: 狙影猎手
A18: 100010 | B18: 风弩手
A19: 100011 | B19: 愈灵师
A20: 100012 | B20: 魔灵士
... A13293: 700000003 | B13293: 增加##1%暴击,笨尼攻击有##2%概率击飞目标##3秒
A13294: 700000002
A13295: 400080 | B13295: 待寻找
A13296: 400534 | B13296: 当前难度开放满3天且通关时防御值为10解锁扫荡
A13297: 400535 | B13297: 通关当前难度且防御值为10时解锁扫荡
A13298: 400536 | B13298: 悲伤蛙好感：
A13299: 400537 | B13299: 悲伤蛙宇宙
A13300: 400538 | B13300: 躲蛙蛙
A13301: 400539 | B13301: 守卫佛系蛙
A13302: 400540 | B13302: 失眠蛙
A13303: 400541 | B13303: 星球之旅
A13304: 400542 | B13304: 高光时刻
A13305: 400543 | B13305: 打爆不开心
A13306: 400544 | B13306: 太空历险蛙
... A14889: 301877 | B14889: 1、每次进攻，都需消耗1点行动力\n2、发起进攻操作，玩家到达目标地块后进入进攻队列，按队列顺序先后挑战守军\n2、若进攻成功，进攻方击败了所有守军，则该地块的所有权变更\n3、若进攻失败，玩家阵亡，则玩家会在10分钟后在设置的复活点复活（大本营、据点Lv3均可作为复活点）
A14890: 301878
A14891: 301879 | B14891: 扫荡规则
A14892: 301880 | B14892: 1、对已占领的资源地块，可进行扫荡操作\n2、每次扫荡将消耗1点行动力，扫荡时击败守军，可获得【PVE战功】及【铁锭】（同进攻操作）
A14893: 301881 | B14893: 防守规则
A14894: 301882 | B14894: 1、驻守后将玩家算进该地块的防守队列\n2、驻守状态，每1分钟可恢复10%最大生命值的血量\n3、若防守成功，防守者击败了所有进攻者，则该地块的所有权维持原状\n4、若防守失败，所有防守者被击败，则地块归属权变更
A14895: 301883
A14896: 301884 | B14896: 复活规则
A14897: 301885 | B14897: 1、被击败后，将于50分钟后在设置的复活点复活（大本营、据点Lv3均可设置为复活点）\n2、消耗【世界树晨露】道具可跳过复活时间，快速复活
A14898: 301886 | B14898: 撤退规则
A14899: 301887 | B14899: 1、战斗中可主动进行撤退\n2、未出首个战报前进行撤退，将返还本次进攻的行动力\n3、若已经进行了战斗且出了战报结果后进行撤退，将不返还行动力\n4、撤退过程中无法进行其他操作
A14900: 301888 | B14900: 战斗规则
A14901: 301889 | B14901: 0、以下所有公式中的局外属性，为去掉局外同伴的上阵效果后的值！！\n1、局内主角生命=【局内船只生命】*(1+局外基础生命加成百分比^0.6+【局内船只生命加成】)*(1+局外全局生命加成百分比)\n2、局内主角攻击力=【局内船只攻击】*(1+局外基础攻击加成百分比^0.6+【局内船只攻击加成】）*(1+局外全局攻击加成百分比）\n3、局内主角防御=【局内船只防御】*(1+局外基础防御加成百分比^0.6+【局内船只防御加成】)*(1+局外全局防御加成百分比)\n4、局内攻速 = 局外最终攻速（除同伴加成）\n5、局内主/副炮攻击力=【局内主角攻击】\n6、局内主/副炮攻速=【局内主角攻速】 +【船炮攻速加成】\n7、局内主炮伤害=(【局内主炮攻击】-【局内对手防御】) *【普攻系数】*【1-普攻减伤】*【1+船炮伤害比例】*【1 - 船炮减伤百分比】\n8、局内副炮伤害=(【局内副炮攻击】-【【局内对手防御】) *【普攻系数】*【1-普攻减伤】*【1+船炮伤害比例 】*【副炮伤害百分比】*【1-船炮减伤百分比】\n9、局内的船长【全局连击伤害】/【全局反击伤害】/【全局技能伤害】=局外的【全局连击伤害】^0.6/【全局反击伤害】^0.6/【全局技能伤害】^0.6\n10、局内的船长【普攻减伤】/【连击减伤】/【反击减伤】/【技能减伤】/【同伴减伤】属性数值=局外的【普攻减伤】* 0.7/【连击减伤】* 0.7/【反击减伤】* 0.7/【技能减伤】* 0.7/【同伴减伤】* 0.7
A14902: 301890 | B14902: 平局规则
A14903: 301891 | B14903: 1、若1场战斗后，双方未分出胜负（剩余血量均>0），则将保持上一场的血量继续战斗（上限为3场）\n2、连续战斗3场后仍然未分出胜负，则进攻方自动撤退回复活点
A14904: 301892 | B14904: PVP伤害衰减
A14905: 301893 | B14905: 1、PVP战斗中的所有伤害衰减、回血衰减等效果，在神秘海域的战斗中均生效
A14906: 301894 | B14906: 赛季结算规则
A14907: 301895 | B14907: 1、赛季结束后，将保留【船身】的星级，其他的养成内容将在下赛季中全部重置\n2、赛季结算后，除了【白银船票】、【战功】兑换道具和所有【船身碎片】道具，所有赛季内的其他道具将被全部清除\n3、赛季结算后，将根据个人战功排名和服务器战功排名，结算赛季奖励\n4、赛季结算后，【战船抽奖】中的抽奖次数和保底次数不会被重置\n5、赛季结算后，【藏宝地】中的抽奖次数将被重置
... A17053: 600004366 | B17053: 3000K
A17054: 600004367 | B17054: 10
A17055: 600004368 | B17055: 20
A17056: 600004369 | B17056: 50
A17057: 600004370 | B17057: 100
A17058: 600004371 | B17058: 200
A17059: 600004372 | B17059: 150
A17060: 600004373 | B17060: 500
A17061: 600004374 | B17061: 5
A17062: 600004375 | B17062: 30
A17063: 600004376 | B17063: 40
A17064: 600004377 | B17064: 1
A17065: 600004378 | B17065: 300
A17066: 600004379 | B17066: 50K
A17067: 600004380 | B17067: 150K
A17068: 600004381 | B17068: 3
A17069: 600004382 | B17069: 15
A17070: 600004383 | B17070: 7
A17071: 600004384 | B17071: 25
A17072: 700030102 | B17072: 骑羽令
A17073: 700030103 | B17073: 用于在冲刺商店中兑换坐骑和背饰
A17074: 700030104 | B17074: 同心
A17075: 700030105 | B17075: 钟情
A17076: 700030106 | B17076: 烈焰啸天
A17077: 700030107 | B17077: 用于解锁坐骑烈焰啸天的道具
A17078: 700030108 | B17078: 解锁高级坐骑\n“烈焰啸天”
A17079: 700030109 | B17079: 狂风烈焰越千尺，亘古巨龙啸长空！恭喜~s解锁超级坐骑烈焰啸天！（全服同享礼盒待大佬发送）
A17080: 700030110 | B17080: 每隔10秒造成##1%当前普攻范围伤害，并使目标受到灼烧，每秒受到##2%当前普攻伤害，持续至战斗结束，最多叠加3次；提高自身##3%攻击和防御，增加##4%减伤，持续至战斗结束，最多叠加3次。（战斗开始后立刻释放一次）
A17081: 700030111 | B17081: 玩家最大生命、攻击和防御各下降##1%，10分钟内没有增加击败数则击败数减一
A17082: 700030112 | B17082: 1、每次进攻，都需消耗1点行动力\n2、发起进攻操作，玩家到达目标地块后进入进攻队列，按队列顺序先后挑战守军\n2、若进攻成功，进攻方击败了所有守军，则该地块的所有权变更\n3、若进攻失败，玩家阵亡，则玩家会在50分钟后在设置的复活点复活（大本营、据点Lv3均可作为复活点）
A17083: 700030113 | B17083: 1、玩家连续击败其他玩家达到对应数量后，获得debuff效果，百分比削弱最大生命、攻击、防御属性（每10min未再增加击败数，则击败数-1）：\n击败数【3-4】:玩家生命、攻击和防御各下降15%\n击败数【5-6】:玩家生命、攻击和防御各下降25%\n击败数【7-8】:玩家生命、攻击和防御各下降35%\n击败数【9-10】:玩家生命、攻击和防御各下降45%\n击败数【11-12】:玩家生命、攻击和防御各下降55%\n击败数【13-14】:玩家生命、攻击和防御各下降65%\n击败数【15-17】:玩家生命、攻击和防御各下降75%\n击败数【18-20】:玩家生命、攻击和防御各下降80%\n击败数【21-24】:玩家生命、攻击和防御各下降85%\n击败数【>24】:玩家生命、攻击和防御各下降90%
... A17696: 205682 | B17696: 使用完全升级，前提天赋也将升至最高等级，是否确定使用
