Workbook

Sheet out_language_en
A1: 0
A2: 语言总表
A3: 索引ID | B3: 内容 | C3: 中文，用于导出（不要在原表简转繁）
A4: 1*1 | B4: stack_error,n_list
A5: id | B5: text
A6: int | B6: string
A7: id | B7: text
A8: int | B8: ori_string
A9: 100001 | B9: T Backend Text-Only Mail Template | C9: T后台纯文本邮件模板 | D9: =VLOOKUP(A9,Sheet1!A:C,2,0) | E9: D列为简中语言表的文本，若CD列中文有冲突，以D列为准
A10: 100002 | B10: T Backend Text&Rewards Mail Template | C10: T后台文本+奖励邮件模板 | D10: =VLOOKUP(A10,Sheet1!A:C,2,0)
A11: 100003 | B11: Shroomie | C11: 菇勇者 | D11: =VLOOKUP(A11,Sheet1!A:C,2,0)
A12: 100004 | B12: Warrior | C12: 战士 | D12: =VLOOKUP(A12,Sheet1!A:C,2,0)
A13: 100005 | B13: Archer | C13: 弓箭手 | D13: =VLOOKUP(A13,Sheet1!A:C,2,0)
A14: 100006 | B14: Mage | C14: 法师 | D14: =VLOOKUP(A14,Sheet1!A:C,2,0)
A15: 100007 | B15: Swordsman | C15: 剑客 | D15: =VLOOKUP(A15,Sheet1!A:C,2,0)
A16: 100008 | B16: Axe Warrior | C16: 斧武士 | D16: =VLOOKUP(A16,Sheet1!A:C,2,0)
A17: 100009 | B17: Shadow Sniper | C17: 狙影猎手 | D17: =VLOOKUP(A17,Sheet1!A:C,2,0)
A18: 100010 | B18: Wind Crossbower | C18: 风弩手 | D18: =VLOOKUP(A18,Sheet1!A:C,2,0)
A19: 100011 | B19: Healer | C19: 愈灵师 | D19: =VLOOKUP(A19,Sheet1!A:C,2,0)
A20: 100012 | B20: Spellcaster | C20: 魔灵士 | D20: =VLOOKUP(A20,Sheet1!A:C,2,0)
A21: 100013 | B21: Claymore Wielder | C21: 大剑士 | D21: =VLOOKUP(A21,Sheet1!A:C,2,0)
... A4418: 200094 | B4418: Spend %s? | C4418: 是否消耗%s | D4418: =VLOOKUP(A4418,Sheet1!A:C,2,0)
A4419: 700024509 | B4419: Spend ##1*##2? | C4419: 是否消耗##1*##2
A4420: 200095 | B4420: Reforge | C4420: 重铸 | D4420: =VLOOKUP(A4420,Sheet1!A:C,2,0)
A4421: 200096 | B4421: <b><color=#544231>Milestone: Mileage reaches </color><color=#ab630e>%s</color></b> | C4421: <b><color=#544231>里程目标：里程值达到</color><color=#ab630e>%s</color></b> | D4421: =VLOOKUP(A4421,Sheet1!A:C,2,0)
A4422: 200097 | B4422: <b><color=#544231>Milestone: Complete event Dungeon </color><color=#ab630e>%s</color></b> | C4422: <b><color=#544231>里程目标：通关活动副本</color><color=#ab630e>%s</color></b> | D4422: =VLOOKUP(A4422,Sheet1!A:C,2,0)
A4423: 200098 | B4423: Deploy Effect: %s | C4423: 上阵效果：%s | D4423: =VLOOKUP(A4423,Sheet1!A:C,2,0)
A4424: 200099 | B4424: Base HP, ATK, DEF +%s% | C4424: 基础生命&攻击&防御+%s% | D4424: =VLOOKUP(A4424,Sheet1!A:C,2,0)
A4425: 200100 | B4425: No pals available for equipment | C4425: 没有可以装配的同伴 | D4425: =VLOOKUP(A4425,Sheet1!A:C,2,0)
A4426: 200101 | B4426: Unlock | C4426: 解锁 | D4426: =VLOOKUP(A4426,Sheet1!A:C,2,0)
A4427: 200102 | B4427: Event Duration: %s | C4427: 活动时间：%s | D4427: =VLOOKUP(A4427,Sheet1!A:C,2,0)
A4428: 200103 | B4428: Basic Attributes | C4428: 基础属性 | D4428: =VLOOKUP(A4428,Sheet1!A:C,2,0)
A4429: 200104 | B4429: Advanced Attributes | C4429: 高级属性 | D4429: =VLOOKUP(A4429,Sheet1!A:C,2,0)
A4430: 200105 | B4430: Final Attributes | C4430: 最终属性 | D4430: =VLOOKUP(A4430,Sheet1!A:C,2,0)
A4431: 200106 | B4431: Insufficient level | C4431: 等级不足 | D4431: =VLOOKUP(A4431,Sheet1!A:C,2,0)
... A4981: 200662 | B4981: Exchange | C4981: 兑换 | D4981: =VLOOKUP(A4981,Sheet1!A:C,2,0)
A4982: 200663 | B4982: 1 | C4982: 一 | D4982: =VLOOKUP(A4982,Sheet1!A:C,2,0)
A4983: 200664 | B4983: 2 | C4983: 二 | D4983: =VLOOKUP(A4983,Sheet1!A:C,2,0)
A4984: 200665 | B4984: 3 | C4984: 三 | D4984: =VLOOKUP(A4984,Sheet1!A:C,2,0)
A4985: 200666 | B4985: 4 | C4985: 四 | D4985: =VLOOKUP(A4985,Sheet1!A:C,2,0)
A4986: 200667 | B4986: 5 | C4986: 五 | D4986: =VLOOKUP(A4986,Sheet1!A:C,2,0)
A4987: 200668 | B4987: 6 | C4987: 六 | D4987: =VLOOKUP(A4987,Sheet1!A:C,2,0)
A4988: 200669 | B4988: 7 | C4988: 七 | D4988: =VLOOKUP(A4988,Sheet1!A:C,2,0)
A4989: 200670 | B4989: 8 | C4989: 八 | D4989: =VLOOKUP(A4989,Sheet1!A:C,2,0)
A4990: 200671 | B4990: 9 | C4990: 九 | D4990: =VLOOKUP(A4990,Sheet1!A:C,2,0)
A4991: 200672 | B4991: Handbook | C4991: 图鉴 | D4991: =VLOOKUP(A4991,Sheet1!A:C,2,0)
A4992: 200673 | B4992: Courage Challenges | C4992: 常规勇气挑战 | D4992: =VLOOKUP(A4992,Sheet1!A:C,2,0)
A4993: 200674 | B4993: Exclusive Battle Trial | C4993: 专属战斗试炼 | D4993: =VLOOKUP(A4993,Sheet1!A:C,2,0)
A4994: 200675 | B4994: Farm Experience | C4994: 农庄体验 | D4994: =VLOOKUP(A4994,Sheet1!A:C,2,0)
A4995: 200676 | B4995: Invited Tour | C4995: 特邀行程 | D4995: =VLOOKUP(A4995,Sheet1!A:C,2,0)
A4996: 200677 | B4996: World | C4996: 世界 | D4996: =VLOOKUP(A4996,Sheet1!A:C,2,0)
A4997: 200678 | B4997: Family | C4997: 家族 | D4997: =VLOOKUP(A4997,Sheet1!A:C,2,0)
A4998: 200679 | B4998: Private | C4998: 私聊 | D4998: =VLOOKUP(A4998,Sheet1!A:C,2,0)
A4999: 200680 | B4999: News | C4999: 新闻 | D4999: =VLOOKUP(A4999,Sheet1!A:C,2,0)
A5000: 200681 | B5000: Server Ranking | C5000: 服务器排名 | D5000: =VLOOKUP(A5000,Sheet1!A:C,2,0)
A5001: 200682 | B5001: Personal Ranking | C5001: 个人排名 | D5001: =VLOOKUP(A5001,Sheet1!A:C,2,0)
A5002: 200683 | B5002: Defense Ranking | C5002: 御敌排名 | D5002: =VLOOKUP(A5002,Sheet1!A:C,2,0)
... A5004: 200685 | B5004: DMG: %s | C5004: 伤害：%s | D5004: =VLOOKUP(A5004,Sheet1!A:C,2,0)
A5005: 200686 | B5005: 1 | C5005: 一个 | D5005: =VLOOKUP(A5005,Sheet1!A:C,2,0)
A5006: 200687 | B5006: 2 | C5006: 两个 | D5006: =VLOOKUP(A5006,Sheet1!A:C,2,0)
A5007: 200688 | B5007: 3 | C5007: 三个 | D5007: =VLOOKUP(A5007,Sheet1!A:C,2,0)
A5008: 200689 | B5008: 4 | C5008: 四个 | D5008: =VLOOKUP(A5008,Sheet1!A:C,2,0)
A5009: 200690 | B5009: 5 | C5009: 五个 | D5009: =VLOOKUP(A5009,Sheet1!A:C,2,0)
A5010: 200691 | B5010: 6 | C5010: 六个 | D5010: =VLOOKUP(A5010,Sheet1!A:C,2,0)
A5011: 200692 | B5011: 7 | C5011: 七个 | D5011: =VLOOKUP(A5011,Sheet1!A:C,2,0)
A5012: 200693 | B5012: 8 | C5012: 八个 | D5012: =VLOOKUP(A5012,Sheet1!A:C,2,0)
A5013: 200694 | B5013: 9 | C5013: 九个 | D5013: =VLOOKUP(A5013,Sheet1!A:C,2,0)
A5014: 200695 | B5014: 10 | C5014: 十个 | D5014: =VLOOKUP(A5014,Sheet1!A:C,2,0)
A5015: 200696 | B5015: Pickaxe | C5015: 镐子 | D5015: =VLOOKUP(A5015,Sheet1!A:C,2,0)
A5016: 200697 | B5016: Drill | C5016: 钻头 | D5016: =VLOOKUP(A5016,Sheet1!A:C,2,0)
A5017: 200698 | B5017: Bomb | C5017: 炸弹 | D5017: =VLOOKUP(A5017,Sheet1!A:C,2,0)
A5018: 200699 | B5018: Login server verification failed | C5018: 登录服校验失败 | D5018: =VLOOKUP(A5018,Sheet1!A:C,2,0)
A5019: 200700 | B5019: Platform login verification timeout | C5019: 平台登录验证超时 | D5019: =VLOOKUP(A5019,Sheet1!A:C,2,0)
A5020: 200701 | B5020: Platform login verification failed | C5020: 平台登录验证失败 | D5020: =VLOOKUP(A5020,Sheet1!A:C,2,0)
A5021: 200702 | B5021: Platform login verification encountered unknown error | C5021: 平台登录验证遇见不明错误 | D5021: =VLOOKUP(A5021,Sheet1!A:C,2,0)
A5022: 200703 | B5022: Server currently under maintenance | C5022: 服务器当前处于维护状态 | D5022: =VLOOKUP(A5022,Sheet1!A:C,2,0)
A5023: 200704 | B5023: Invalid Request | C5023: 错误的请求 | D5023: =VLOOKUP(A5023,Sheet1!A:C,2,0)
A5024: 200705 | B5024: Verification failed | C5024: 验证失败 | D5024: =VLOOKUP(A5024,Sheet1!A:C,2,0)
A5025: 200706 | B5025: Parameter error | C5025: 参数错误 | D5025: =VLOOKUP(A5025,Sheet1!A:C,2,0)
A5026: 200707 | B5026: Registration closed | C5026: 关闭注册 | D5026: =VLOOKUP(A5026,Sheet1!A:C,2,0)
... A5530: 201239 | B5530: Actions too frequent. Please try again later. | C5530: 操作过于频繁，请稍后再试 | D5530: =VLOOKUP(A5530,Sheet1!A:C,2,0)
A5531: 201240 | B5531: Strategic Chip | C5531: 策略筹码 | D5531: =VLOOKUP(A5531,Sheet1!A:C,2,0) | F5531: 4. Accumulate Remodel Points for mount enhancements; use Remodeling Guides for leveling.\n5. Longer parking results in extra adventure rewards with diverse mounts offering various bonuses.\n6. No additional earnings after parking for over 8 hours; collect rewards promptly.
A5532: 201241 | B5532: Strategy Points | C5532: 策略值 | D5532: =VLOOKUP(A5532,Sheet1!A:C,2,0) | F5532: 7. After parking for a full 12 hours daily, mounts earn Parking Coins at half the rate and no longer receive remodel points and adventure rewards.\n8. Spot owners receive 5% of total Parking Coin earnings without affecting the mount's owner.\n9. Each mount can be plundered only once. Successful plundering forces the mount to stop parking, and all participating players share a portion of the mount's Parking Coin earnings for that session.
A5533: 201242 | B5533: GG Bond's Friendship | C5533: 猪猪侠好感 | D5533: =VLOOKUP(A5533,Sheet1!A:C,2,0) | F5533: 10. Successful plundering accumulates a combat debuff stack, decreasing combat attributes. Reduce one stack every 30 min, and the refresh time increases with higher stacks. \n11. Cooldown after failed plunder; longer penalty for higher debuff stacks.\n12. No debuff when plundering own spots; no penalties after failed attempts.
A5534: 201243 | B5534: Spicy Strip | C5534: 辣条 | D5534: =VLOOKUP(A5534,Sheet1!A:C,2,0)
A5535: 201244 | B5535: Burger Hat | C5535: 汉堡帽子 | D5535: =VLOOKUP(A5535,Sheet1!A:C,2,0)
A5536: 201245 | B5536: Fried-egg Glasses | C5536: 煎蛋眼镜 | D5536: =VLOOKUP(A5536,Sheet1!A:C,2,0)
A5537: 201246 | B5537: Wizard Hat | C5537: 幽幽巫帽 | D5537: =VLOOKUP(A5537,Sheet1!A:C,2,0)
A5538: 201247 | B5538: Dragonic Resonance | C5538: 龙吟双声 | D5538: =VLOOKUP(A5538,Sheet1!A:C,2,0)
A5539: 201248 | B5539: Worldly Snare | C5539: 天下罗网 | D5539: =VLOOKUP(A5539,Sheet1!A:C,2,0)
A5540: 201249 | B5540: Star Array | C5540: 塔罗星阵 | D5540: =VLOOKUP(A5540,Sheet1!A:C,2,0)
A5541: 201250 | B5541: Bobby | C5541: 波比 | D5541: =VLOOKUP(A5541,Sheet1!A:C,2,0)
A5542: 201252 | B5542: Skyward Blade | C5542: 开天宝剑 | D5542: =VLOOKUP(A5542,Sheet1!A:C,2,0)
A5543: 201253 | B5543: Random Red Soul 1 | C5543: 随机红色武魂1 | D5543: =VLOOKUP(A5543,Sheet1!A:C,2,0)
A5544: 201254 | B5544: Flower Gate | C5544: 花门 | D5544: =VLOOKUP(A5544,Sheet1!A:C,2,0)
A5545: 201255 | B5545: Archway | C5545: 拱门 | D5545: =VLOOKUP(A5545,Sheet1!A:C,2,0)
... A5669: 201386 | B5669: Unable to teleport to this area. | C5669: 此区域无法传送 | D5669: =VLOOKUP(A5669,Sheet1!A:C,2,0)
A5670: 201387 | B5670: 1 | C5670: 一个 | D5670: =VLOOKUP(A5670,Sheet1!A:C,2,0)
A5671: 201388 | B5671: 2 | C5671: 两个 | D5671: =VLOOKUP(A5671,Sheet1!A:C,2,0)
A5672: 201389 | B5672: 3 | C5672: 三个 | D5672: =VLOOKUP(A5672,Sheet1!A:C,2,0)
...

Sheet Sheet1
A1: 0
A2: 语言总表
A3: 索引ID | B3: 内容
A4: 1*1 | B4: stack_error,n_list | C4: 外语查找用这列
A5: id | B5: text
A6: int | B6: string
A7: id | B7: text
A8: int | B8: ori_string
A9: 100001 | B9: T后台纯文本邮件模板 | C9: T后台纯文本邮件模板
A10: 100002 | B10: T后台文本+奖励邮件模板 | C10: T后台文本+奖励邮件模板
A11: 100003 | B11: 菇勇者 | C11: 菇勇者
A12: 100004 | B12: 战士 | C12: 战士
A13: 100005 | B13: 弓箭手 | C13: 弓箭手
A14: 100006 | B14: 法师 | C14: 法师
A15: 100007 | B15: 剑客 | C15: 剑客
A16: 100008 | B16: 斧武士 | C16: 斧武士
A17: 100009 | B17: 狙影猎手 | C17: 狙影猎手
A18: 100010 | B18: 风弩手 | C18: 风弩手
A19: 100011 | B19: 愈灵师 | C19: 愈灵师
A20: 100012 | B20: 魔灵士 | C20: 魔灵士
... A13293: 700000003 | B13293: 增加##1%暴击,笨尼攻击有##2%概率击飞目标##3秒 | C13293: 增加##1%暴击,笨尼攻击有##2%概率击飞目标##3秒
A13294: 700000002 | C13294: 悲伤蛙称号，不需要文字
A13295: 400080 | B13295: 待寻找 | C13295: 待寻找
A13296: 400534 | B13296: 当前难度开放满3天且通关时防御值为10解锁扫荡 | C13296: 当前难度开放满3天且通关时防御值为10解锁扫荡
A13297: 400535 | B13297: 通关当前难度且防御值为10时解锁扫荡 | C13297: 通关当前难度且防御值为10时解锁扫荡
A13298: 400536 | B13298: 悲伤蛙好感： | C13298: 悲伤蛙好感：
A13299: 400537 | B13299: 悲伤蛙宇宙 | C13299: 悲伤蛙宇宙
A13300: 400538 | B13300: 躲蛙蛙 | C13300: 躲蛙蛙
A13301: 400539 | B13301: 守卫佛系蛙 | C13301: 守卫佛系蛙
A13302: 400540 | B13302: 失眠蛙 | C13302: 失眠蛙
A13303: 400541 | B13303: 星球之旅 | C13303: 星球之旅
A13304: 400542 | B13304: 高光时刻 | C13304: 高光时刻
A13305: 400543 | B13305: 打爆不开心 | C13305: 打爆不开心
A13306: 400544 | B13306: 太空历险蛙 | C13306: 太空历险蛙
... A14889: 301877 | B14889: 1、每次进攻，都需消耗1点行动力\n2、发起进攻操作，玩家到达目标地块后进入进攻队列，按队列顺序先后挑战守军\n2、若进攻成功，进攻方击败了所有守军，则该地块的所有权变更\n3、若进攻失败，玩家阵亡，则玩家会在10分钟后在设置的复活点复活（大本营、据点Lv3均可作为复活点） | C14889: 1、每次进攻，都需消耗1点行动力\n2、发起进攻操作，玩家到达目标地块后进入进攻队列，按队列顺序先后挑战守军\n2、若进攻成功，进攻方击败了所有守军，则该地块的所有权变更\n3、若进攻失败，玩家阵亡，则玩家会在10分钟后在设置的复活点复活（大本营、据点Lv3均可作为复活点）
A14890: 301878
A14891: 301879 | B14891: 扫荡规则 | C14891: 扫荡规则
A14892: 301880 | B14892: 1、对已占领的资源地块，可进行扫荡操作\n2、每次扫荡将消耗1点行动力，扫荡时击败守军，可获得【PVE战功】及【铁锭】（同进攻操作） | C14892: 1、对已占领的资源地块，可进行扫荡操作\n2、每次扫荡将消耗1点行动力，扫荡时击败守军，可获得【PVE战功】及【铁锭】（同进攻操作）
A14893: 301881 | B14893: 防守规则 | C14893: 防守规则
A14894: 301882 | B14894: 1、驻守后将玩家算进该地块的防守队列\n2、驻守状态，每1分钟可恢复10%最大生命值的血量\n3、若防守成功，防守者击败了所有进攻者，则该地块的所有权维持原状\n4、若防守失败，所有防守者被击败，则地块归属权变更 | C14894: 1、驻守后将玩家算进该地块的防守队列\n2、驻守状态，每1分钟可恢复10%最大生命值的血量\n3、若防守成功，防守者击败了所有进攻者，则该地块的所有权维持原状\n4、若防守失败，所有防守者被击败，则地块归属权变更
A14895: 301883
A14896: 301884 | B14896: 复活规则 | C14896: 复活规则
A14897: 301885 | B14897: 1、被击败后，将于50分钟后在设置的复活点复活（大本营、据点Lv3均可设置为复活点）\n2、消耗【世界树晨露】道具可跳过复活时间，快速复活 | C14897: 1、被击败后，将于50分钟后在设置的复活点复活（大本营、据点Lv3均可设置为复活点）\n2、消耗【世界树晨露】道具可跳过复活时间，快速复活
A14898: 301886 | B14898: 撤退规则 | C14898: 撤退规则
A14899: 301887 | B14899: 1、战斗中可主动进行撤退\n2、未出首个战报前进行撤退，将返还本次进攻的行动力\n3、若已经进行了战斗且出了战报结果后进行撤退，将不返还行动力\n4、撤退过程中无法进行其他操作 | C14899: 1、战斗中可主动进行撤退\n2、未出首个战报前进行撤退，将返还本次进攻的行动力\n3、若已经进行了战斗且出了战报结果后进行撤退，将不返还行动力\n4、撤退过程中无法进行其他操作
A14900: 301888 | B14900: 战斗规则 | C14900: 战斗规则
A14901: 301889 | B14901: 0、以下所有公式中的局外属性，为去掉局外同伴的上阵效果后的值！！\n1、局内主角生命=【局内船只生命】*(1+局外基础生命加成百分比^0.6+【局内船只生命加成】)*(1+局外全局生命加成百分比)\n2、局内主角攻击力=【局内船只攻击】*(1+局外基础攻击加成百分比^0.6+【局内船只攻击加成】）*(1+局外全局攻击加成百分比）\n3、局内主角防御=【局内船只防御】*(1+局外基础防御加成百分比^0.6+【局内船只防御加成】)*(1+局外全局防御加成百分比)\n4、局内攻速 = 局外最终攻速（除同伴加成）\n5、局内主/副炮攻击力=【局内主角攻击】\n6、局内主/副炮攻速=【局内主角攻速】 +【船炮攻速加成】\n7、局内主炮伤害=(【局内主炮攻击】-【局内对手防御】) *【普攻系数】*【1-普攻减伤】*【1+船炮伤害比例】*【1 - 船炮减伤百分比】\n8、局内副炮伤害=(【局内副炮攻击】-【【局内对手防御】) *【普攻系数】*【1-普攻减伤】*【1+船炮伤害比例 】*【副炮伤害百分比】*【1-船炮减伤百分比】\n9、局内的船长【全局连击伤害】/【全局反击伤害】/【全局技能伤害】=局外的【全局连击伤害】^0.6/【全局反击伤害】^0.6/【全局技能伤害】^0.6\n10、局内的船长【普攻减伤】/【连击减伤】/【反击减伤】/【技能减伤】/【同伴减伤】属性数值=局外的【普攻减伤】* 0.7/【连击减伤】* 0.7/【反击减伤】* 0.7/【技能减伤】* 0.7/【同伴减伤】* 0.7 | C14901: 0、以下所有公式中的局外属性，为去掉局外同伴的上阵效果后的值！！\n1、局内主角生命=【局内船只生命】*(1+局外基础生命加成百分比^0.6+【局内船只生命加成】)*(1+局外全局生命加成百分比)\n2、局内主角攻击力=【局内船只攻击】*(1+局外基础攻击加成百分比^0.6+【局内船只攻击加成】）*(1+局外全局攻击加成百分比）\n3、局内主角防御=【局内船只防御】*(1+局外基础防御加成百分比^0.6+【局内船只防御加成】)*(1+局外全局防御加成百分比)\n4、局内攻速 = 局外最终攻速（除同伴加成）\n5、局内主/副炮攻击力=【局内主角攻击】\n6、局内主/副炮攻速=【局内主角攻速】 +【船炮攻速加成】\n7、局内主炮伤害=(【局内主炮攻击】-【局内对手防御】) *【普攻系数】*【1-普攻减伤】*【1+船炮伤害比例】*【1 - 船炮减伤百分比】\n8、局内副炮伤害=(【局内副炮攻击】-【【局内对手防御】) *【普攻系数】*【1-普攻减伤】*【1+船炮伤害比例 】*【副炮伤害百分比】*【1-船炮减伤百分比】\n9、局内的船长【全局连击伤害】/【全局反击伤害】/【全局技能伤害】=局外的【全局连击伤害】^0.6/【全局反击伤害】^0.6/【全局技能伤害】^0.6\n10、局内的船长【普攻减伤】/【连击减伤】/【反击减伤】/【技能减伤】/【同伴减伤】属性数值=局外的【普攻减伤】* 0.7/【连击减伤】* 0.7/【反击减伤】* 0.7/【技能减伤】* 0.7/【同伴减伤】* 0.7
A14902: 301890 | B14902: 平局规则 | C14902: 平局规则
A14903: 301891 | B14903: 1、若1场战斗后，双方未分出胜负（剩余血量均>0），则将保持上一场的血量继续战斗（上限为3场）\n2、连续战斗3场后仍然未分出胜负，则进攻方自动撤退回复活点 | C14903: 1、若1场战斗后，双方未分出胜负（剩余血量均>0），则将保持上一场的血量继续战斗（上限为3场）\n2、连续战斗3场后仍然未分出胜负，则进攻方自动撤退回复活点
A14904: 301892 | B14904: PVP伤害衰减 | C14904: PVP伤害衰减
A14905: 301893 | B14905: 1、PVP战斗中的所有伤害衰减、回血衰减等效果，在神秘海域的战斗中均生效 | C14905: 1、PVP战斗中的所有伤害衰减、回血衰减等效果，在神秘海域的战斗中均生效
A14906: 301894 | B14906: 赛季结算规则 | C14906: 赛季结算规则
A14907: 301895 | B14907: 1、赛季结束后，将保留【船身】的星级，其他的养成内容将在下赛季中全部重置\n2、赛季结算后，除了【白银船票】、【战功】兑换道具和所有【船身碎片】道具，所有赛季内的其他道具将被全部清除\n3、赛季结算后，将根据个人战功排名和服务器战功排名，结算赛季奖励\n4、赛季结算后，【战船抽奖】中的抽奖次数和保底次数不会被重置\n5、赛季结算后，【藏宝地】中的抽奖次数将被重置 | C14907: 1、赛季结束后，将保留【船身】的星级，其他的养成内容将在下赛季中全部重置\n2、赛季结算后，除了【白银船票】、【战功】兑换道具和所有【船身碎片】道具，所有赛季内的其他道具将被全部清除\n3、赛季结算后，将根据个人战功排名和服务器战功排名，结算赛季奖励\n4、赛季结算后，【战船抽奖】中的抽奖次数和保底次数不会被重置\n5、赛季结算后，【藏宝地】中的抽奖次数将被重置
... A17053: 600004366 | B17053: 3000K | C17053: 3000K
A17054: 600004367 | B17054: 10 | C17054: 10
A17055: 600004368 | B17055: 20 | C17055: 20
A17056: 600004369 | B17056: 50 | C17056: 50
A17057: 600004370 | B17057: 100 | C17057: 100
A17058: 600004371 | B17058: 200 | C17058: 200
A17059: 600004372 | B17059: 150 | C17059: 150
A17060: 600004373 | B17060: 500 | C17060: 500
A17061: 600004374 | B17061: 5 | C17061: 5
A17062: 600004375 | B17062: 30 | C17062: 30
A17063: 600004376 | B17063: 40 | C17063: 40
A17064: 600004377 | B17064: 1 | C17064: 1
A17065: 600004378 | B17065: 300 | C17065: 300
A17066: 600004379 | B17066: 50K | C17066: 50K
A17067: 600004380 | B17067: 150K | C17067: 150K
A17068: 600004381 | B17068: 3 | C17068: 3
A17069: 600004382 | B17069: 15 | C17069: 15
A17070: 600004383 | B17070: 7 | C17070: 7
A17071: 600004384 | B17071: 25 | C17071: 25
A17072: 700030102 | B17072: 骑羽令 | C17072: 骑羽令
A17073: 700030103 | B17073: 用于在冲刺商店中兑换坐骑和背饰 | C17073: 用于在冲刺商店中兑换坐骑和背饰
A17074: 700030104 | B17074: 同心 | C17074: 同心
A17075: 700030105 | B17075: 钟情 | C17075: 钟情
A17076: 700030106 | B17076: 烈焰啸天 | C17076: 烈焰啸天
A17077: 700030107 | B17077: 用于解锁坐骑烈焰啸天的道具 | C17077: 用于解锁坐骑烈焰啸天的道具
A17078: 700030108 | B17078: 解锁高级坐骑\n“烈焰啸天” | C17078: 解锁高级坐骑\n“烈焰啸天”
A17079: 700030109 | B17079: 狂风烈焰越千尺，亘古巨龙啸长空！恭喜~s解锁超级坐骑烈焰啸天！（全服同享礼盒待大佬发送） | C17079: 狂风烈焰越千尺，亘古巨龙啸长空！恭喜~s解锁超级坐骑烈焰啸天！（全服同享礼盒待大佬发送）
A17080: 700030110 | B17080: 每隔10秒造成##1%当前普攻范围伤害，并使目标受到灼烧，每秒受到##2%当前普攻伤害，持续至战斗结束，最多叠加3次；提高自身##3%攻击和防御，增加##4%减伤，持续至战斗结束，最多叠加3次。（战斗开始后立刻释放一次） | C17080: 每隔10秒造成##1%当前普攻范围伤害，并使目标受到灼烧，每秒受到##2%当前普攻伤害，持续至战斗结束，最多叠加3次；提高自身##3%攻击和防御，增加##4%减伤，持续至战斗结束，最多叠加3次。（战斗开始后立刻释放一次）
A17081: 700030111 | B17081: 玩家最大生命、攻击和防御各下降##1%，10分钟内没有增加击败数则击败数减一 | C17081: 玩家最大生命、攻击和防御各下降##1%，10分钟内没有增加击败数则击败数减一
A17082: 700030112 | B17082: 1、每次进攻，都需消耗1点行动力\n2、发起进攻操作，玩家到达目标地块后进入进攻队列，按队列顺序先后挑战守军\n2、若进攻成功，进攻方击败了所有守军，则该地块的所有权变更\n3、若进攻失败，玩家阵亡，则玩家会在50分钟后在设置的复活点复活（大本营、据点Lv3均可作为复活点） | C17082: 1、每次进攻，都需消耗1点行动力\n2、发起进攻操作，玩家到达目标地块后进入进攻队列，按队列顺序先后挑战守军\n2、若进攻成功，进攻方击败了所有守军，则该地块的所有权变更\n3、若进攻失败，玩家阵亡，则玩家会在50分钟后在设置的复活点复活（大本营、据点Lv3均可作为复活点）
A17083: 700030113 | B17083: 1、玩家连续击败其他玩家达到对应数量后，获得debuff效果，百分比削弱最大生命、攻击、防御属性（每10min未再增加击败数，则击败数-1）：\n击败数【3-4】:玩家生命、攻击和防御各下降15%\n击败数【5-6】:玩家生命、攻击和防御各下降25%\n击败数【7-8】:玩家生命、攻击和防御各下降35%\n击败数【9-10】:玩家生命、攻击和防御各下降45%\n击败数【11-12】:玩家生命、攻击和防御各下降55%\n击败数【13-14】:玩家生命、攻击和防御各下降65%\n击败数【15-17】:玩家生命、攻击和防御各下降75%\n击败数【18-20】:玩家生命、攻击和防御各下降80%\n击败数【21-24】:玩家生命、攻击和防御各下降85%\n击败数【>24】:玩家生命、攻击和防御各下降90% | C17083: 1、玩家连续击败其他玩家达到对应数量后，获得debuff效果，百分比削弱最大生命、攻击、防御属性（每10min未再增加击败数，则击败数-1）：\n击败数【3-4】:玩家生命、攻击和防御各下降15%\n击败数【5-6】:玩家生命、攻击和防御各下降25%\n击败数【7-8】:玩家生命、攻击和防御各下降35%\n击败数【9-10】:玩家生命、攻击和防御各下降45%\n击败数【11-12】:玩家生命、攻击和防御各下降55%\n击败数【13-14】:玩家生命、攻击和防御各下降65%\n击败数【15-17】:玩家生命、攻击和防御各下降75%\n击败数【18-20】:玩家生命、攻击和防御各下降80%\n击败数【21-24】:玩家生命、攻击和防御各下降85%\n击败数【>24】:玩家生命、攻击和防御各下降90%
... A17696: 205682 | B17696: 使用完全升级，前提天赋也将升至最高等级，是否确定使用 | C17696: 使用完全升级，前提天赋也将升至最高等级，是否确定使用

Sheet Sheet2
C14: Marry me please!
C15: 愿未来的岁月充满爱和快乐。
C16: 天作之合，缘聚两心！
C17: 彼此相爱，互敬互爱。
C18: 命运美好，奇迹即将降临！
C19: 你们就是童话中的王子和公主，愿你们幸福永远！
C20: 爱会找到出路~
C21: 一句话，一生情，一世爱，一杯酒。
C22: 祝愿你们的梦想成真，世界充满幸福和爱。
C23: 我们从未见过如此般配的两个人。
C24: 爱是最伟大的。
C25: 今天是你们新篇章的开始。向你们干杯！
... C33: 凡事都要心存爱心。
