Workbook

Sheet out_language_it
A1: 0
A2: 语言总表
A3: 索引ID | B3: 内容
A4: 1*1 | B4: stack_error,n_list
A5: id | B5: text
A6: int | B6: string
A7: id | B7: text
A8: int | B8: ori_string
A9: 100001 | B9: Modello di posta testuale per il backend T | C9: T后台纯文本邮件模板 | D9: =VLOOKUP(A9,Sheet1!A:B,2,0) | E9: D列为简中语言表的文本，若CD列中文有冲突，以D列为准
A10: 100002 | B10: Modello di posta delle ricompense + testo di backend T | C10: T后台文本+奖励邮件模板 | D10: =VLOOKUP(A10,Sheet1!A:B,2,0)
A11: 100003 | B11: Funghetto | C11: 菇勇者 | D11: =VLOOKUP(A11,Sheet1!A:B,2,0)
A12: 100004 | B12: Guerriero | C12: 战士 | D12: =VLOOKUP(A12,Sheet1!A:B,2,0)
A13: 100005 | B13: Arciere | C13: 弓箭手 | D13: =VLOOKUP(A13,Sheet1!A:B,2,0)
A14: 100006 | B14: Mago | C14: 法师 | D14: =VLOOKUP(A14,Sheet1!A:B,2,0)
A15: 100007 | B15: Spadaccino | C15: 剑客 | D15: =VLOOKUP(A15,Sheet1!A:B,2,0)
A16: 100008 | B16: Barbaro | C16: 斧武士 | D16: =VLOOKUP(A16,Sheet1!A:B,2,0)
A17: 100009 | B17: Cacciatore d'agguato | C17: 狙影猎手 | D17: =VLOOKUP(A17,Sheet1!A:B,2,0)
A18: 100010 | B18: Balestriere del Vento | C18: 风弩手 | D18: =VLOOKUP(A18,Sheet1!A:B,2,0)
A19: 100011 | B19: Guaritore | C19: 愈灵师 | D19: =VLOOKUP(A19,Sheet1!A:B,2,0)
A20: 100012 | B20: Incantatore | C20: 魔灵士 | D20: =VLOOKUP(A20,Sheet1!A:B,2,0)
A21: 100013 | B21: Maestro della Spada | C21: 大剑士 | D21: =VLOOKUP(A21,Sheet1!A:B,2,0)
... A4418: 200094 | B4418: Desideri utilizzare %s | C4418: 是否消耗%s | D4418: =VLOOKUP(A4418,Sheet1!A:B,2,0)
A4419: 700024509 | B4419: Desideri utilizzare ##1*##2 | C4419: 是否消耗##1*##2
A4420: 200095 | B4420: Fondi di nuovo | C4420: 重铸 | D4420: =VLOOKUP(A4420,Sheet1!A:B,2,0)
A4421: 200096 | B4421: <b><color=#544231>Obiettivo della via: ottieni i Punti miliari</color><color=#ab630e>%s</color></b> | C4421: <b><color=#544231>里程目标：里程值达到</color><color=#ab630e>%s</color></b> | D4421: =VLOOKUP(A4421,Sheet1!A:B,2,0)
A4422: 200097 | B4422: <b><color=#544231>Obiettivo della via: completa il dungeon dell'evento</color><color=#ab630e>%s</color></b> | C4422: <b><color=#544231>里程目标：通关活动副本</color><color=#ab630e>%s</color></b> | D4422: =VLOOKUP(A4422,Sheet1!A:B,2,0)
A4423: 200098 | B4423: Effetto sul Campo: %s | C4423: 上阵效果：%s | D4423: =VLOOKUP(A4423,Sheet1!A:B,2,0)
A4424: 200099 | B4424: Punti Vita di base & Attacco & Difesa +%s% | C4424: 基础生命&攻击&防御+%s% | D4424: =VLOOKUP(A4424,Sheet1!A:B,2,0)
A4425: 200100 | B4425: Non ci sono alleati da radunare | C4425: 没有可以装配的同伴 | D4425: =VLOOKUP(A4425,Sheet1!A:B,2,0)
A4426: 200101 | B4426: Sblocca | C4426: 解锁 | D4426: =VLOOKUP(A4426,Sheet1!A:B,2,0)
A4427: 200102 | B4427: Durata dell'Evento: %s | C4427: 活动时间：%s | D4427: =VLOOKUP(A4427,Sheet1!A:B,2,0)
A4428: 200103 | B4428: Caratteristiche di base | C4428: 基础属性 | D4428: =VLOOKUP(A4428,Sheet1!A:B,2,0)
A4429: 200104 | B4429: Caratteristiche avanzate | C4429: 高级属性 | D4429: =VLOOKUP(A4429,Sheet1!A:B,2,0)
A4430: 200105 | B4430: Caratteristiche ultime | C4430: 最终属性 | D4430: =VLOOKUP(A4430,Sheet1!A:B,2,0)
A4431: 200106 | B4431: Livello non sufficiente | C4431: 等级不足 | D4431: =VLOOKUP(A4431,Sheet1!A:B,2,0)
... A5529: 201236 | B5529: Felice Halloween! Queste sono le tue caramelle | C5529: 万圣节快乐!这是给你的糖果 | D5529: =VLOOKUP(A5529,Sheet1!A:B,2,0)
A5530: 201237 | B5530: Vuoi guardare una pubblicità per aumentare tutti le caratteristiche del 50%? | C5530: 是否观看广告，全属性提升50%？ | D5530: =VLOOKUP(A5530,Sheet1!A:B,2,0) | E5530: 4. Accumulate Remodel Points for mount enhancements; use Remodeling Guides for leveling.\n5. Longer parking results in extra adventure rewards with diverse mounts offering various bonuses.\n6. No additional earnings after parking for over 8 hours; collect rewards promptly.
A5531: 201239 | B5531: Operazione troppo frequente, riprovare più tardi | C5531: 操作过于频繁，请稍后再试 | D5531: =VLOOKUP(A5531,Sheet1!A:B,2,0) | E5531: 7. After parking for a full 12 hours daily, mounts earn Parking Coins at half the rate and no longer receive remodel points and adventure rewards.\n8. Spot owners receive 5% of total Parking Coin earnings without affecting the mount's owner.\n9. Each mount can be plundered only once. Successful plundering forces the mount to stop parking, and all participating players share a portion of the mount's Parking Coin earnings for that session.
A5532: 201240 | B5532: Fiches Tattiche | C5532: 策略筹码 | D5532: =VLOOKUP(A5532,Sheet1!A:B,2,0)
A5533: 201241 | B5533: Punti Tattici | C5533: 策略值 | D5533: =VLOOKUP(A5533,Sheet1!A:B,2,0)
A5534: 201242 | B5534: Affetto di GG Bond | C5534: 猪猪侠好感 | D5534: =VLOOKUP(A5534,Sheet1!A:B,2,0)
A5535: 201243 | B5535: Snack Piccante | C5535: 辣条 | D5535: =VLOOKUP(A5535,Sheet1!A:B,2,0)
A5536: 201244 | B5536: Cappello degli Hamburger | C5536: 汉堡帽子 | D5536: =VLOOKUP(A5536,Sheet1!A:B,2,0)
A5537: 201245 | B5537: Occhiali della Frittata | C5537: 煎蛋眼镜 | D5537: =VLOOKUP(A5537,Sheet1!A:B,2,0)
A5538: 201246 | B5538: Cappello da Stregone | C5538: 幽幽巫帽 | D5538: =VLOOKUP(A5538,Sheet1!A:B,2,0)
A5539: 201247 | B5539: Ruggito del Drago Doppio | C5539: 龙吟双声 | D5539: =VLOOKUP(A5539,Sheet1!A:B,2,0)
A5540: 201248 | B5540: Trappola nel Cielo | C5540: 天下罗网 | D5540: =VLOOKUP(A5540,Sheet1!A:B,2,0)
A5541: 201249 | B5541: Costellazione dei Tarocchi | C5541: 塔罗星阵 | D5541: =VLOOKUP(A5541,Sheet1!A:B,2,0)
A5542: 201250 | B5542: Poppy | C5542: 波比 | D5542: =VLOOKUP(A5542,Sheet1!A:B,2,0)
A5543: 201251 | B5543: Motocicletta Fiammeggiante | C5543: 烈焰摩托 | D5543: =VLOOKUP(A5543,Sheet1!A:B,2,0)
... A13184: 999300208 | B13184: Indizio %s | C13184: 线索 %s | D13184: =VLOOKUP(A13184,Sheet1!A:B,2,0)
A13185: 700000002 | D13185: =VLOOKUP(A13185,Sheet1!A:B,2,0)
A13186: 400080 | B13186: Da trovare | C13186: 待寻找 | D13186: =VLOOKUP(A13186,Sheet1!A:B,2,0)
A13187: 400534 | B13187: La difficoltà attuale è disponibile per un massimo di 3 giorni e sblocca la funzione di distruzione al termine del completamento con una difesa di 10 | C13187: 当前难度开放满3天且通关时防御值为10解锁扫荡 | D13187: =VLOOKUP(A13187,Sheet1!A:B,2,0)
A13188: 400535 | B13188: Sblocca la funzione di distruzione al completamento della difficoltà corrente con una difesa di 10 | C13188: 通关当前难度且防御值为10时解锁扫荡 | D13188: =VLOOKUP(A13188,Sheet1!A:B,2,0)
A13189: 400536 | B13189: Affetto del Pepe: | C13189: 悲伤蛙好感： | D13189: =VLOOKUP(A13189,Sheet1!A:B,2,0)
A13190: 400537 | B13190: Universo del Pepe | C13190: 悲伤蛙宇宙 | D13190: =VLOOKUP(A13190,Sheet1!A:B,2,0)
A13191: 400538 | B13191: Nascondi il Pepe | C13191: 躲蛙蛙 | D13191: =VLOOKUP(A13191,Sheet1!A:B,2,0)
A13192: 400539 | B13192: Difendi il Pepe Scansafatiche | C13192: 守卫佛系蛙 | D13192: =VLOOKUP(A13192,Sheet1!A:B,2,0)
A13193: 400540 | B13193: Pepe Insonne | C13193: 失眠蛙 | D13193: =VLOOKUP(A13193,Sheet1!A:B,2,0)
A13194: 400541 | B13194: Viaggio fra le Stelle | C13194: 星球之旅 | D13194: =VLOOKUP(A13194,Sheet1!A:B,2,0)
A13195: 400542 | B13195: Attimo di Gloria | C13195: 高光时刻 | D13195: =VLOOKUP(A13195,Sheet1!A:B,2,0)
A13196: 400543 | B13196: Tristezza al rogo! | C13196: 打爆不开心 | D13196: =VLOOKUP(A13196,Sheet1!A:B,2,0)
A13197: 400544 | B13197: Pepe Astronauta | C13197: 太空历险蛙 | D13197: =VLOOKUP(A13197,Sheet1!A:B,2,0)
... A14486: 301877 | B14486: 1. Ogni volta che si assalta, è necessario consumare 1 punto Azione.\n2. Avviando l'Assalto, il giocatore raggiunge l'area di destinazione e entra in coda d'attacco ed affronta le truppe difensive una dopo l'altra, secondo l'ordine di coda.\n3. Se l'attacco ha successo e il giocatore sconfigge tutti le truppe difensive, l'area viene conquistata.\n4. Se l'attacco fallisce e il giocatore muore, riprenderà il gioco presso il punto di Respawn impostato dopo 10 minuti (il Campo Base e le Fortezza di livello 3 possono essere usati come punti di Respawn). | C14486: 1、每次进攻，都需消耗1点行动力\n2、发起进攻操作，玩家到达目标地块后进入进攻队列，按队列顺序先后挑战守军\n2、若进攻成功，进攻方击败了所有守军，则该地块的所有权变更\n3、若进攻失败，玩家阵亡，则玩家会在10分钟后在设置的复活点复活（大本营、据点Lv3均可作为复活点） | D14486: =VLOOKUP(A14486,Sheet1!A:B,2,0)
A14487: 301878 | D14487: =VLOOKUP(A14487,Sheet1!A:B,2,0)
A14488: 301879 | B14488: Regole di Distruzione | C14488: 扫荡规则 | D14488: =VLOOKUP(A14488,Sheet1!A:B,2,0)
A14489: 301880 | B14489: 1. È possibile distruggere le Aree di Risorse già occupate. Ogni volta che si esegue questa operazione, si consuma 1 punto Azione.\n2. Durante lo distruzione, sconfiggendo le truppe difensive, si possono ottenere [Meriti di Guerra PVE] e [Lingotto di ferro] (come nelle operazioni di Assalto). | C14489: 1、对已占领的资源地块，可进行扫荡操作\n2、每次扫荡将消耗1点行动力，扫荡时击败守军，可获得【PVE战功】及【铁锭】（同进攻操作） | D14489: =VLOOKUP(A14489,Sheet1!A:B,2,0)
A14490: 301881 | B14490: Regole della Difesa | C14490: 防守规则 | D14490: =VLOOKUP(A14490,Sheet1!A:B,2,0)
A14491: 301882 | B14491: 1. Dopo aver difeso, i giocatori vengono inclusi nella coda di Difesa di quell'Area.\n2. Una volta schierati nella Difesa, verrà ripristinato il 10% dei PV massimi del giocatore ogni minuto.\n3. Se la difesa riesce e i truppe difensive sconfiggono tutti gli attaccanti, l'Area non viene conquistata.\n4. Se la difesa fallisce e tutti i difensori vengono sconfitti, Area viene conquistata e cambia di mano. | C14491: 1、驻守后将玩家算进该地块的防守队列\n2、驻守状态，每1分钟可恢复10%最大生命值的血量\n3、若防守成功，防守者击败了所有进攻者，则该地块的所有权维持原状\n4、若防守失败，所有防守者被击败，则地块归属权变更 | D14491: =VLOOKUP(A14491,Sheet1!A:B,2,0)
A14492: 301883 | D14492: =VLOOKUP(A14492,Sheet1!A:B,2,0)
A14493: 301884 | B14493: Regole del Respawn | C14493: 复活规则 | D14493: =VLOOKUP(A14493,Sheet1!A:B,2,0)
A14494: 301885 | B14494: 1. Dopo essere stati sconfitti, i giocatori riprendono a giocare dal punto di Respawn designato dopo 50 minuti (il Campo Base e le Fortezze di livello 3 possono essere impostati come punti di Respawn).\n2. L'uso dell'oggetto [Rugiada dell'Albero del Mondo] consente di evitare il tempo di Respawn, permettendo un Respawn rapido. | C14494: 1、被击败后，将于50分钟后在设置的复活点复活（大本营、据点Lv3均可设置为复活点）\n2、消耗【世界树晨露】道具可跳过复活时间，快速复活 | D14494: =VLOOKUP(A14494,Sheet1!A:B,2,0)
A14495: 301886 | B14495: Regole della Ritirata | C14495: 撤退规则 | D14495: =VLOOKUP(A14495,Sheet1!A:B,2,0)
A14496: 301887 | B14496: 1. Durante il combattimento è possibile ritirarsi volontariamente.\n2. Se ci si ritira prima che venga visualizzato il primo Resoconto della Battaglia, verrà restituita l'Azione utilizzata per l'Assalto.\n3. Se il combattimento è già iniziato e il Resoconto della Battaglia è già stato generato, ritirarsi non restituirà l'Azione utilizzata.\n4. Durante il ritiro non è possibile eseguire altre azioni. | C14496: 1、战斗中可主动进行撤退\n2、未出首个战报前进行撤退，将返还本次进攻的行动力\n3、若已经进行了战斗且出了战报结果后进行撤退，将不返还行动力\n4、撤退过程中无法进行其他操作 | D14496: =VLOOKUP(A14496,Sheet1!A:B,2,0)
A14497: 301888 | B14497: Regole di Battaglia | C14497: 战斗规则 | D14497: =VLOOKUP(A14497,Sheet1!A:B,2,0)
A14498: 301890 | B14498: Regole dei Pareggi | C14498: 平局规则 | D14498: =VLOOKUP(A14498,Sheet1!A:B,2,0)
A14499: 301891 | B14499: 1. Se dopo una battaglia nessuna delle due fazioni consegue la vittoria (i PV di entrambe le Navi sono maggiori di 0), i PV delle navi verranno mantenuti per la battaglia successiva (fino a un massimo di 3 battaglie).\n2. Se dopo tre battaglie consecutive non viene determinato un vincitore, la fazione attaccante si ritirerà automaticamente e tornerà al punto di Respawn. | C14499: 1、若1场战斗后，双方未分出胜负（剩余血量均>0），则将保持上一场的血量继续战斗（上限为3场）\n2、连续战斗3场后仍然未分出胜负，则进攻方自动撤退回复活点 | D14499: =VLOOKUP(A14499,Sheet1!A:B,2,0)
A14500: 301892 | B14500: Attenuazione dei Danni PVP | C14500: PVP伤害衰减 | D14500: =VLOOKUP(A14500,Sheet1!A:B,2,0)
A14501: 301893 | B14501: 1. Tutti gli effetti di riduzione del danno e di cura durante le battaglie PVP sono attivi anche durante le battaglie del Mare Misterioso. | C14501: 1、PVP战斗中的所有伤害衰减、回血衰减等效果，在神秘海域的战斗中均生效 | D14501: =VLOOKUP(A14501,Sheet1!A:B,2,0)
A14502: 301894 | B14502: Regole del Calcolo Stagionale | C14502: 赛季结算规则 | D14502: =VLOOKUP(A14502,Sheet1!A:B,2,0)
A14503: 301895 | B14503: 1. Al termine della stagione, le stelle possedute dagli [Scafi] verranno conservate, mentre gli altri progressi di sviluppo verranno resettati per la nuova stagione.\n2. Dopo il Calcolo Stagionale, tutti gli oggetti tranne [Biglietto Navale d'Argento], [Meriti di Guerra] ed i [Frammenti di Scafo] verranno rimossi.\n3. Al termine della stagione, verranno distribuite ricompense stagionali in base al posizionamento in classifica personale e del Server.\n4. Dopo il Calcolo Stagionale, i tentativi di estrazione ed il numero di estrazioni garantite relative alle [Estrazioni delle Navi da Guerra] non verranno resettati.\n5. Dopo il Calcolo Stagionale, i tentativi di estrazioni rimanenti della [Terra dei Tesori Nascosti] verranno resettati. | C14503: 1、赛季结束后，将保留【船身】的星级，其他的养成内容将在下赛季中全部重置\n2、赛季结算后，除了【白银船票】、【战功】兑换道具和所有【船身碎片】道具，所有赛季内的其他道具将被全部清除\n3、赛季结算后，将根据个人战功排名和服务器战功排名，结算赛季奖励\n4、赛季结算后，【战船抽奖】中的抽奖次数和保底次数不会被重置\n5、赛季结算后，【藏宝地】中的抽奖次数将被重置 | D14503: =VLOOKUP(A14503,Sheet1!A:B,2,0)
A14504: 301896 | B14504: Regole dei Meriti di Guerra PVE | C14504: PVE战功规则 | D14504: =VLOOKUP(A14504,Sheet1!A:B,2,0)
... A16304: 600004366 | B16304: 3000K | C16304: 3000K | D16304: =VLOOKUP(A16304,Sheet1!A:B,2,0)
A16305: 600004367 | B16305: 10 | C16305: 10 | D16305: =VLOOKUP(A16305,Sheet1!A:B,2,0)
A16306: 600004368 | B16306: 20 | C16306: 20 | D16306: =VLOOKUP(A16306,Sheet1!A:B,2,0)
A16307: 600004369 | B16307: 50 | C16307: 50 | D16307: =VLOOKUP(A16307,Sheet1!A:B,2,0)
A16308: 600004370 | B16308: 100 | C16308: 100 | D16308: =VLOOKUP(A16308,Sheet1!A:B,2,0)
A16309: 600004371 | B16309: 200 | C16309: 200 | D16309: =VLOOKUP(A16309,Sheet1!A:B,2,0)
A16310: 600004372 | B16310: 150 | C16310: 150 | D16310: =VLOOKUP(A16310,Sheet1!A:B,2,0)
A16311: 600004373 | B16311: 500 | C16311: 500 | D16311: =VLOOKUP(A16311,Sheet1!A:B,2,0)
A16312: 600004374 | B16312: 5 | C16312: 5 | D16312: =VLOOKUP(A16312,Sheet1!A:B,2,0)
A16313: 600004375 | B16313: 30 | C16313: 30 | D16313: =VLOOKUP(A16313,Sheet1!A:B,2,0)
A16314: 600004376 | B16314: 40 | C16314: 40 | D16314: =VLOOKUP(A16314,Sheet1!A:B,2,0)
A16315: 600004377 | B16315: 1 | C16315: 1 | D16315: =VLOOKUP(A16315,Sheet1!A:B,2,0)
A16316: 600004378 | B16316: 300 | C16316: 300 | D16316: =VLOOKUP(A16316,Sheet1!A:B,2,0)
A16317: 600004379 | B16317: 50K | C16317: 50K | D16317: =VLOOKUP(A16317,Sheet1!A:B,2,0)
A16318: 600004380 | B16318: 150K | C16318: 150K | D16318: =VLOOKUP(A16318,Sheet1!A:B,2,0)
A16319: 600004381 | B16319: 3 | C16319: 3 | D16319: =VLOOKUP(A16319,Sheet1!A:B,2,0)
A16320: 600004382 | B16320: 15 | C16320: 15 | D16320: =VLOOKUP(A16320,Sheet1!A:B,2,0)
...

Sheet Sheet1
A1: 0
A2: 语言总表
A3: 索引ID | B3: 内容
A4: 1*1 | B4: stack_error,n_list
A5: id | B5: text
A6: int | B6: string
A7: id | B7: text
A8: int | B8: ori_string
A9: 100001 | B9: T后台纯文本邮件模板
A10: 100002 | B10: T后台文本+奖励邮件模板
A11: 100003 | B11: 菇勇者
A12: 100004 | B12: 战士
A13: 100005 | B13: 弓箭手
A14: 100006 | B14: 法师
A15: 100007 | B15: 剑客
A16: 100008 | B16: 斧武士
A17: 100009 | B17: 狙影猎手
A18: 100010 | B18: 风弩手
A19: 100011 | B19: 愈灵师
A20: 100012 | B20: 魔灵士
... A13293: 700000003 | B13293: 增加##1%暴击,笨尼攻击有##2%概率击飞目标##3秒
A13294: 700000002
A13295: 400080 | B13295: 待寻找
A13296: 400534 | B13296: 当前难度开放满3天且通关时防御值为10解锁扫荡
A13297: 400535 | B13297: 通关当前难度且防御值为10时解锁扫荡
A13298: 400536 | B13298: 悲伤蛙好感：
A13299: 400537 | B13299: 悲伤蛙宇宙
A13300: 400538 | B13300: 躲蛙蛙
A13301: 400539 | B13301: 守卫佛系蛙
A13302: 400540 | B13302: 失眠蛙
A13303: 400541 | B13303: 星球之旅
A13304: 400542 | B13304: 高光时刻
A13305: 400543 | B13305: 打爆不开心
A13306: 400544 | B13306: 太空历险蛙
... A14889: 301877 | B14889: 1、每次进攻，都需消耗1点行动力\n2、发起进攻操作，玩家到达目标地块后进入进攻队列，按队列顺序先后挑战守军\n2、若进攻成功，进攻方击败了所有守军，则该地块的所有权变更\n3、若进攻失败，玩家阵亡，则玩家会在10分钟后在设置的复活点复活（大本营、据点Lv3均可作为复活点）
A14890: 301878
A14891: 301879 | B14891: 扫荡规则
A14892: 301880 | B14892: 1、对已占领的资源地块，可进行扫荡操作\n2、每次扫荡将消耗1点行动力，扫荡时击败守军，可获得【PVE战功】及【铁锭】（同进攻操作）
A14893: 301881 | B14893: 防守规则
A14894: 301882 | B14894: 1、驻守后将玩家算进该地块的防守队列\n2、驻守状态，每1分钟可恢复10%最大生命值的血量\n3、若防守成功，防守者击败了所有进攻者，则该地块的所有权维持原状\n4、若防守失败，所有防守者被击败，则地块归属权变更
A14895: 301883
A14896: 301884 | B14896: 复活规则
A14897: 301885 | B14897: 1、被击败后，将于50分钟后在设置的复活点复活（大本营、据点Lv3均可设置为复活点）\n2、消耗【世界树晨露】道具可跳过复活时间，快速复活
A14898: 301886 | B14898: 撤退规则
A14899: 301887 | B14899: 1、战斗中可主动进行撤退\n2、未出首个战报前进行撤退，将返还本次进攻的行动力\n3、若已经进行了战斗且出了战报结果后进行撤退，将不返还行动力\n4、撤退过程中无法进行其他操作
A14900: 301888 | B14900: 战斗规则
A14901: 301889 | B14901: 0、以下所有公式中的局外属性，为去掉局外同伴的上阵效果后的值！！\n1、局内主角生命=【局内船只生命】*(1+局外基础生命加成百分比^0.6+【局内船只生命加成】)*(1+局外全局生命加成百分比)\n2、局内主角攻击力=【局内船只攻击】*(1+局外基础攻击加成百分比^0.6+【局内船只攻击加成】）*(1+局外全局攻击加成百分比）\n3、局内主角防御=【局内船只防御】*(1+局外基础防御加成百分比^0.6+【局内船只防御加成】)*(1+局外全局防御加成百分比)\n4、局内攻速 = 局外最终攻速（除同伴加成）\n5、局内主/副炮攻击力=【局内主角攻击】\n6、局内主/副炮攻速=【局内主角攻速】 +【船炮攻速加成】\n7、局内主炮伤害=(【局内主炮攻击】-【局内对手防御】) *【普攻系数】*【1-普攻减伤】*【1+船炮伤害比例】*【1 - 船炮减伤百分比】\n8、局内副炮伤害=(【局内副炮攻击】-【【局内对手防御】) *【普攻系数】*【1-普攻减伤】*【1+船炮伤害比例 】*【副炮伤害百分比】*【1-船炮减伤百分比】\n9、局内的船长【全局连击伤害】/【全局反击伤害】/【全局技能伤害】=局外的【全局连击伤害】^0.6/【全局反击伤害】^0.6/【全局技能伤害】^0.6\n10、局内的船长【普攻减伤】/【连击减伤】/【反击减伤】/【技能减伤】/【同伴减伤】属性数值=局外的【普攻减伤】* 0.7/【连击减伤】* 0.7/【反击减伤】* 0.7/【技能减伤】* 0.7/【同伴减伤】* 0.7
A14902: 301890 | B14902: 平局规则
A14903: 301891 | B14903: 1、若1场战斗后，双方未分出胜负（剩余血量均>0），则将保持上一场的血量继续战斗（上限为3场）\n2、连续战斗3场后仍然未分出胜负，则进攻方自动撤退回复活点
A14904: 301892 | B14904: PVP伤害衰减
A14905: 301893 | B14905: 1、PVP战斗中的所有伤害衰减、回血衰减等效果，在神秘海域的战斗中均生效
A14906: 301894 | B14906: 赛季结算规则
A14907: 301895 | B14907: 1、赛季结束后，将保留【船身】的星级，其他的养成内容将在下赛季中全部重置\n2、赛季结算后，除了【白银船票】、【战功】兑换道具和所有【船身碎片】道具，所有赛季内的其他道具将被全部清除\n3、赛季结算后，将根据个人战功排名和服务器战功排名，结算赛季奖励\n4、赛季结算后，【战船抽奖】中的抽奖次数和保底次数不会被重置\n5、赛季结算后，【藏宝地】中的抽奖次数将被重置
... A17053: 600004366 | B17053: 3000K
A17054: 600004367 | B17054: 10
A17055: 600004368 | B17055: 20
A17056: 600004369 | B17056: 50
A17057: 600004370 | B17057: 100
A17058: 600004371 | B17058: 200
A17059: 600004372 | B17059: 150
A17060: 600004373 | B17060: 500
A17061: 600004374 | B17061: 5
A17062: 600004375 | B17062: 30
A17063: 600004376 | B17063: 40
A17064: 600004377 | B17064: 1
A17065: 600004378 | B17065: 300
A17066: 600004379 | B17066: 50K
A17067: 600004380 | B17067: 150K
A17068: 600004381 | B17068: 3
A17069: 600004382 | B17069: 15
A17070: 600004383 | B17070: 7
A17071: 600004384 | B17071: 25
A17072: 700030102 | B17072: 骑羽令
A17073: 700030103 | B17073: 用于在冲刺商店中兑换坐骑和背饰
A17074: 700030104 | B17074: 同心
A17075: 700030105 | B17075: 钟情
A17076: 700030106 | B17076: 烈焰啸天
A17077: 700030107 | B17077: 用于解锁坐骑烈焰啸天的道具
A17078: 700030108 | B17078: 解锁高级坐骑\n“烈焰啸天”
A17079: 700030109 | B17079: 狂风烈焰越千尺，亘古巨龙啸长空！恭喜~s解锁超级坐骑烈焰啸天！（全服同享礼盒待大佬发送）
A17080: 700030110 | B17080: 每隔10秒造成##1%当前普攻范围伤害，并使目标受到灼烧，每秒受到##2%当前普攻伤害，持续至战斗结束，最多叠加3次；提高自身##3%攻击和防御，增加##4%减伤，持续至战斗结束，最多叠加3次。（战斗开始后立刻释放一次）
A17081: 700030111 | B17081: 玩家最大生命、攻击和防御各下降##1%，10分钟内没有增加击败数则击败数减一
A17082: 700030112 | B17082: 1、每次进攻，都需消耗1点行动力\n2、发起进攻操作，玩家到达目标地块后进入进攻队列，按队列顺序先后挑战守军\n2、若进攻成功，进攻方击败了所有守军，则该地块的所有权变更\n3、若进攻失败，玩家阵亡，则玩家会在50分钟后在设置的复活点复活（大本营、据点Lv3均可作为复活点）
A17083: 700030113 | B17083: 1、玩家连续击败其他玩家达到对应数量后，获得debuff效果，百分比削弱最大生命、攻击、防御属性（每10min未再增加击败数，则击败数-1）：\n击败数【3-4】:玩家生命、攻击和防御各下降15%\n击败数【5-6】:玩家生命、攻击和防御各下降25%\n击败数【7-8】:玩家生命、攻击和防御各下降35%\n击败数【9-10】:玩家生命、攻击和防御各下降45%\n击败数【11-12】:玩家生命、攻击和防御各下降55%\n击败数【13-14】:玩家生命、攻击和防御各下降65%\n击败数【15-17】:玩家生命、攻击和防御各下降75%\n击败数【18-20】:玩家生命、攻击和防御各下降80%\n击败数【21-24】:玩家生命、攻击和防御各下降85%\n击败数【>24】:玩家生命、攻击和防御各下降90%
... A17696: 205682 | B17696: 使用完全升级，前提天赋也将升至最高等级，是否确定使用

Sheet Sheet2
C14: Marry me please!
C15: 愿未来的岁月充满爱和快乐。
C16: 天作之合，缘聚两心！
C17: 彼此相爱，互敬互爱。
C18: 命运美好，奇迹即将降临！
C19: 你们就是童话中的王子和公主，愿你们幸福永远！
C20: 爱会找到出路~
C21: 一句话，一生情，一世爱，一杯酒。
C22: 祝愿你们的梦想成真，世界充满幸福和爱。
C23: 我们从未见过如此般配的两个人。
C24: 爱是最伟大的。
C25: 今天是你们新篇章的开始。向你们干杯！
... C33: 凡事都要心存爱心。
