Workbook

Sheet out_language_tr
A1: 0
A2: 语言总表
A3: 索引ID | B3: 内容 | C3: 中文，用于导出（不要在原表简转繁）
A4: 1*1 | B4: stack_error,n_list
A5: id | B5: text
A6: int | B6: string
A7: id | B7: text
A8: int | B8: ori_string
A9: 100001 | B9: T Arka Planı Saf Metin E-posta Şablonu | C9: T后台纯文本邮件模板 | D9: =VLOOKUP(A9,Sheet1!A:B,2,0) | E9: D列为简中语言表的文本，若CD列中文有冲突，以D列为准
A10: 100002 | B10: T Arka Planı Metin+Ödül E-posta Şablonu | C10: T后台文本+奖励邮件模板 | D10: =VLOOKUP(A10,Sheet1!A:B,2,0)
A11: 100003 | B11: Kahraman Mantar | C11: 菇勇者 | D11: =VLOOKUP(A11,Sheet1!A:B,2,0)
A12: 100004 | B12: Savaşçı | C12: 战士 | D12: =VLOOKUP(A12,Sheet1!A:B,2,0)
A13: 100005 | B13: Okçu | C13: 弓箭手 | D13: =VLOOKUP(A13,Sheet1!A:B,2,0)
A14: 100006 | B14: Büyücü | C14: 法师 | D14: =VLOOKUP(A14,Sheet1!A:B,2,0)
A15: 100007 | B15: Kılıç Ustası | C15: 剑客 | D15: =VLOOKUP(A15,Sheet1!A:B,2,0)
A16: 100008 | B16: Baltalı Savaşçı | C16: 斧武士 | D16: =VLOOKUP(A16,Sheet1!A:B,2,0)
A17: 100009 | B17: Nişancı Avcısı | C17: 狙影猎手 | D17: =VLOOKUP(A17,Sheet1!A:B,2,0)
A18: 100010 | B18: Rüzgar Arbaletçisi | C18: 风弩手 | D18: =VLOOKUP(A18,Sheet1!A:B,2,0)
A19: 100011 | B19: Şifacı | C19: 愈灵师 | D19: =VLOOKUP(A19,Sheet1!A:B,2,0)
A20: 100012 | B20: Büyücü | C20: 魔灵士 | D20: =VLOOKUP(A20,Sheet1!A:B,2,0)
A21: 100013 | B21: Büyük Kılıçlı Savaşçı | C21: 大剑士 | D21: =VLOOKUP(A21,Sheet1!A:B,2,0)
... A4418: 200094 | B4418: %s tüketilsin mi? | C4418: 是否消耗%s | D4418: =VLOOKUP(A4418,Sheet1!A:B,2,0)
A4419: 700024509 | B4419: ##1*##2 tüketilsin mi? | C4419: 是否消耗##1*##2
A4420: 200095 | B4420: Yeniden döv | C4420: 重铸 | D4420: =VLOOKUP(A4420,Sheet1!A:B,2,0)
A4421: 200096 | B4421: <b><color=#544231>Mesafe Hedefi: Mesafe değeri</color> <color=#ab630e>%s sayısına ulaştı</color></b> | C4421: <b><color=#544231>里程目标：里程值达到</color><color=#ab630e>%s</color></b> | D4421: =VLOOKUP(A4421,Sheet1!A:B,2,0)
A4422: 200097 | B4422: <b><color=#544231>Mesafe Hedefi: Etkinlik zindanını geç</color> <color=#ab630e>%s</color></b> | C4422: <b><color=#544231>里程目标：通关活动副本</color><color=#ab630e>%s</color></b> | D4422: =VLOOKUP(A4422,Sheet1!A:B,2,0)
A4423: 200098 | B4423: Savaş Etkisi: %s | C4423: 上阵效果：%s | D4423: =VLOOKUP(A4423,Sheet1!A:B,2,0)
A4424: 200099 | B4424: Temel Sağlık & Saldırı & Savunma +%%s | C4424: 基础生命&攻击&防御+%s% | D4424: =VLOOKUP(A4424,Sheet1!A:B,2,0)
A4425: 200100 | B4425: Birleştirilecek dost yok | C4425: 没有可以装配的同伴 | D4425: =VLOOKUP(A4425,Sheet1!A:B,2,0)
A4426: 200101 | B4426: Kilidi Açık | C4426: 解锁 | D4426: =VLOOKUP(A4426,Sheet1!A:B,2,0)
A4427: 200102 | B4427: Etkinlik Zamanı: %s | C4427: 活动时间：%s | D4427: =VLOOKUP(A4427,Sheet1!A:B,2,0)
A4428: 200103 | B4428: Temel Özellik | C4428: 基础属性 | D4428: =VLOOKUP(A4428,Sheet1!A:B,2,0)
A4429: 200104 | B4429: Gelişmiş Özellikler | C4429: 高级属性 | D4429: =VLOOKUP(A4429,Sheet1!A:B,2,0)
A4430: 200105 | B4430: Nihai Özellikler | C4430: 最终属性 | D4430: =VLOOKUP(A4430,Sheet1!A:B,2,0)
A4431: 200106 | B4431: Seviye Yetersiz | C4431: 等级不足 | D4431: =VLOOKUP(A4431,Sheet1!A:B,2,0)
... A13200: 999300208 | B13200: %s ipucu | C13200: 线索 %s | D13200: =VLOOKUP(A13200,Sheet1!A:B,2,0)
A13201: 700000002 | C13201: 悲伤蛙称号，不需要文字 | D13201: =VLOOKUP(A13201,Sheet1!A:B,2,0)
A13202: 999000001 | B13202: ##1. Sıra | C13202: 第##1名 | D13202: =VLOOKUP(A13202,Sheet1!A:B,2,0)
A13203: 899000001 | B13203: Karakter 50. seviye | C13203: 角色50级 | D13203: =VLOOKUP(A13203,Sheet1!A:B,2,0)
A13204: 899000103 | B13204: Ekran donuyor, Sade Mod otomatik olarak açıldı | C13204: 画面卡顿，已自动为您开启精简模式 | D13204: =VLOOKUP(A13204,Sheet1!A:B,2,0)
A13205: 202255 | B13205: Sevgili Mantar, henüz alınmamış e-posta ödülleriniz mevcut, Mantar Kız bunları sizin için sakladı, lütfen kontrol edin~ | C13205: 亲爱的菇菇，您有未领取的到期邮件奖励，菇妹已为您保管，请注意查收哟~ | D13205: =VLOOKUP(A13205,Sheet1!A:B,2,0)
A13206: 600000001 | B13206: Dost Hasar Bonusu | C13206: 同伴伤害加成 | D13206: =VLOOKUP(A13206,Sheet1!A:B,2,0)
A13207: 202101 | B13207: %s. kata ulaş ve kilidi aç | C13207: 达到%s层解锁 | D13207: =VLOOKUP(A13207,Sheet1!A:B,2,0)
A13208: 700000001 | B13208: Her ##1 saniyede bir, hedefe ##2% mevcut saldırı menzili hasarı verilir ve hedef kargaşa durumuna düşer: Hedef her saldırı gerçekleştirdiğinde (normal saldırı, kombo saldırı, karşı saldırı, beceri), kendisine ek olarak ##3% mevcut saldırı hasarı verilir ve bu durum ##4 saniye sürer. (Savaş başladıktan hemen sonra bir kez salınır) | C13208: 每隔##1秒造成##2%当前普攻范围伤害，并使目标陷入混乱状态：目标每次攻击（普攻，连击，反击，技能）时会额外对自身造成##3%目标当前普攻伤害，持续##4秒。（战斗开始后立刻释放一次） | D13208: =VLOOKUP(A13208,Sheet1!A:B,2,0)
A13209: 400080 | B13209: Aranmayı bekliyor | C13209: 待寻找 | D13209: =VLOOKUP(A13209,Sheet1!A:B,2,0)
A13210: 400534 | B13210: Mevcut zorluk seviyesi 3 gün boyunca açık olacaktır ve tamamlandığında savunma değeri 10 olduğunda temizleme açılır | C13210: 当前难度开放满3天且通关时防御值为10解锁扫荡 | D13210: =VLOOKUP(A13210,Sheet1!A:B,2,0)
A13211: 400535 | B13211: Mevcut zorluk seviyesi tamamlandığında ve savunma değeri 10 olduğunda temizleme açılır | C13211: 通关当前难度且防御值为10时解锁扫荡 | D13211: =VLOOKUP(A13211,Sheet1!A:B,2,0)
A13212: 400536 | B13212: Pepe İlişkisi: | C13212: 悲伤蛙好感： | D13212: =VLOOKUP(A13212,Sheet1!A:B,2,0)
A13213: 400537 | B13213: Pepe Evreni | C13213: 悲伤蛙宇宙 | D13213: =VLOOKUP(A13213,Sheet1!A:B,2,0)
... A14632: 301877 | B14632: 1. Her saldırı için 1 hareket gücü tüketilir\n2. Saldırı işlemi başlatılır, oyuncular hedef bölgeye saldırı sırasına girer, sıraya göre savunmacılarla art arda mücadele ederler\n3. Saldırı başarılı olursa ve saldırgan tüm savunucuları yenerse, arazinin sahipliği değişir\n4. Eğer saldırı başarısız olur ve bir oyuncu öldürülürse, oyuncu 10 dakika sonra canlanma noktasında yeniden canlanacaktır (Ana kamp ve Kale Sv. 3 canlanma noktası olarak kullanılabilir) | C14632: 1、每次进攻，都需消耗1点行动力\n2、发起进攻操作，玩家到达目标地块后进入进攻队列，按队列顺序先后挑战守军\n2、若进攻成功，进攻方击败了所有守军，则该地块的所有权变更\n3、若进攻失败，玩家阵亡，则玩家会在10分钟后在设置的复活点复活（大本营、据点Lv3均可作为复活点） | D14632: =VLOOKUP(A14632,Sheet1!A:B,2,0)
A14633: 301878 | D14633: =VLOOKUP(A14633,Sheet1!A:B,2,0)
A14634: 301879 | B14634: Temizle Kuralları | C14634: 扫荡规则 | D14634: =VLOOKUP(A14634,Sheet1!A:B,2,0)
A14635: 301880 | B14635: 1. Temizleme işlemi işgal edilmiş kaynak arazileri için kullanılabilir\n2. Her temizleme 1 hareket gücü tüketir. Temizleme sırasında savunmacıları yenmek size [PVE Başarısı] ve [Demir Külçe] kazandırır (saldırı işlemi ile aynı) | C14635: 1、对已占领的资源地块，可进行扫荡操作\n2、每次扫荡将消耗1点行动力，扫荡时击败守军，可获得【PVE战功】及【铁锭】（同进攻操作） | D14635: =VLOOKUP(A14635,Sheet1!A:B,2,0)
A14636: 301881 | B14636: Savunma Kuralları | C14636: 防守规则 | D14636: =VLOOKUP(A14636,Sheet1!A:B,2,0)
A14637: 301882 | B14637: 1. Oyuncu orada konuşlandıktan sonra arazinin savunma sırasında sayılır\n2. Konuşlandırma Durumunda, her 1 dakikada bir maks sağlık değerinin %10'u kadar sağlık iyileştirilebilir\n3. Savunma başarılı olursa ve savunmacı tüm saldırganları yenerse, arazinin sahipliği değişmeden kalır\n4. Savunma başarısız olursa ve tüm savunmacılar yenilirse, arazinin sahipliği değişir | C14637: 1、驻守后将玩家算进该地块的防守队列\n2、驻守状态，每1分钟可恢复10%最大生命值的血量\n3、若防守成功，防守者击败了所有进攻者，则该地块的所有权维持原状\n4、若防守失败，所有防守者被击败，则地块归属权变更 | D14637: =VLOOKUP(A14637,Sheet1!A:B,2,0)
A14638: 301883 | D14638: =VLOOKUP(A14638,Sheet1!A:B,2,0)
A14639: 301884 | B14639: Canlanma Kuralları | C14639: 复活规则 | D14639: =VLOOKUP(A14639,Sheet1!A:B,2,0)
A14640: 301885 | B14640: 1. Yenildikten sonra, belirlenen canlanma noktasında 50 dakika sonra yeniden canlanırsınız (Ana Kamp ve Kale Sv. 3 canlanma noktası olarak ayarlanabilir)\n2. [Dünya Ağacı Çiğ Tanesi] eşyası tüketerek canlanma süresini atlayabilir ve hızla canlanabilirsiniz | C14640: 1、被击败后，将于50分钟后在设置的复活点复活（大本营、据点Lv3均可设置为复活点）\n2、消耗【世界树晨露】道具可跳过复活时间，快速复活 | D14640: =VLOOKUP(A14640,Sheet1!A:B,2,0)
A14641: 301886 | B14641: Geri Çekilme Kuralları | C14641: 撤退规则 | D14641: =VLOOKUP(A14641,Sheet1!A:B,2,0)
A14642: 301887 | B14642: 1. Savaş sırasında aktif geri çekilme yapılabilir\n2. İlk savaş raporundan önce yeniden savaşmak bu saldırının hareket gücünü iade eder\n3. Eğer savaş yapıldı ve savaş raporu çıkarıldıysa ve ardından geri çekilme yapılırsa, hareket gücü iade edilmeyecektir.\n4. Geri çekilme işlemi sırasında başka bir işlem yapılamaz | C14642: 1、战斗中可主动进行撤退\n2、未出首个战报前进行撤退，将返还本次进攻的行动力\n3、若已经进行了战斗且出了战报结果后进行撤退，将不返还行动力\n4、撤退过程中无法进行其他操作 | D14642: =VLOOKUP(A14642,Sheet1!A:B,2,0)
A14643: 301888 | B14643: Savaş Kuralları | C14643: 战斗规则 | D14643: =VLOOKUP(A14643,Sheet1!A:B,2,0)
A14644: 301890 | B14644: Beraberlik Kuralları | C14644: 平局规则 | D14644: =VLOOKUP(A14644,Sheet1!A:B,2,0)
A14645: 301891 | B14645: 1. Eğer 1 savaştan sonra her iki taraf da kazanan ve kaybeden olarak ayrılmamışsa (her ikisinin de kalan sağlığı > 0), savaşa devam etmek için önceki savaşın sağlık seviyesi korunacaktır (3 savaşla sınırlıdır)\n2. Art arda 3 savaştan sonra hala kazanan yoksa, saldıran taraf otomatik olarak canlanma noktasına geri çekilecektir. | C14645: 1、若1场战斗后，双方未分出胜负（剩余血量均>0），则将保持上一场的血量继续战斗（上限为3场）\n2、连续战斗3场后仍然未分出胜负，则进攻方自动撤退回复活点 | D14645: =VLOOKUP(A14645,Sheet1!A:B,2,0)
A14646: 301892 | B14646: PVP Hasar Düşüşü | C14646: PVP伤害衰减 | D14646: =VLOOKUP(A14646,Sheet1!A:B,2,0)
A14647: 301893 | B14647: 1. PVP savaşında tüm hasar azaltma, sağlık yenileme azalması gibi etkiler, Gizemli Denizlerdeki savaşlarda da etkilidir | C14647: 1、PVP战斗中的所有伤害衰减、回血衰减等效果，在神秘海域的战斗中均生效 | D14647: =VLOOKUP(A14647,Sheet1!A:B,2,0)
A14648: 301894 | B14648: Sezon Hesaplama Kuralları | C14648: 赛季结算规则 | D14648: =VLOOKUP(A14648,Sheet1!A:B,2,0)
A14649: 301895 | B14649: 1. Sezon sona erdikten sonra, [Gemi Gövdesi]'nin yıldız seviyesi korunacak ve diğer tüm gelişim içeriği bir sonraki sezonda sıfırlanacaktır\n2. Sezon hesaplamasından sonra, [Gümüş Gemi Bileti], [Başarı] takas eşyaları ve tüm [Gemi Gövde Parçası] eşyaları hariç, sezon içindeki diğer tüm eşyalar temizlenecektir\n3. Sezon hesaplamasının ardından, sezon ödülleri bireysel başarı sıralamasına ve sunucu başarı sıralamasına göre belirlenecektir\n4. Sezon hesaplamasından sonra, [Savaş Gemisi Çekilişi]'ndeki çekiliş hakı ve garanti edilen çekiliş sayısı sıfırlanmayacaktır\n5. Sezon hesaplamasından sonra, [Hazine Yeri]'ndeki çekiliş sayısı sıfırlanacaktır | C14649: 1、赛季结束后，将保留【船身】的星级，其他的养成内容将在下赛季中全部重置\n2、赛季结算后，除了【白银船票】、【战功】兑换道具和所有【船身碎片】道具，所有赛季内的其他道具将被全部清除\n3、赛季结算后，将根据个人战功排名和服务器战功排名，结算赛季奖励\n4、赛季结算后，【战船抽奖】中的抽奖次数和保底次数不会被重置\n5、赛季结算后，【藏宝地】中的抽奖次数将被重置 | D14649: =VLOOKUP(A14649,Sheet1!A:B,2,0)
A14650: 301896 | B14650: PVE Başarı Kuralları | C14650: PVE战功规则 | D14650: =VLOOKUP(A14650,Sheet1!A:B,2,0)
... A16312: 600004366 | B16312: 3000K | C16312: 3000K | D16312: =VLOOKUP(A16312,Sheet1!A:B,2,0)
A16313: 600004367 | B16313: 10 | C16313: 10 | D16313: =VLOOKUP(A16313,Sheet1!A:B,2,0)
A16314: 600004368 | B16314: 20 | C16314: 20 | D16314: =VLOOKUP(A16314,Sheet1!A:B,2,0)
A16315: 600004369 | B16315: 50 | C16315: 50 | D16315: =VLOOKUP(A16315,Sheet1!A:B,2,0)
A16316: 600004370 | B16316: 100 | C16316: 100 | D16316: =VLOOKUP(A16316,Sheet1!A:B,2,0)
A16317: 600004371 | B16317: 200 | C16317: 200 | D16317: =VLOOKUP(A16317,Sheet1!A:B,2,0)
A16318: 600004372 | B16318: 150 | C16318: 150 | D16318: =VLOOKUP(A16318,Sheet1!A:B,2,0)
A16319: 600004373 | B16319: 500 | C16319: 500 | D16319: =VLOOKUP(A16319,Sheet1!A:B,2,0)
A16320: 600004374 | B16320: 5 | C16320: 5 | D16320: =VLOOKUP(A16320,Sheet1!A:B,2,0)
A16321: 600004375 | B16321: 30 | C16321: 30 | D16321: =VLOOKUP(A16321,Sheet1!A:B,2,0)
A16322: 600004376 | B16322: 40 | C16322: 40 | D16322: =VLOOKUP(A16322,Sheet1!A:B,2,0)
A16323: 600004377 | B16323: 1 | C16323: 1 | D16323: =VLOOKUP(A16323,Sheet1!A:B,2,0)
A16324: 600004378 | B16324: 300 | C16324: 300 | D16324: =VLOOKUP(A16324,Sheet1!A:B,2,0)
A16325: 600004379 | B16325: 50K | C16325: 50K | D16325: =VLOOKUP(A16325,Sheet1!A:B,2,0)
A16326: 600004380 | B16326: 150K | C16326: 150K | D16326: =VLOOKUP(A16326,Sheet1!A:B,2,0)
A16327: 600004381 | B16327: 3 | C16327: 3 | D16327: =VLOOKUP(A16327,Sheet1!A:B,2,0)
A16328: 600004382 | B16328: 15 | C16328: 15 | D16328: =VLOOKUP(A16328,Sheet1!A:B,2,0)
A16329: 600004383 | B16329: 7 | C16329: 7 | D16329: =VLOOKUP(A16329,Sheet1!A:B,2,0)
A16330: 600004384 | B16330: 25 | C16330: 25 | D16330: =VLOOKUP(A16330,Sheet1!A:B,2,0)
A16331: 104454 | B16331: 1. Oyuncular, istiridye içindeki ödülleri almak için öğeler harcamalı ve istiridye kabuğunu açmalıdır.\n2. Büyük ödüller, seçilebilir ve seçilemez olmak üzere iki türdedir, seçilebilir büyük ödüllerin katlarında, oyuncular istedikleri kata karşılık gelen büyük ödülü seçebilirler, seçilemez büyük ödüllerin katlarında ise, oyuncular sadece belirlenen büyük ödül eşyalarını alabilirler. Her katın büyük ödülü kazanıldığında, o katın geri kalan tüm istiridye ödülleri oyuncuya verilir.\n3. Oyuncular 16. kata başarıyla ulaştıktan sonra, tek tıkla istiridye açma fonksiyonunu açabilirler\n4. Alınan deniz incisi eşyaları, mağazaya giderek ürünlerle takas edilebilir. | C16331: 1、玩家需要消耗道具打开蚌壳，获取蚌内的奖励\n2、大奖分为可自选和不可自选两种类型，可自选大奖的楼层中，玩家可以自主选择对应层数的大奖，而不可自选大奖的楼层中，玩家只能获得指定的大奖道具。砸中每层的大奖后，会将该层剩余所有其余蚌壳的奖励赠送给玩家\n3、玩家成功到达16层后，可以开启一键开蚌功能\n4、获取到的海珍珠道具还可以前往商店进行商品兑换 | D16331: =VLOOKUP(A16331,Sheet1!A:B,2,0)
A16332: 104455 | B16332: Serinletici Sörf Hediye Paketi Ⅰ | C16332: 冲浪解暑礼包Ⅰ | D16332: =VLOOKUP(A16332,Sheet1!A:B,2,0)
A16333: 104456 | B16333: Serinletici Sörf Hediye Paketi Ⅱ | C16333: 冲浪解暑礼包Ⅱ | D16333: =VLOOKUP(A16333,Sheet1!A:B,2,0)
A16334: 104457 | B16334: Serinletici Sörf Hediye Paketi Ⅲ | C16334: 冲浪解暑礼包Ⅲ | D16334: =VLOOKUP(A16334,Sheet1!A:B,2,0)
A16335: 104458 | B16335: Serinletici Sörf Hediye Paketi Ⅳ | C16335: 冲浪解暑礼包Ⅳ | D16335: =VLOOKUP(A16335,Sheet1!A:B,2,0)
A16336: 104459 | B16336: Serinletici Sörf Hediye Paketi Ⅴ | C16336: 冲浪解暑礼包Ⅴ | D16336: =VLOOKUP(A16336,Sheet1!A:B,2,0)
A16337: 104460 | B16337: Serinletici Sörf Hediye Paketi Ⅵ | C16337: 冲浪解暑礼包Ⅵ | D16337: =VLOOKUP(A16337,Sheet1!A:B,2,0)
A16338: 104461 | B16338: İstiridye Açma Hediye Paketi Ⅰ | C16338: 开蚌礼包Ⅰ | D16338: =VLOOKUP(A16338,Sheet1!A:B,2,0)
A16339: 104462 | B16339: İstiridye Açma Hediye Paketi Ⅱ | C16339: 开蚌礼包Ⅱ | D16339: =VLOOKUP(A16339,Sheet1!A:B,2,0)
A16340: 104463 | B16340: İstiridye Açma Hediye Paketi Ⅲ | C16340: 开蚌礼包Ⅲ | D16340: =VLOOKUP(A16340,Sheet1!A:B,2,0)
A16341: 104464 | B16341: İstiridye Açma Hediye Paketi Ⅳ | C16341: 开蚌礼包Ⅳ | D16341: =VLOOKUP(A16341,Sheet1!A:B,2,0)
A16342: 104465 | B16342: İstiridye Açma Hediye Paketi Ⅴ | C16342: 开蚌礼包Ⅴ | D16342: =VLOOKUP(A16342,Sheet1!A:B,2,0)
... A17253: 700030321 | B17253: Mücadele Aşamasında 60 sn. kal | C17253: 在挑战关卡中存活60秒 | D17253: =VLOOKUP(A17253,Sheet1!A:B,2,0)
...

Sheet Sheet1
A1: 0
A2: 语言总表
A3: 索引ID | B3: 内容
A4: 1*1 | B4: stack_error,n_list
A5: id | B5: text
A6: int | B6: string
A7: id | B7: text
A8: int | B8: ori_string
A9: 100001 | B9: T后台纯文本邮件模板
A10: 100002 | B10: T后台文本+奖励邮件模板
A11: 100003 | B11: 菇勇者
A12: 100004 | B12: 战士
A13: 100005 | B13: 弓箭手
A14: 100006 | B14: 法师
A15: 100007 | B15: 剑客
A16: 100008 | B16: 斧武士
A17: 100009 | B17: 狙影猎手
A18: 100010 | B18: 风弩手
A19: 100011 | B19: 愈灵师
A20: 100012 | B20: 魔灵士
... A13293: 700000003 | B13293: 增加##1%暴击,笨尼攻击有##2%概率击飞目标##3秒
A13294: 700000002
A13295: 400080 | B13295: 待寻找
A13296: 400534 | B13296: 当前难度开放满3天且通关时防御值为10解锁扫荡
A13297: 400535 | B13297: 通关当前难度且防御值为10时解锁扫荡
A13298: 400536 | B13298: 悲伤蛙好感：
A13299: 400537 | B13299: 悲伤蛙宇宙
A13300: 400538 | B13300: 躲蛙蛙
A13301: 400539 | B13301: 守卫佛系蛙
A13302: 400540 | B13302: 失眠蛙
A13303: 400541 | B13303: 星球之旅
A13304: 400542 | B13304: 高光时刻
A13305: 400543 | B13305: 打爆不开心
A13306: 400544 | B13306: 太空历险蛙
... A14889: 301877 | B14889: 1、每次进攻，都需消耗1点行动力\n2、发起进攻操作，玩家到达目标地块后进入进攻队列，按队列顺序先后挑战守军\n2、若进攻成功，进攻方击败了所有守军，则该地块的所有权变更\n3、若进攻失败，玩家阵亡，则玩家会在10分钟后在设置的复活点复活（大本营、据点Lv3均可作为复活点）
A14890: 301878
A14891: 301879 | B14891: 扫荡规则
A14892: 301880 | B14892: 1、对已占领的资源地块，可进行扫荡操作\n2、每次扫荡将消耗1点行动力，扫荡时击败守军，可获得【PVE战功】及【铁锭】（同进攻操作）
A14893: 301881 | B14893: 防守规则
A14894: 301882 | B14894: 1、驻守后将玩家算进该地块的防守队列\n2、驻守状态，每1分钟可恢复10%最大生命值的血量\n3、若防守成功，防守者击败了所有进攻者，则该地块的所有权维持原状\n4、若防守失败，所有防守者被击败，则地块归属权变更
A14895: 301883
A14896: 301884 | B14896: 复活规则
A14897: 301885 | B14897: 1、被击败后，将于50分钟后在设置的复活点复活（大本营、据点Lv3均可设置为复活点）\n2、消耗【世界树晨露】道具可跳过复活时间，快速复活
A14898: 301886 | B14898: 撤退规则
A14899: 301887 | B14899: 1、战斗中可主动进行撤退\n2、未出首个战报前进行撤退，将返还本次进攻的行动力\n3、若已经进行了战斗且出了战报结果后进行撤退，将不返还行动力\n4、撤退过程中无法进行其他操作
A14900: 301888 | B14900: 战斗规则
A14901: 301889 | B14901: 0、以下所有公式中的局外属性，为去掉局外同伴的上阵效果后的值！！\n1、局内主角生命=【局内船只生命】*(1+局外基础生命加成百分比^0.6+【局内船只生命加成】)*(1+局外全局生命加成百分比)\n2、局内主角攻击力=【局内船只攻击】*(1+局外基础攻击加成百分比^0.6+【局内船只攻击加成】）*(1+局外全局攻击加成百分比）\n3、局内主角防御=【局内船只防御】*(1+局外基础防御加成百分比^0.6+【局内船只防御加成】)*(1+局外全局防御加成百分比)\n4、局内攻速 = 局外最终攻速（除同伴加成）\n5、局内主/副炮攻击力=【局内主角攻击】\n6、局内主/副炮攻速=【局内主角攻速】 +【船炮攻速加成】\n7、局内主炮伤害=(【局内主炮攻击】-【局内对手防御】) *【普攻系数】*【1-普攻减伤】*【1+船炮伤害比例】*【1 - 船炮减伤百分比】\n8、局内副炮伤害=(【局内副炮攻击】-【【局内对手防御】) *【普攻系数】*【1-普攻减伤】*【1+船炮伤害比例 】*【副炮伤害百分比】*【1-船炮减伤百分比】\n9、局内的船长【全局连击伤害】/【全局反击伤害】/【全局技能伤害】=局外的【全局连击伤害】^0.6/【全局反击伤害】^0.6/【全局技能伤害】^0.6\n10、局内的船长【普攻减伤】/【连击减伤】/【反击减伤】/【技能减伤】/【同伴减伤】属性数值=局外的【普攻减伤】* 0.7/【连击减伤】* 0.7/【反击减伤】* 0.7/【技能减伤】* 0.7/【同伴减伤】* 0.7
A14902: 301890 | B14902: 平局规则
A14903: 301891 | B14903: 1、若1场战斗后，双方未分出胜负（剩余血量均>0），则将保持上一场的血量继续战斗（上限为3场）\n2、连续战斗3场后仍然未分出胜负，则进攻方自动撤退回复活点
A14904: 301892 | B14904: PVP伤害衰减
A14905: 301893 | B14905: 1、PVP战斗中的所有伤害衰减、回血衰减等效果，在神秘海域的战斗中均生效
A14906: 301894 | B14906: 赛季结算规则
A14907: 301895 | B14907: 1、赛季结束后，将保留【船身】的星级，其他的养成内容将在下赛季中全部重置\n2、赛季结算后，除了【白银船票】、【战功】兑换道具和所有【船身碎片】道具，所有赛季内的其他道具将被全部清除\n3、赛季结算后，将根据个人战功排名和服务器战功排名，结算赛季奖励\n4、赛季结算后，【战船抽奖】中的抽奖次数和保底次数不会被重置\n5、赛季结算后，【藏宝地】中的抽奖次数将被重置
... A17053: 600004366 | B17053: 3000K
A17054: 600004367 | B17054: 10
A17055: 600004368 | B17055: 20
A17056: 600004369 | B17056: 50
A17057: 600004370 | B17057: 100
A17058: 600004371 | B17058: 200
A17059: 600004372 | B17059: 150
A17060: 600004373 | B17060: 500
A17061: 600004374 | B17061: 5
A17062: 600004375 | B17062: 30
A17063: 600004376 | B17063: 40
A17064: 600004377 | B17064: 1
A17065: 600004378 | B17065: 300
A17066: 600004379 | B17066: 50K
A17067: 600004380 | B17067: 150K
A17068: 600004381 | B17068: 3
A17069: 600004382 | B17069: 15
A17070: 600004383 | B17070: 7
A17071: 600004384 | B17071: 25
A17072: 700030102 | B17072: 骑羽令
A17073: 700030103 | B17073: 用于在冲刺商店中兑换坐骑和背饰
A17074: 700030104 | B17074: 同心
A17075: 700030105 | B17075: 钟情
A17076: 700030106 | B17076: 烈焰啸天
A17077: 700030107 | B17077: 用于解锁坐骑烈焰啸天的道具
A17078: 700030108 | B17078: 解锁高级坐骑\n“烈焰啸天”
A17079: 700030109 | B17079: 狂风烈焰越千尺，亘古巨龙啸长空！恭喜~s解锁超级坐骑烈焰啸天！（全服同享礼盒待大佬发送）
A17080: 700030110 | B17080: 每隔10秒造成##1%当前普攻范围伤害，并使目标受到灼烧，每秒受到##2%当前普攻伤害，持续至战斗结束，最多叠加3次；提高自身##3%攻击和防御，增加##4%减伤，持续至战斗结束，最多叠加3次。（战斗开始后立刻释放一次）
A17081: 700030111 | B17081: 玩家最大生命、攻击和防御各下降##1%，10分钟内没有增加击败数则击败数减一
A17082: 700030112 | B17082: 1、每次进攻，都需消耗1点行动力\n2、发起进攻操作，玩家到达目标地块后进入进攻队列，按队列顺序先后挑战守军\n2、若进攻成功，进攻方击败了所有守军，则该地块的所有权变更\n3、若进攻失败，玩家阵亡，则玩家会在50分钟后在设置的复活点复活（大本营、据点Lv3均可作为复活点）
A17083: 700030113 | B17083: 1、玩家连续击败其他玩家达到对应数量后，获得debuff效果，百分比削弱最大生命、攻击、防御属性（每10min未再增加击败数，则击败数-1）：\n击败数【3-4】:玩家生命、攻击和防御各下降15%\n击败数【5-6】:玩家生命、攻击和防御各下降25%\n击败数【7-8】:玩家生命、攻击和防御各下降35%\n击败数【9-10】:玩家生命、攻击和防御各下降45%\n击败数【11-12】:玩家生命、攻击和防御各下降55%\n击败数【13-14】:玩家生命、攻击和防御各下降65%\n击败数【15-17】:玩家生命、攻击和防御各下降75%\n击败数【18-20】:玩家生命、攻击和防御各下降80%\n击败数【21-24】:玩家生命、攻击和防御各下降85%\n击败数【>24】:玩家生命、攻击和防御各下降90%
... A17696: 205682 | B17696: 使用完全升级，前提天赋也将升至最高等级，是否确定使用
